Workbook

Sheet ÍNDICE
B5: MATRIZ INSUMO-PRODUTO - 2021 (67 ATIVIDADES - PREÇOS CORRENTES)
B7: Tabela 1 - Recursos de bens e serviços
B8: Tabela 2 - Usos Totais a preços de consumidor
B9: Tabela 3 - Demanda da produção nacionais a preço básico
B10: Tabela 4 - Demanda de produtos importados a preço básico
B11: Tabela 5 - Destino dos impostos sobre produtos nacionais e importados (soma das Tabels 5 e 6 do SCN 2010, IBGE)
B12: Tabela 6 - Destino da margem de comércio sobre produtos nacionais e importados (soma das Tabels 7 e 8 do SCN 2010, IBGE)
B13: Tabela 7 - Destino da margem de transporte sobre produtos nacionais e importados (soma das Tabels 9 e 10 do SCN 2010, IBGE)
B14: Tabela 8 - Matriz dos coeficientes técnicos intersetoriais nacionais
B15: Tabela 9 - Matriz dos coeficientes técnicos intersetoriais importados
B16: Tabela 10 - Matriz de impacto intersetorial - Matriz de Leontief
B18: Referenciar como:
B19: ALVES-PASSONI, Patieene; FREITAS, Fabio. Como deflacionar matrizes insumo-produto? Uma proposta de uma série deflacionada para o Brasil no SCN 2010. Texto para Discussão, 030/2021, Instituto de Economia/IE, UFRJ. 2021. Disponível em: https://www.ie.ufrj.br/images/IE/TDS/2021/TD_IE_030_2021_PASSONI_FREITAS.pdf

Sheet Recursos
A1: Tabela 1 - Recursos de bens e serviços - 2021 (Preços correntes)
A2: Unidade de Medida: R$ 1.000.000,00
A3: Código da Atividade Nível 67 | B3: Descrição da Atividade Nível 67 | C3: Oferta de bens e serviços | L3: Produção das atividades | U3: Produção das atividades | AD3: Produção das atividades | AM3: Produção das atividades | AV3: Produção das atividades | BE3: Produção das atividades | BN3: Produção das atividades | CA3: Produção das atividades | CB3: Importação de bens e serviços (1)
C4: Oferta total a preço de consumidor | D4: Margem de comércio | E4: Margem de transporte | F4: Imposto de importação | G4: IPI | H4: ICMS | I4: Outros impostos menos subsídios | J4: Total de impostos líquidos de subsídios | K4: Oferta total a preço básico | L4: 0191 | M4: 0192 | N4: 0280 | O4: 0580 | P4: 0680 | Q4: 0791 | R4: 0792 | S4: 1091 | T4: 1092 | U4: 1093 | V4: 1100 | W4: 1200 | X4: 1300 | Y4: 1400 | Z4: 1500 | AA4: 1600 | AB4: 1700 | AC4: 1800 | AD4: 1991 | AE4: 1992 | AF4: 2091 | AG4: 2092 | AH4: 2093 | AI4: 2100 | AJ4: 2200 | AK4: 2300 | AL4: 2491 | AM4: 2492 | AN4: 2500 | AO4: 2600 | AP4: 2700 | AQ4: 2800 | AR4: 2991 | AS4: 2992 | AT4: 3000 | AU4: 3180 | AV4: 3300 | AW4: 3500 | AX4: 3680 | AY4: 4180 | AZ4: 4580 | BA4: 4900 | BB4: 5000 | BC4: 5100 | BD4: 5280 | BE4: 5500 | BF4: 5600 | BG4: 5800 | BH4: 5980 | BI4: 6100 | BJ4: 6280 | BK4: 6480 | BL4: 6800 | BM4: 6980 | BN4: 7180 | BO4: 7380 | BP4: 7700 | BQ4: 7880 | BR4: 8000 | BS4: 8400 | BT4: 8591 | BU4: 8592 | BV4: 8691 | BW4: 8692 | BX4: 9080 | BY4: 9480 | BZ4: 9700 | CA4: Total do produto
L5: Agricultura, inclusive o apoio à agricultura e a pós-colheita | M5: Pecuária, inclusive o apoio à pecuária | N5: Produção florestal; pesca e aquicultura | O5: Extração de carvão mineral e de minerais não metálicos | P5: Extração de petróleo e gás, inclusive as atividades de apoio | Q5: Extração de minério de ferro, inclusive beneficiamentos e a aglomeração | R5: Extração de minerais metálicos não ferrosos, inclusive beneficiamentos | S5: Abate e produtos de carne, inclusive os produtos do laticínio e da pesca | T5: Fabricação e refino de açúcar | U5: Outros produtos alimentares | V5: Fabricação de bebidas | W5: Fabricação de produtos do fumo | X5: Fabricação de produtos têxteis | Y5: Confecção de artefatos do vestuário e acessórios | Z5: Fabricação de calçados e de artefatos de couro | AA5: Fabricação de produtos da madeira | AB5: Fabricação de celulose, papel e produtos de papel | AC5: Impressão e reprodução de gravações | AD5: Refino de petróleo e coquerias | AE5: Fabricação de biocombustíveis | AF5: Fabricação de químicos orgânicos e inorgânicos, resinas e elastômeros | AG5: Fabricação de defensivos, desinfestantes, tintas e químicos diversos | AH5: Fabricação de produtos de limpeza, cosméticos/perfumaria e higiene pessoal | AI5: Fabricação de produtos farmoquímicos e farmacêuticos | AJ5: Fabricação de produtos de borracha e de material plástico | AK5: Fabricação de produtos de minerais não metálicos | AL5: Produção de ferro gusa/ferroligas, siderurgia e tubos de aço sem costura | AM5: Metalurgia de metais não ferosos e a fundição de metais | AN5: Fabricação de produtos de metal, exceto máquinas e equipamentos | AO5: Fabricação de equipamentos de informática, produtos eletrônicos e ópticos | AP5: Fabricação de máquinas e equipamentos elétricos | AQ5: Fabricação de máquinas e equipamentos mecânicos | AR5: Fabricação de automóveis, caminhões e ônibus, exceto peças | AS5: Fabricação de peças e acessórios para veículos automotores | AT5: Fabricação de outros equipamentos de transporte, exceto veículos automotores | AU5: Fabricação de móveis e de produtos de indústrias diversas | AV5: Manutenção, reparação e instalação de máquinas e equipamentos | AW5: Energia elétrica, gás natural e outras utilidades | AX5: Água, esgoto e gestão de resíduos | AY5: Construção | AZ5: Comércio por atacado e varejo | BA5: Transporte terrestre | BB5: Transporte aquaviário | BC5: Transporte aéreo | BD5: Armazenamento, atividades auxiliares dos transportes e correio | BE5: Alojamento | BF5: Alimentação | BG5: Edição e edição integrada à impressão | BH5: Atividades de televisão, rádio, cinema e gravação/edição de som e imagem | BI5: Telecomunicações | BJ5: Desenvolvimento de sistemas e outros serviços de informação | BK5: Intermediação financeira, seguros e previdência complementar | BL5: Atividades imobiliárias | BM5: Atividades jurídicas, contábeis, consultoria e sedes de empresas | BN5: Serviços de arquitetura, engenharia, testes/análises técnicas e P & D | BO5: Outras atividades profissionais, científicas e técnicas | BP5: Aluguéis não imobiliários e gestão de ativos de propriedade intelectual | BQ5: Outras atividades administrativas e serviços complementares | BR5: Atividades de vigilância, segurança e investigação | BS5: Administração pública, defesa e seguridade social | BT5: Educação pública | BU5: Educação privada | BV5: Saúde pública | BW5: Saúde privada | BX5: Atividades artísticas, criativas e de espetáculos | BY5: Organizações associativas e outros serviços pessoais | BZ5: Serviços domésticos
A6: 0191 | B6: Agricultura, inclusive o apoio à agricultura e a pós-colheita | C6: 906406.02 | D6: 84475.178 | E6: 16491.264 | F6: 345.45298 | G6: 101.53823 | H6: 6792.6681 | I6: 4222.2285 | J6: 11461.888 | K6: 793977.69 | L6: 721811.42 | M6: 35121.785 | N6: 2537.2217 | O6: 61.51842 | P6: 1.1610699 | Q6: 15.985026 | R6: 0 | S6: 396.34287 | T6: 171.41343 | U6: 2528.5604 | V6: 225.27517 | W6: 219.68728 | X6: 1795.1726 | Y6: 2.6284723 | Z6: 0.35085065 | AA6: 30.030951 | AB6: 1.3919555 | AC6: 0.79925413 | AD6: 0.18799358 | AE6: 73.608822 | AF6: 11.545733 | AG6: 1.3692319 | AH6: 0.28177697 | AI6: 0.44900395 | AJ6: 2.6162551 | AK6: 3.6771978 | AL6: 1.6664218 | AM6: 1.9415755 | AN6: 1.4091853 | AO6: 0.084991108 | AP6: 0.8009427 | AQ6: 0.13170808 | AR6: 0.081051123 | AS6: 0.60675771 | AT6: 0.051219807 | AU6: 4.5603799 | AV6: 0.033905816 | AW6: 7.18991 | AX6: 0.34052729 | AY6: 3002.0436 | AZ6: 405.96583 | BA6: 9.7467163 | BB6: 0.50600666 | BC6: 0.22176488 | BD6: 0.795877 | BE6: 38.732352 | BF6: 0.78799703 | BG6: 0.076548283 | BH6: 0.023077056 | BI6: 0.38330427 | BJ6: 0.30900741 | BK6: 5.1833319 | BL6: 118.71124 | BM6: 0.16829365 | BN6: 0.64334329 | BO6: 0.042214127 | BP6: 1.339595 | BQ6: 0.83696542 | BR6: 0.037711286 | BS6: 539.23097 | BT6: 0.095901889 | BU6: 0.23471054 | BV6: 0.00056285502 | BW6: 0.24990763 | BX6: 0.11482242 | BY6: 0.13564806 | BZ6: 0 | CA6: 769160 | CB6: 24817.685
A7: 0192 | B7: Pecuária, inclusive o apoio à pecuária | C7: 309970.73 | D7: 25288.404 | E7: 2182.3848 | F7: 58.314471 | G7: 75.061713 | H7: 4744.891 | I7: 3159.7606 | J7: 8038.0277 | K7: 274461.92 | L7: 35121.785 | M7: 222563.47 | N7: 3692.2261 | O7: 323.91158 | P7: 2.257212 | Q7: 29.150193 | R7: 0 | S7: 2452.7868 | T7: 66.62461 | U7: 787.12555 | V7: 279.75752 | W7: 120.63196 | X7: 836.81393 | Y7: 1.2322372 | Z7: 0.77647319 | AA7: 21.927141 | AB7: 0.81340173 | AC7: 0.46091956 | AD7: 0.10841347 | AE7: 20.188335 | AF7: 7.8707797 | AG7: 1.3074815 | AH7: 0.45142952 | AI7: 0.41035411 | AJ7: 1.4826292 | AK7: 15.211836 | AL7: 1.0578168 | AM7: 1.1949804 | AN7: 0.82259023 | AO7: 0.049013277 | AP7: 0.46189333 | AQ7: 0.07595435 | AR7: 0.046741138 | AS7: 0.34990936 | AT7: 0.029537803 | AU7: 2.1935904 | AV7: 0.020014964 | AW7: 4.1463285 | AX7: 0.1963777 | AY7: 5497.2756 | AZ7: 96.790489 | BA7: 17.580553 | BB7: 0.29180752 | BC7: 0.12788895 | BD7: 0.45897201 | BE7: 130.52953 | BF7: 0.45442774 | BG7: 0.044144409 | BH7: 0.013308241 | BI7: 0.22104663 | BJ7: 0.17820059 | BK7: 2.9891607 | BL7: 68.461464 | BM7: 0.097052781 | BN7: 0.37100779 | BO7: 0.024344343 | BP7: 0.77252715 | BQ7: 0.48266717 | BR7: 0.021747613 | BS7: 63.846503 | BT7: 0.12048814 | BU7: 0.13535455 | BV7: 0.00032459124 | BW7: 0.14411851 | BX7: 0.066216613 | BY7: 0.078226489 | BZ7: 0 | CA7: 272241 | CB7: 2220.9155
A8: 0280 | B8: Produção florestal; pesca e aquicultura | C8: 73945.687 | D8: 8002.165 | E8: 879.16787 | F8: 89.609382 | G8: 0.95910902 | H8: 3658.1609 | I8: 740.55635 | J8: 4489.2858 | K8: 60575.069 | L8: 2537.2217 | M8: 3692.2261 | N8: 47465.894 | O8: 25.694112 | P8: 0.038783309 | Q8: 2.1300456 | R8: 0 | S8: 23.495002 | T8: 4.4642044 | U8: 320.11333 | V8: 7.6584262 | W8: 0.98101925 | X8: 4.8539117 | Y8: 0.011586492 | Z8: 0.0075975123 | AA8: 5.9373806 | AB8: 0.11143831 | AC8: 0.058840795 | AD8: 0.013840018 | AE8: 4.5697123 | AF8: 0.67014336 | AG8: 0.18555402 | AH8: 0.0091351719 | AI8: 0.039795125 | AJ8: 0.13939015 | AK8: 1.2313329 | AL8: 0.12978536 | AM8: 0.14846341 | AN8: 0.11175609 | AO8: 0.0062570141 | AP8: 0.058965106 | AQ8: 0.0096963 | AR8: 0.0059669538 | AS8: 0.04466928 | AT8: 0.0037707833 | AU8: 0.047524773 | AV8: 0.0028688027 | AW8: 0.52931853 | AX8: 0.025069494 | AY8: 397.80955 | AZ8: 20.745129 | BA8: 198.90445 | BB8: 0.037252024 | BC8: 0.016326249 | BD8: 0.058592172 | BE8: 15.470529 | BF8: 0.058012051 | BG8: 0.0056354564 | BH8: 0.0016989244 | BI8: 0.028218719 | BJ8: 0.022749012 | BK8: 0.38159499 | BL8: 8.7395758 | BM8: 0.012389717 | BN8: 0.047362696 | BO8: 0.0031077885 | BP8: 0.098620487 | BQ8: 0.061617086 | BR8: 0.002776291 | BS8: 1.545399 | BT8: 0.014662833 | BU8: 0.017279304 | BV8: 4.143718e-05 | BW8: 0.018398108 | BX8: 0.0084531846 | BY8: 0.0099863603 | BZ8: 0 | CA8: 54743 | CB8: 5832.0688
A9: 0580 | B9: Extração de carvão mineral e de minerais não metálicos | C9: 62551.128 | D9: 4643.3001 | E9: 3771.6966 | F9: 51.112909 | G9: 6.1642404 | H9: 1764.5799 | I9: 555.17428 | J9: 2377.0314 | K9: 51759.1 | L9: 61.51842 | M9: 323.91158 | N9: 25.694112 | O9: 26274.217 | P9: 20.825161 | Q9: 1.4524874 | R9: 117.67863 | S9: 5.7206928 | T9: 0.18658425 | U9: 284.59871 | V9: 0.4613504 | W9: 0.026445887 | X9: 0.95401771 | Y9: 0.044688675 | Z9: 0.090109131 | AA9: 0.19662951 | AB9: 0.72468214 | AC9: 0.25718788 | AD9: 0.38102285 | AE9: 0.11566899 | AF9: 335.79294 | AG9: 36.385555 | AH9: 1.5487599 | AI9: 1.5402441 | AJ9: 8.5813058 | AK9: 1819.211 | AL9: 11.652292 | AM9: 308.04369 | AN9: 6.570851 | AO9: 0.97964062 | AP9: 3.7152266 | AQ9: 14.759996 | AR9: 0.48281006 | AS9: 4.0674004 | AT9: 0.36878286 | AU9: 3.7061277 | AV9: 9.9478128 | AW9: 2.3004177 | AX9: 0.11254061 | AY9: 0.58900985 | AZ9: 320.97699 | BA9: 0.49062924 | BB9: 0.15521677 | BC9: 0.068742441 | BD9: 0.25014691 | BE9: 0.021747741 | BF9: 0.23852562 | BG9: 0.029054176 | BH9: 0.0073610717 | BI9: 0.24624158 | BJ9: 0.78649971 | BK9: 1.6186209 | BL9: 36.413957 | BM9: 0.052524753 | BN9: 1.5483024 | BO9: 0.013285612 | BP9: 0.75490389 | BQ9: 0.26913539 | BR9: 0.013174363 | BS9: 23.526482 | BT9: 3.2339423 | BU9: 0.26529905 | BV9: 0.44019421 | BW9: 0.082664326 | BX9: 0.036003135 | BY9: 0.049175506 | BZ9: 0 | CA9: 30081 | CB9: 21678.1
A10: 0680 | B10: Extração de petróleo e gás, inclusive as atividades de apoio | C10: 464886.06 | D10: 529.94494 | E10: 1316.0515 | F10: 19.668928 | G10: 7.7416885 | H10: 169.48489 | I10: 6317.3711 | J10: 6514.2666 | K10: 456525.79 | L10: 1.1610699 | M10: 2.257212 | N10: 0.038783309 | O10: 20.825161 | P10: 366005.05 | Q10: 168.34829 | R10: 0.016420659 | S10: 0.90561326 | T10: 2.2256718 | U10: 2.7632161 | V10: 3.0186013 | W10: 0.15200345 | X10: 1.1058343 | Y10: 0.41082993 | Z10: 0.50743298 | AA10: 2.1807082 | AB10: 9.1212424 | AC10: 3.001638 | AD10: 3874.9964 | AE10: 0.49229216 | AF10: 122.33329 | AG10: 11.58188 | AH10: 2.4940661 | AI10: 2.5113714 | AJ10: 8.7751739 | AK10: 5.5627849 | AL10: 9.5539989 | AM10: 8.3210204 | AN10: 110.03566 | AO10: 19.112275 | AP10: 10.770648 | AQ10: 334.57366 | AR10: 4.9437445 | AS10: 11.457354 | AT10: 3.3794653 | AU10: 3.3463294 | AV10: 34.527075 | AW10: 25.455258 | AX10: 1.2255612 | AY10: 34998.192 | AZ10: 361.86888 | BA10: 5.3493396 | BB10: 1.7570538 | BC10: 0.77005473 | BD10: 2.9214303 | BE10: 0.23844334 | BF10: 2.7362351 | BG10: 0.29413954 | BH10: 0.080132599 | BI10: 1.9272256 | BJ10: 4.7921979 | BK10: 18.15132 | BL10: 412.206 | BM10: 0.58438164 | BN10: 10.003604 | BO10: 0.14658402 | BP10: 5.9112466 | BQ10: 2.9641722 | BR10: 0.13094839 | BS10: 18.129278 | BT10: 17.354681 | BU10: 1.8337937 | BV10: 2.3487361 | BW10: 0.89980698 | BX10: 0.39870854 | BY10: 0.47102333 | BZ10: 0 | CA10: 406701 | CB10: 49824.793
A11: 0791 | B11: Extração de minério de ferro, inclusive beneficiamentos e a aglomeração | C11: 311419.15 | D11: 27293.255 | E11: 3515.4322 | F11: 13.671903 | G11: 2.3427919 | H11: 8.8802528 | I11: 885.34166 | J11: 910.23661 | K11: 279700.23 | L11: 15.985026 | M11: 29.150193 | N11: 2.1300456 | O11: 1.4524874 | P11: 168.34829 | Q11: 275440.29 | R11: 245.42252 | S11: 1.0239194 | T11: 1.2106751 | U11: 1.304692 | V11: 0.22171541 | W11: 0.34215122 | X11: 0.32964651 | Y11: 0.36683666 | Z11: 1.4591713 | AA11: 0.28865406 | AB11: 2.4453105 | AC11: 0.17249884 | AD11: 0.01737367 | AE11: 0.1280216 | AF11: 33.162112 | AG11: 5.3191102 | AH11: 2.065801 | AI11: 5.0950622 | AJ11: 4.5524631 | AK11: 3.6073404 | AL11: 1028.4021 | AM11: 161.10516 | AN11: 5.2117809 | AO11: 11.560931 | AP11: 7.4797449 | AQ11: 140.58944 | AR11: 7.297535 | AS11: 7.661001 | AT11: 4.8173711 | AU11: 1.7593228 | AV11: 1.2050461 | AW11: 2.0229243 | AX11: 0.1603469 | AY11: 1597.306 | AZ11: 5.8871314 | BA11: 0.0945113 | BB11: 0.031043354 | BC11: 0.013605207 | BD11: 0.11307034 | BE11: 0.0042127799 | BF11: 0.048343376 | BG11: 0.096338499 | BH11: 0.0014157703 | BI11: 1.951988 | BJ11: 11.480303 | BK11: 0.81206727 | BL11: 7.2827915 | BM11: 0.010324764 | BN11: 23.206742 | BO11: 0.0025898237 | BP11: 0.40093951 | BQ11: 0.23861659 | BR11: 0.0023135759 | BS11: 38.494659 | BT11: 55.320535 | BU11: 3.3095372 | BV11: 7.5904064 | BW11: 0.11892738 | BX11: 0.0070443205 | BY11: 0.0083219669 | BZ11: 0 | CA11: 279099 | CB11: 601.22756
A12: 0792 | B12: Extração de minerais metálicos não ferrosos, inclusive beneficiamentos | C12: 42086.821 | D12: 3573.7623 | E12: 1371.6594 | F12: 18.603938 | G12: 3.442771 | H12: 33.122103 | I12: 598.88182 | J12: 654.05063 | K12: 36487.349 | L12: 0 | M12: 0 | N12: 0 | O12: 117.67863 | P12: 0.016420659 | Q12: 245.42252 | R12: 28652.189 | S12: 0.067053179 | T12: 0.035156297 | U12: 0.13907913 | V12: 0.019611152 | W12: 0.017999922 | X12: 0.66114996 | Y12: 0.018761829 | Z12: 0.077861006 | AA12: 0.012763805 | AB12: 0.60696308 | AC12: 0.0034730953 | AD12: 0.021857426 | AE12: 0.0019667848 | AF12: 47.513671 | AG12: 1.4876058 | AH12: 0.29377771 | AI12: 0.28066949 | AJ12: 6.1199924 | AK12: 25.21126 | AL12: 40.39905 | AM12: 1516.9202 | AN12: 19.213349 | AO12: 0.5887314 | AP12: 11.816399 | AQ12: 4.7968444 | AR12: 0.33848638 | AS12: 2.6072647 | AT12: 0.22417208 | AU12: 0.82598323 | AV12: 0.34575783 | AW12: 0.085196181 | AX12: 0.0074106868 | AY12: 0.0071989529 | AZ12: 8.1398957 | BA12: 0.003536053 | BB12: 0 | BC12: 0.00025284886 | BD12: 0.00069921745 | BE12: 0.00024135573 | BF12: -0.0011263267 | BG12: 0.0049618249 | BH12: 9.9607127e-05 | BI12: 0.10843265 | BJ12: 0.61420439 | BK12: 0.026255005 | BL12: 0 | BM12: 0.0003179766 | BN12: 1.2191789 | BO12: 0.00011876234 | BP12: 0.02115286 | BQ12: 0.010495502 | BR12: 0.00056699441 | BS12: 2.2494017 | BT12: 2.9399652 | BU12: 0.17590846 | BV12: 0.4033531 | BW12: 0.0055050816 | BX12: 0.00027583512 | BY12: 0.0026702372 | BZ12: 0 | CA12: 30712 | CB12: 5775.3487
A13: 1091 | B13: Abate e produtos de carne, inclusive os produtos do laticínio e da pesca | C13: 654849.15 | D13: 95816.847 | E13: 4490.6635 | F13: 359.85618 | G13: 505.35172 | H13: 42792.969 | I13: 4855.2985 | J13: 48513.475 | K13: 506028.16 | L13: 396.34287 | M13: 2452.7868 | N13: 23.495002 | O13: 5.7206928 | P13: 0.90561326 | Q13: 1.0239194 | R13: 0.067053179 | S13: 457232.94 | T13: 4.3279009 | U13: 16429.665 | V13: 320.63104 | W13: 0.66902054 | X13: 1.4760123 | Y13: 1.3037725 | Z13: 305.33544 | AA13: 1.8190545 | AB13: 4.1576187 | AC13: 2.1177038 | AD13: 1.6965763 | AE13: 186.94721 | AF13: 380.75902 | AG13: 180.94169 | AH13: 190.96496 | AI13: 140.28027 | AJ13: 10.55668 | AK13: 8.460885 | AL13: 12.404863 | AM13: 8.0618273 | AN13: 104.11553 | AO13: 11.130784 | AP13: 7.3428636 | AQ13: 16.129942 | AR13: 9.4046501 | AS13: 9.4120331 | AT13: 5.7443049 | AU13: 34.901644 | AV13: 1.2930743 | AW13: 15.273636 | AX13: 0.77629189 | AY13: 3.5362833 | AZ13: 16450.863 | BA13: 5.2028106 | BB13: 0.90025726 | BC13: 0.51642416 | BD13: 1.5638388 | BE13: 0.23850408 | BF13: 0.85906842 | BG13: 0.29251494 | BH13: 0.089067974 | BI13: 5.908533 | BJ13: 18.792705 | BK13: 9.8257439 | BL13: 211.20095 | BM13: 0.45268287 | BN13: 29.6254 | BO13: 0.13234834 | BP13: 4.8087929 | BQ13: 1.9801759 | BR13: 0.34038501 | BS13: 51.195608 | BT13: 67.747666 | BU13: 4.8327521 | BV13: 9.2781226 | BW13: 0.57123781 | BX13: 0.33723782 | BY13: 1.5283914 | BZ13: 0 | CA13: 495404 | CB13: 10624.164
A14: 1092 | B14: Fabricação e refino de açúcar | C14: 118140.27 | D14: 12665.015 | E14: 2382.5848 | F14: 40.420133 | G14: 97.313983 | H14: 5475.5959 | I14: 1969.6406 | J14: 7582.9706 | K14: 95509.697 | L14: 171.41343 | M14: 66.62461 | N14: 4.4642044 | O14: 0.18658425 | P14: 2.2256718 | Q14: 1.2106751 | R14: 0.035156297 | S14: 4.3279009 | T14: 57815.616 | U14: 3719.7621 | V14: 27.511335 | W14: 0.32702647 | X14: 0.78820896 | Y14: 0.54442848 | Z14: 1.0693348 | AA14: 1.0899594 | AB14: 9.8749337 | AC14: 1.5200074 | AD14: 0.28480346 | AE14: 30376.765 | AF14: 228.96101 | AG14: 25.949758 | AH14: 273.94282 | AI14: 7.2682037 | AJ14: 8.1107016 | AK14: 4.418418 | AL14: 4.5307005 | AM14: 4.896582 | AN14: 10.159067 | AO14: 28.649734 | AP14: 13.066153 | AQ14: 475.61473 | AR14: 8.4071718 | AS14: 14.908461 | AT14: 5.2670456 | AU14: 4.2846892 | AV14: 3.6059452 | AW14: 10.944494 | AX14: 0.55540867 | AY14: 2.6693398 | AZ14: 986.11947 | BA14: 48.248311 | BB14: 0.68916245 | BC14: 0.32710978 | BD14: 1.338424 | BE14: 0.11745816 | BF14: 0.96152888 | BG14: 0.17358325 | BH14: 0.041307807 | BI14: 2.3794449 | BJ14: 9.0742406 | BK14: 7.3841146 | BL14: 161.67797 | BM14: 0.26074244 | BN14: 16.92735 | BO14: 0.069271352 | BP14: 2.4518061 | BQ14: 1.3169002 | BR14: 0.10758833 | BS14: 28.444449 | BT14: 36.443721 | BU14: 2.5643701 | BV14: 4.9876776 | BW14: 0.40842782 | BX14: 0.18373756 | BY14: 0.44954619 | BZ14: 0 | CA14: 94655 | CB14: 854.69667
A15: 1093 | B15: Outros produtos alimentares | C15: 725169.67 | D15: 122243.99 | E15: 8325.4945 | F15: 1604.3253 | G15: 983.33624 | H15: 43704.452 | I15: 9572.4776 | J15: 55864.591 | K15: 538735.6 | L15: 2528.5604 | M15: 787.12555 | N15: 320.11333 | O15: 284.59871 | P15: 2.7632161 | Q15: 1.304692 | R15: 0.13907913 | S15: 16429.665 | T15: 3719.7621 | U15: 408482.57 | V15: 4011.3576 | W15: 1.619154 | X15: 6.2740592 | Y15: 4.7001181 | Z15: 56.007045 | AA15: 20.894831 | AB15: 89.463413 | AC15: 9.7130278 | AD15: 28.646819 | AE15: 13453.736 | AF15: 3722.2275 | AG15: 2870.1749 | AH15: 529.15379 | AI15: 1362.0272 | AJ15: 112.70491 | AK15: 46.594829 | AL15: 464.16151 | AM15: 38.61932 | AN15: 482.44636 | AO15: 37.440563 | AP15: 20.17717 | AQ15: 66.574505 | AR15: 16.381877 | AS15: 29.051377 | AT15: 10.113854 | AU15: 335.1011 | AV15: 4.785902 | AW15: 50.275357 | AX15: 2.379515 | AY15: 12.28897 | AZ15: 52202.798 | BA15: 69.142129 | BB15: 3.2285088 | BC15: 1.8716287 | BD15: 5.640095 | BE15: 0.87405778 | BF15: 2.9933773 | BG15: 0.79038821 | BH15: 0.32714718 | BI15: 16.058631 | BJ15: 35.101382 | BK15: 33.804319 | BL15: 757.41031 | BM15: 1.6480942 | BN15: 40.097251 | BO15: 0.48384625 | BP15: 16.652539 | BQ15: 6.600454 | BR15: 1.2646983 | BS15: 79.207314 | BT15: 82.546373 | BU15: 7.8376271 | BV15: 11.260809 | BW15: 1.7481445 | BX15: 1.2308135 | BY15: 5.688378 | BZ15: 0 | CA15: 513838 | CB15: 24897.596
A16: 1100 | B16: Fabricação de bebidas | C16: 182780.12 | D16: 24932.467 | E16: 2719.1392 | F16: 739.34076 | G16: 6351.438 | H16: 18688.468 | I16: 7196.2157 | J16: 32975.462 | K16: 122153.05 | L16: 225.27517 | M16: 279.75752 | N16: 7.6584262 | O16: 0.4613504 | P16: 3.0186013 | Q16: 0.22171541 | R16: 0.019611152 | S16: 320.63104 | T16: 27.511335 | U16: 4011.3576 | V16: 97187.747 | W16: 0.36637712 | X16: 2.9806755 | Y16: 1.2329641 | Z16: 0.71736583 | AA16: 5.6104837 | AB16: 12.570569 | AC16: 7.2950621 | AD16: 3.5211087 | AE16: 281.57624 | AF16: 44.656588 | AG16: 234.51164 | AH16: 7.4453256 | AI16: 30.831767 | AJ16: 27.151139 | AK16: 24.073851 | AL16: 35.798713 | AM16: 23.594036 | AN16: 344.37991 | AO16: 12.701531 | AP16: 12.267039 | AQ16: 114.23192 | AR16: 3.8198499 | AS16: 13.017665 | AT16: 1.9223475 | AU16: 6.6414815 | AV16: 2.4388308 | AW16: 59.684218 | AX16: 2.798549 | AY16: 15.545359 | AZ16: 5586.6515 | BA16: 14.780954 | BB16: 4.1504964 | BC16: 1.9630558 | BD16: 6.749333 | BE16: 0.70074099 | BF16: 5.8218786 | BG16: 0.68380352 | BH16: 0.24603135 | BI16: 6.610043 | BJ16: 8.1564419 | BK16: 42.535136 | BL16: 973.70922 | BM16: 1.5615616 | BN16: 7.2780064 | BO16: 0.41391438 | BP16: 13.416461 | BQ16: 7.1823111 | BR16: 0.63232291 | BS16: 16.374896 | BT16: 2.7442978 | BU16: 2.5108585 | BV16: 0.2979645 | BW16: 2.0538595 | BX16: 1.0989597 | BY16: 2.6337921 | BZ16: 0 | CA16: 110108 | CB16: 12045.052
A17: 1200 | B17: Fabricação de produtos do fumo | C17: 50280.054 | D17: 5127.9994 | E17: 41.063639 | F17: 28.187699 | G17: 7023.6992 | H17: 7214.5668 | I17: 968.0017 | J17: 15234.455 | K17: 29876.535 | L17: 219.68728 | M17: 120.63196 | N17: 0.98101925 | O17: 0.026445887 | P17: 0.15200345 | Q17: 0.34215122 | R17: 0.017999922 | S17: 0.66902054 | T17: 0.32702647 | U17: 1.619154 | V17: 0.36637712 | W17: 18018.108 | X17: 0.12512738 | Y17: 0.16862189 | Z17: 13.342624 | AA17: 0.12981354 | AB17: 26.68881 | AC17: 0.21396381 | AD17: 0.010536708 | AE17: 0.040445022 | AF17: 11.021097 | AG17: 2.1989401 | AH17: 0.93479956 | AI17: 2.098511 | AJ17: 1.5503062 | AK17: 1.410159 | AL17: 0.70255561 | AM17: 0.3970713 | AN17: 0.64533829 | AO17: 2.5714415 | AP17: 1.6474583 | AQ17: 13.080163 | AR17: 2.6201829 | AS17: 2.0520462 | AT17: 1.7093531 | AU17: 0.50885125 | AV17: 0.20664549 | AW17: 0.96231442 | AX17: 0.069867173 | AY17: 0.13502682 | AZ17: 140.1795 | BA17: 0.1498445 | BB17: 0.021730348 | BC17: 0.015507735 | BD17: 0.046496886 | BE17: 0.0086610315 | BF17: 0.0071839638 | BG17: 0.041766123 | BH17: 0.0033484079 | BI17: 0.92129497 | BJ17: 4.7403922 | BK17: 0.4183162 | BL17: 5.097954 | BM17: 0.014752781 | BN17: 9.1363666 | BO17: 0.0046235854 | BP17: 0.28353385 | BQ17: 0.12300202 | BR17: 0.015038371 | BS17: 15.210372 | BT17: 21.916222 | BU17: 1.3344402 | BV17: 3.0068382 | BW17: 0.051770111 | BX17: 0.011459122 | BY17: 0.069020991 | BZ17: 0 | CA17: 18653 | CB17: 11223.535
... A72: 9700 | B72: Serviços domésticos | C72: 61371 | D72: 0 | E72: 0 | F72: 0 | G72: 0 | H72: 0 | I72: 0 | J72: 0 | K72: 61371 | L72: 0 | M72: 0 | N72: 0 | O72: 0 | P72: 0 | Q72: 0 | R72: 0 | S72: 0 | T72: 0 | U72: 0 | V72: 0 | W72: 0 | X72: 0 | Y72: 0 | Z72: 0 | AA72: 0 | AB72: 0 | AC72: 0 | AD72: 0 | AE72: 0 | AF72: 0 | AG72: 0 | AH72: 0 | AI72: 0 | AJ72: 0 | AK72: 0 | AL72: 0 | AM72: 0 | AN72: 0 | AO72: 0 | AP72: 0 | AQ72: 0 | AR72: 0 | AS72: 0 | AT72: 0 | AU72: 0 | AV72: 0 | AW72: 0 | AX72: 0 | AY72: 0 | AZ72: 0 | BA72: 0 | BB72: 0 | BC72: 0 | BD72: 0 | BE72: 0 | BF72: 0 | BG72: 0 | BH72: 0 | BI72: 0 | BJ72: 0 | BK72: 0 | BL72: 0 | BM72: 0 | BN72: 0 | BO72: 0 | BP72: 0 | BQ72: 0 | BR72: 0 | BS72: 0 | BT72: 0 | BU72: 0 | BV72: 0 | BW72: 0 | BX72: 0 | BY72: 0 | BZ72: 61371 | CA72: 61371 | CB72: 0
A74: Total | C74: 19551489 | D74: -9.5154995e-12 | E74: -4.9022314e-12 | F74: 61876 | G74: 70414 | H74: 652462 | I74: 513391 | J74: 1298143 | K74: 18253346 | L74: 769160 | M74: 272241 | N74: 54743 | O74: 30081 | P74: 406701 | Q74: 279099 | R74: 30712 | S74: 495404 | T74: 94655 | U74: 513838 | V74: 110108 | W74: 18653 | X74: 82836 | Y74: 80645 | Z74: 50739 | AA74: 61516 | AB74: 156926 | AC74: 22332 | AD74: 678319 | AE74: 105728 | AF74: 353156 | AG74: 138097 | AH74: 67872 | AI74: 99278 | AJ74: 197694 | AK74: 143010 | AL74: 305615 | AM74: 121205 | AN74: 189661 | AO74: 146376 | AP74: 137668 | AQ74: 242983 | AR74: 241683 | AS74: 145523 | AT74: 50525 | AU74: 113057 | AV74: 107939 | AW74: 455696 | AX74: 107088 | AY74: 704341 | AZ74: 1668202 | BA74: 506364 | BB74: 34706 | BC74: 35749 | BD74: 188012 | BE74: 31722 | BF74: 287344 | BG74: 17626 | BH74: 46662 | BI74: 182343 | BJ74: 267495 | BK74: 717847 | BL74: 758313 | BM74: 285030 | BN74: 85091 | BO74: 146292 | BP74: 75203 | BQ74: 319061 | BR74: 46889 | BS74: 993216 | BT74: 404343 | BU74: 150446 | BV74: 279166 | BW74: 382369 | BX74: 42806 | BY74: 185302 | BZ74: 61371 | CA74: 16581873 | CB74: 1671473
A76: (1) Importação de bens e serviços líquida de ajuste CIF/FOB.

Sheet Usos
A1: Tabela 2 - Usos de bens e serviços - 2021 (Preços correntes)
A2: Unidade de Medida: R$ 1.000.000,00
A3: Código da Atividade Nível 67 | B3: Descrição da Atividade Nível 67 | C3: Consumo intermediário das atividades | L3: Consumo intermediário das atividades | U3: Consumo intermediário das atividades | AD3: Consumo intermediário das atividades | AM3: Consumo intermediário das atividades | AV3: Consumo intermediário das atividades | BE3: Consumo intermediário das atividades | BR3: Consumo intermediário das atividades | BS3: Demanda final | BZ3: Demanda Total
C4: 0191 | D4: 0192 | E4: 0280 | F4: 0580 | G4: 0680 | H4: 0791 | I4: 0792 | J4: 1091 | K4: 1092 | L4: 1093 | M4: 1100 | N4: 1200 | O4: 1300 | P4: 1400 | Q4: 1500 | R4: 1600 | S4: 1700 | T4: 1800 | U4: 1991 | V4: 1992 | W4: 2091 | X4: 2092 | Y4: 2093 | Z4: 2100 | AA4: 2200 | AB4: 2300 | AC4: 2491 | AD4: 2492 | AE4: 2500 | AF4: 2600 | AG4: 2700 | AH4: 2800 | AI4: 2991 | AJ4: 2992 | AK4: 3000 | AL4: 3180 | AM4: 3300 | AN4: 3500 | AO4: 3680 | AP4: 4180 | AQ4: 4580 | AR4: 4900 | AS4: 5000 | AT4: 5100 | AU4: 5280 | AV4: 5500 | AW4: 5600 | AX4: 5800 | AY4: 5980 | AZ4: 6100 | BA4: 6280 | BB4: 6480 | BC4: 6800 | BD4: 6980 | BE4: 7180 | BF4: 7380 | BG4: 7700 | BH4: 7880 | BI4: 8000 | BJ4: 8400 | BK4: 8591 | BL4: 8592 | BM4: 8691 | BN4: 8692 | BO4: 9080 | BP4: 9480 | BQ4: 9700 | BR4: Total do produto | BS4: Exportação de bens e serviços (1) | BT4: Consumo do governo | BU4: Consumo das ISFLSF | BV4: Consumo das famílias | BW4: Formação bruta de capital fixo | BX4: Variação de estoque | BY4: Demanda final y
C5: Agricultura, inclusive o apoio à agricultura e a pós-colheita | D5: Pecuária, inclusive o apoio à pecuária | E5: Produção florestal; pesca e aquicultura | F5: Extração de carvão mineral e de minerais não metálicos | G5: Extração de petróleo e gás, inclusive as atividades de apoio | H5: Extração de minério de ferro, inclusive beneficiamentos e a aglomeração | I5: Extração de minerais metálicos não ferrosos, inclusive beneficiamentos | J5: Abate e produtos de carne, inclusive os produtos do laticínio e da pesca | K5: Fabricação e refino de açúcar | L5: Outros produtos alimentares | M5: Fabricação de bebidas | N5: Fabricação de produtos do fumo | O5: Fabricação de produtos têxteis | P5: Confecção de artefatos do vestuário e acessórios | Q5: Fabricação de calçados e de artefatos de couro | R5: Fabricação de produtos da madeira | S5: Fabricação de celulose, papel e produtos de papel | T5: Impressão e reprodução de gravações | U5: Refino de petróleo e coquerias | V5: Fabricação de biocombustíveis | W5: Fabricação de químicos orgânicos e inorgânicos, resinas e elastômeros | X5: Fabricação de defensivos, desinfestantes, tintas e químicos diversos | Y5: Fabricação de produtos de limpeza, cosméticos/perfumaria e higiene pessoal | Z5: Fabricação de produtos farmoquímicos e farmacêuticos | AA5: Fabricação de produtos de borracha e de material plástico | AB5: Fabricação de produtos de minerais não metálicos | AC5: Produção de ferro gusa/ferroligas, siderurgia e tubos de aço sem costura | AD5: Metalurgia de metais não ferosos e a fundição de metais | AE5: Fabricação de produtos de metal, exceto máquinas e equipamentos | AF5: Fabricação de equipamentos de informática, produtos eletrônicos e ópticos | AG5: Fabricação de máquinas e equipamentos elétricos | AH5: Fabricação de máquinas e equipamentos mecânicos | AI5: Fabricação de automóveis, caminhões e ônibus, exceto peças | AJ5: Fabricação de peças e acessórios para veículos automotores | AK5: Fabricação de outros equipamentos de transporte, exceto veículos automotores | AL5: Fabricação de móveis e de produtos de indústrias diversas | AM5: Manutenção, reparação e instalação de máquinas e equipamentos | AN5: Energia elétrica, gás natural e outras utilidades | AO5: Água, esgoto e gestão de resíduos | AP5: Construção | AQ5: Comércio por atacado e varejo | AR5: Transporte terrestre | AS5: Transporte aquaviário | AT5: Transporte aéreo | AU5: Armazenamento, atividades auxiliares dos transportes e correio | AV5: Alojamento | AW5: Alimentação | AX5: Edição e edição integrada à impressão | AY5: Atividades de televisão, rádio, cinema e gravação/edição de som e imagem | AZ5: Telecomunicações | BA5: Desenvolvimento de sistemas e outros serviços de informação | BB5: Intermediação financeira, seguros e previdência complementar | BC5: Atividades imobiliárias | BD5: Atividades jurídicas, contábeis, consultoria e sedes de empresas | BE5: Serviços de arquitetura, engenharia, testes/análises técnicas e P & D | BF5: Outras atividades profissionais, científicas e técnicas | BG5: Aluguéis não imobiliários e gestão de ativos de propriedade intelectual | BH5: Outras atividades administrativas e serviços complementares | BI5: Atividades de vigilância, segurança e investigação | BJ5: Administração pública, defesa e seguridade social | BK5: Educação pública | BL5: Educação privada | BM5: Saúde pública | BN5: Saúde privada | BO5: Atividades artísticas, criativas e de espetáculos | BP5: Organizações associativas e outros serviços pessoais | BQ5: Serviços domésticos
A6: 0191 | B6: Agricultura, inclusive o apoio à agricultura e a pós-colheita | C6: 21763.314 | D6: 17112.899 | E6: 326.40662 | F6: 3.1620347 | G6: 11.247145 | H6: 19.109115 | I6: 2.682393 | J6: 15863.447 | K6: 42790.231 | L6: 193303.68 | M6: 4429.6644 | N6: 7692.6095 | O6: 14497.27 | P6: 1296.6729 | Q6: 11.638649 | R6: 163.48789 | S6: 313.14024 | T6: 0.30962663 | U6: 19.688264 | V6: 39735.053 | W6: 34.007364 | X6: 30.319622 | Y6: 5.5720956 | Z6: 40.86561 | AA6: 60.160668 | AB6: 31.534554 | AC6: 67.253879 | AD6: 41.28878 | AE6: 7.9404265 | AF6: 0.51340578 | AG6: 0.6443122 | AH6: 1.7510737 | AI6: 0.86895386 | AJ6: 0.71755076 | AK6: 0.70420744 | AL6: 24.765207 | AM6: 0.16545958 | AN6: 1.13106 | AO6: 88.148562 | AP6: 489.70524 | AQ6: 24335.471 | AR6: 2.4765859 | AS6: 0.11771577 | AT6: 0.44073394 | AU6: 20.617997 | AV6: 559.20552 | AW6: 7788.8309 | AX6: 0.2522445 | AY6: 1.1022581 | AZ6: 47.089224 | BA6: 6.237767 | BB6: 17.587587 | BC6: 20.802821 | BD6: 15.627761 | BE6: 17.623155 | BF6: 2.5334746 | BG6: 1.8762792 | BH6: 257.1969 | BI6: 0.54088568 | BJ6: 1826.3358 | BK6: 643.71859 | BL6: 114.59755 | BM6: 832.13591 | BN6: 349.22373 | BO6: 5.8969499 | BP6: 610.59416 | BQ6: 0 | BR6: 397761.9 | BS6: 288934.79 | BT6: 177.53961 | BU6: 0 | BV6: 168172.1 | BW6: 5007.4692 | BX6: 46352.209 | BY6: 508644.11 | BZ6: 906406.02
A7: 0192 | B7: Pecuária, inclusive o apoio à pecuária | C7: 2360.7092 | D7: 13282.043 | E7: 438.80011 | F7: 7.8843246 | G7: 29.24995 | H7: 34.479303 | I7: 4.9193312 | J7: 176538.76 | K7: 242.25269 | L7: 10363.856 | M7: 131.91233 | N7: 362.12402 | O7: 726.00686 | P7: 605.03346 | Q7: 11.346024 | R7: 327.14125 | S7: 545.89438 | T7: 0.5355486 | U7: 1.3893184 | V7: 474.32308 | W7: 119.11562 | X7: 14.737362 | Y7: 15.025633 | Z7: 20.13707 | AA7: 95.457877 | AB7: 148.03236 | AC7: 144.73255 | AD7: 80.792901 | AE7: 6.5297936 | AF7: 1.1352704 | AG7: 2.0774562 | AH7: 3.6271096 | AI7: 1.6803937 | AJ7: 1.6826953 | AK7: 1.0960173 | AL7: 14.65016 | AM7: 0.42699741 | AN7: 1.6685506 | AO7: 15.049298 | AP7: 986.28236 | AQ7: 879.8348 | AR7: 2.5410432 | AS7: 0.10464714 | AT7: 0.49084396 | AU7: 34.463198 | AV7: 578.05529 | AW7: 3181.6283 | AX7: 0.44475333 | AY7: 1.81705 | AZ7: 84.108436 | BA7: 10.854565 | BB7: 27.87088 | BC7: 38.83934 | BD7: 11.803109 | BE7: 22.814536 | BF7: 12.726878 | BG7: 2.5315187 | BH7: 44.24211 | BI7: 0.68820619 | BJ7: 507.44616 | BK7: 179.1148 | BL7: 36.068744 | BM7: 210.66233 | BN7: 158.81552 | BO7: 5.5628368 | BP7: 83.779411 | BQ7: 0 | BR7: 214279.9 | BS7: 13128.774 | BT7: 10.623994 | BU7: 0 | BV7: 50185.289 | BW7: 31332.458 | BX7: 1033.6845 | BY7: 95690.829 | BZ7: 309970.73
A8: 0280 | B8: Produção florestal; pesca e aquicultura | C8: 2777.9267 | D8: 2784.0452 | E8: 4512.2752 | F8: 2.6154121 | G8: 2.3158156 | H8: 2.6351451 | I8: 0.36466992 | J8: 4549.406 | K8: 1.4484283 | L8: 473.78993 | M8: 22.984987 | N8: 20.525818 | O8: 43.089871 | P8: 10.596841 | Q8: 7.1700035 | R8: 3847.9358 | S8: 6246.3106 | T8: 0.042726502 | U8: 0.11823837 | V8: 14.196616 | W8: 430.76307 | X8: 4.8145642 | Y8: 0.18822283 | Z8: 0.29995925 | AA8: 1028.5835 | AB8: 124.98758 | AC8: 1558.8024 | AD8: 5.9732383 | AE8: 10.022643 | AF8: 0.12359312 | AG8: 0.19966173 | AH8: 0.41648055 | AI8: 0.18322751 | AJ8: 0.16630926 | AK8: 0.097864775 | AL8: 3.2042458 | AM8: 0.050841502 | AN8: 0.22630631 | AO8: 1.0479283 | AP8: 1168.6602 | AQ8: 289.50085 | AR8: 0.28539583 | AS8: 0.012090688 | AT8: 0.045236979 | AU8: 2.6951149 | AV8: 70.612539 | AW8: 889.01129 | AX8: 0.052633971 | AY8: 0.19586468 | AZ8: 6.2234647 | BA8: 1.0745269 | BB8: 2.3499401 | BC8: 2.9762221 | BD8: 1.0867401 | BE8: 5.2977743 | BF8: 0.31883408 | BG8: 0.26556341 | BH8: 3.0592281 | BI8: 0.071800631 | BJ8: 192.97068 | BK8: 124.07145 | BL8: 17.899089 | BM8: 154.96757 | BN8: 31.549106 | BO8: 0.53273047 | BP8: 6.2016657 | BQ8: 0 | BR8: 31461.933 | BS8: 6688.6279 | BT8: 5.0223877 | BU8: 0 | BV8: 34559.58 | BW8: 2181.9304 | BX8: -951.40685 | BY8: 42483.754 | BZ8: 73945.687
A9: 0580 | B9: Extração de carvão mineral e de minerais não metálicos | C9: 249.79761 | D9: 1137.4064 | E9: 35.214173 | F9: 529.81219 | G9: 1072.3962 | H9: 2.6522006 | I9: 22.085726 | J9: 158.20153 | K9: 28.818489 | L9: 477.05887 | M9: 40.661769 | N9: 0.017652694 | O9: 0.72652667 | P9: 0.14011781 | Q9: 0.57799161 | R9: 0.17984183 | S9: 29.939155 | T9: 2.3963787 | U9: 101.44059 | V9: 807.67399 | W9: 6556.5997 | X9: 186.05574 | Y9: 10.198562 | Z9: 2.1930927 | AA9: 12.194856 | AB9: 10491.048 | AC9: 15847.337 | AD9: 1919.7405 | AE9: 29.941949 | AF9: 1.5358305 | AG9: 144.11792 | AH9: 20.340688 | AI9: 38.352838 | AJ9: 186.99506 | AK9: 8.3354314 | AL9: 75.807036 | AM9: 9.6435027 | AN9: 4151.1631 | AO9: 817.48558 | AP9: 11159.332 | AQ9: 174.75649 | AR9: 0.6280623 | AS9: 0.18763093 | AT9: 0.045234481 | AU9: 9.7716412 | AV9: 3.9304086 | AW9: 19.606694 | AX9: 0.097169311 | AY9: 0.13526986 | AZ9: 0.6190792 | BA9: 0.95593506 | BB9: 1.1996308 | BC9: 392.96344 | BD9: 1.4837362 | BE9: 12.523935 | BF9: 0.50758344 | BG9: 0.46377093 | BH9: 2.8566104 | BI9: 0.10947533 | BJ9: 130.75277 | BK9: 28.164628 | BL9: 1.5333608 | BM9: 19.046914 | BN9: 6.0923649 | BO9: 1.0271983 | BP9: 4.4172371 | BQ9: 0 | BR9: 57179.492 | BS9: 3941.0545 | BT9: 0.045260178 | BU9: 0 | BV9: 305.61348 | BW9: 25.265464 | BX9: 1099.657 | BY9: 5371.6357 | BZ9: 62551.128
A10: 0680 | B10: Extração de petróleo e gás, inclusive as atividades de apoio | C10: 67.626452 | D10: 45.676109 | E10: 2.857084 | F10: 5.033237 | G10: 9940.189 | H10: 1516.9024 | I10: 79.629162 | J10: 98.44333 | K10: 1.3546489 | L10: 903.48828 | M10: 188.128 | N10: 0.28513687 | O10: 155.5883 | P10: 1.2402705 | Q10: 2.9435957 | R10: 83.665141 | S10: 1032.6486 | T10: 0.69526972 | U10: 193934.67 | V10: 2.0401343 | W10: 2704.8483 | X10: 129.28253 | Y10: 36.588871 | Z10: 45.722364 | AA10: 158.74824 | AB10: 923.60665 | AC10: 575.18697 | AD10: 420.89789 | AE10: 511.75048 | AF10: 1.2653128 | AG10: 51.399009 | AH10: 187.71152 | AI10: 75.412668 | AJ10: 185.06088 | AK10: 3.644864 | AL10: 3.9501158 | AM10: 72.064558 | AN10: 30352.293 | AO10: 1628.6263 | AP10: 1898.8581 | AQ10: 289.15665 | AR10: 207.41841 | AS10: 4.9631533 | AT10: 0.33445265 | AU10: 153.59058 | AV10: 3.4530661 | AW10: 78.454894 | AX10: 0.65754673 | AY10: 1.4394632 | AZ10: 202.41202 | BA10: 8.7447584 | BB10: 13.178959 | BC10: 6.0506155 | BD10: 15.539587 | BE10: 84.989509 | BF10: 5.9122029 | BG10: 11.40374 | BH10: 21.78021 | BI10: 0.98761379 | BJ10: 3414.5232 | BK10: 39.705057 | BL10: 14.667452 | BM10: 4.3301047 | BN10: 9.242633 | BO10: 10.931864 | BP10: 42.846156 | BQ10: 0 | BR10: 252676.74 | BS10: 165144.13 | BT10: 0 | BU10: 0 | BV10: 1115.359 | BW10: 58608.187 | BX10: -12658.357 | BY10: 212209.32 | BZ10: 464886.06
A11: 0791 | B11: Extração de minério de ferro, inclusive beneficiamentos e a aglomeração | C11: 0.59468298 | D11: 1.2087742 | E11: 0.082631066 | F11: 0.17977575 | G11: 26.681913 | H11: 9060.1728 | I11: 134.0236 | J11: 1.925513 | K11: 0.10424184 | L11: 2.6549729 | M11: 0.37428293 | N11: 0.10099242 | O11: 0.21375188 | P11: 0.086831236 | Q11: 0.095647879 | R11: 0.44115074 | S11: 1.5901467 | T11: 1.3240992 | U11: 0.295459 | V11: 0.018094235 | W11: 0.60624145 | X11: 1.0080674 | Y11: 0.27164079 | Z11: 1.0262498 | AA11: 0.86208238 | AB11: 463.99709 | AC11: 68268.366 | AD11: 193.75942 | AE11: 12.835028 | AF11: 1.1007262 | AG11: 34.727108 | AH11: 68.187645 | AI11: 7.2949467 | AJ11: 13.286343 | AK11: 4.3838377 | AL11: 11.564517 | AM11: 27.942387 | AN11: 0.38476817 | AO11: 21.772745 | AP11: 216.61348 | AQ11: 5.864803 | AR11: 1.5405428 | AS11: 0.68526929 | AT11: 0.0043854348 | AU11: 10.672376 | AV11: 0.36436978 | AW11: 3.4108406 | AX11: 0.016152737 | AY11: 0.022237953 | AZ11: 25.400129 | BA11: 0.78520618 | BB11: 5.2590448 | BC11: 8.600266 | BD11: 2.0137999 | BE11: 15.729435 | BF11: 0.13182895 | BG11: 0.2176563 | BH11: 11.239392 | BI11: 0.080712117 | BJ11: 60.049152 | BK11: 2.817764 | BL11: 0.26310494 | BM11: 18.933916 | BN11: 0.172361 | BO11: 0.93233806 | BP11: 0.57970533 | BQ11: 0 | BR11: 78757.947 | BS11: 238522.42 | BT11: 0 | BU11: 0 | BV11: 18.770746 | BW11: 1812.8497 | BX11: -7692.8352 | BY11: 232661.2 | BZ11: 311419.15
A12: 0792 | B12: Extração de minerais metálicos não ferrosos, inclusive beneficiamentos | C12: 5.6514314 | D12: 1.9818869 | E12: 0.069584294 | F12: 0.063934853 | G12: 120.56938 | H12: 60.780043 | I12: 2605.3398 | J12: 12.578046 | K12: 0.229787 | L12: 23.087046 | M12: 1.5554655 | N12: 0.0063430536 | O12: 0.058896238 | P12: 0.0069516394 | Q12: 0.056094995 | R12: 0.0090763278 | S12: 13.014887 | T12: 10.551075 | U12: 0.0029115929 | V12: 0.010210761 | W12: 16.813469 | X12: 9.2345637 | Y12: 0.59245837 | Z12: 0.5292537 | AA12: 4.5743456 | AB12: 112.18417 | AC12: 4277.7152 | AD12: 14785.433 | AE12: 109.96405 | AF12: 6.8874203 | AG12: 289.7197 | AH12: 48.363477 | AI12: 26.10615 | AJ12: 127.70132 | AK12: 28.601229 | AL12: 101.58268 | AM12: 15.949668 | AN12: 0.54659874 | AO12: 4.1720047 | AP12: 106.97562 | AQ12: 1.3120497 | AR12: 0.61365405 | AS12: 0.004196379 | AT12: 0 | AU12: 0.0066549864 | AV12: 0.12634566 | AW12: 0.43489313 | AX12: 0.0018103055 | AY12: 0.0023292743 | AZ12: 0.024122209 | BA12: 0.037014298 | BB12: 0.0019529975 | BC12: 1.8097538 | BD12: 0.001677997 | BE12: 1.1873313 | BF12: 0.0025283167 | BG12: 0.012630621 | BH12: 0.086105622 | BI12: 0.0010995094 | BJ12: 0.54977154 | BK12: 0.15810954 | BL12: 0.00026919956 | BM12: 0.24944434 | BN12: 0.252943 | BO12: 0.00063718334 | BP12: 0.17295506 | BQ12: 0 | BR12: 22936.319 | BS12: 22409.989 | BT12: 0 | BU12: 0 | BV12: 13.302392 | BW12: 11.168367 | BX12: -3283.958 | BY12: 19150.502 | BZ12: 42086.821
A13: 1091 | B13: Abate e produtos de carne, inclusive os produtos do laticínio e da pesca | C13: 100.15135 | D13: 5271.5197 | E13: 54.165642 | F13: 21.054952 | G13: 21.135649 | H13: 20.601654 | I13: 2.9991927 | J13: 58615.538 | K13: 2.2509941 | L13: 6878.336 | M13: 103.56114 | N13: 0.74808011 | O13: 10.41066 | P13: 4.80142 | Q13: 2463.6265 | R13: 10.255182 | S13: 37.929292 | T13: 1.997377 | U13: 6.3263462 | V13: 2137.7703 | W13: 167.4838 | X13: 154.79643 | Y13: 5968.7316 | Z13: 41.18153 | AA13: 35.585438 | AB13: 10.001295 | AC13: 15.921528 | AD13: 5.4672649 | AE13: 179.08223 | AF13: 4.7281936 | AG13: 9.9773187 | AH13: 31.017499 | AI13: 9.4365201 | AJ13: 5.0760772 | AK13: 2.8151337 | AL13: 13.205986 | AM13: 8.2218516 | AN13: 4.9031508 | AO13: 7.0644243 | AP13: 35.494697 | AQ13: 940.63383 | AR13: 18.513919 | AS13: 0.33223777 | AT13: 0.41225361 | AU13: 8.4205233 | AV13: 926.22886 | AW13: 33859.88 | AX13: 0.91966111 | AY13: 1.8768964 | AZ13: 9.416963 | BA13: 6.0890404 | BB13: 9.2240854 | BC13: 3.7646672 | BD13: 9.919628 | BE13: 7.8685417 | BF13: 6.6879322 | BG13: 4.849547 | BH13: 8.8128326 | BI13: 1.2242711 | BJ13: 4865.8701 | BK13: 2362.9083 | BL13: 501.30878 | BM13: 3235.1781 | BN13: 1463.9684 | BO13: 13.104671 | BP13: 412.84907 | BQ13: 0 | BR13: 131155.63 | BS13: 114930.97 | BT13: 101.02011 | BU13: 0 | BV13: 406060.51 | BW13: 255.22113 | BX13: 2345.79 | BY13: 523693.51 | BZ13: 654849.15
A14: 1092 | B14: Fabricação e refino de açúcar | C14: 107.67493 | D14: 221.52063 | E14: 5.8870263 | F14: 3.1741749 | G14: 556.65548 | H14: 77.243334 | I14: 8.9053058 | J14: 715.70942 | K14: 3164.1118 | L14: 7667.4427 | M14: 1752.1188 | N14: 0.20020437 | O14: 0.87791872 | P14: 0.98358962 | Q14: 0.50347001 | R14: 58.185908 | S14: 8.7733159 | T14: 0.087717373 | U14: 18298.418 | V14: 2800.3141 | W14: 290.81823 | X14: 1001.9189 | Y14: 1178.5593 | Z14: 546.59328 | AA14: 2.5308212 | AB14: 2.555786 | AC14: 1.8815432 | AD14: 1.1445144 | AE14: 31.940838 | AF14: 1.5319163 | AG14: 7.6118447 | AH14: 222.10184 | AI14: 23.273384 | AJ14: 2.2970089 | AK14: 4.3687097 | AL14: 3.5228837 | AM14: 93.556109 | AN14: 7.8291368 | AO14: 37.84811 | AP14: 395.21957 | AQ14: 1039.2375 | AR14: 672.59226 | AS14: 11.357167 | AT14: 23.776004 | AU14: 66.289187 | AV14: 19.29053 | AW14: 1660.227 | AX14: 6.1529032 | AY14: 12.08134 | AZ14: 29.829894 | BA14: 71.985725 | BB14: 116.83295 | BC14: 24.349459 | BD14: 131.70626 | BE14: 159.79502 | BF14: 60.365467 | BG14: 155.3213 | BH14: 195.27624 | BI14: 74.174375 | BJ14: 595.74298 | BK14: 154.07611 | BL14: 24.182172 | BM14: 168.61032 | BN14: 114.4334 | BO14: 27.970079 | BP14: 177.90083 | BQ14: 0 | BR14: 45099.448 | BS14: 43445.093 | BT14: 0.034380726 | BU14: 0 | BV14: 28436.384 | BW14: 655.5277 | BX14: 503.77962 | BY14: 73040.819 | BZ14: 118140.27
A15: 1093 | B15: Outros produtos alimentares | C15: 4788.4353 | D15: 33543.216 | E15: 2505.9331 | F15: 407.55777 | G15: 427.50378 | H15: 189.43821 | I15: 35.112665 | J15: 60910.736 | K15: 78.004932 | L15: 69362.873 | M15: 5176.6393 | N15: 4.0053189 | O15: 85.246062 | P15: 37.944023 | Q15: 63.9742 | R15: 158.3019 | S15: 2098.3272 | T15: 32.828432 | U15: 6578.6252 | V15: 10760.222 | W15: 1805.8628 | X15: 2417.968 | Y15: 2249.1116 | Z15: 505.91381 | AA15: 350.08747 | AB15: 164.48257 | AC15: 184.88235 | AD15: 44.643786 | AE15: 264.46402 | AF15: 20.654924 | AG15: 72.624646 | AH15: 207.93099 | AI15: 76.542648 | AJ15: 65.539144 | AK15: 17.747662 | AL15: 122.20028 | AM15: 77.423945 | AN15: 25.636854 | AO15: 81.529179 | AP15: 468.47349 | AQ15: 8089.4699 | AR15: 316.4545 | AS15: 6.0665684 | AT15: 42.817925 | AU15: 85.48875 | AV15: 437.12695 | AW15: 23085.452 | AX15: 6.3519512 | AY15: 11.718415 | AZ15: 61.797552 | BA15: 47.097631 | BB15: 257.87737 | BC15: 49.484191 | BD15: 125.50305 | BE15: 84.831709 | BF15: 142.21393 | BG15: 80.850202 | BH15: 121.46809 | BI15: 30.949762 | BJ15: 3654.2468 | BK15: 2317.7976 | BL15: 356.05947 | BM15: 4848.9649 | BN15: 1333.9866 | BO15: 84.539402 | BP15: 1449.2713 | BQ15: 0 | BR15: 253596.53 | BS15: 77693.403 | BT15: 128.06951 | BU15: 0 | BV15: 384417.11 | BW15: 432.49348 | BX15: 8902.0646 | BY15: 471573.14 | BZ15: 725169.67
A16: 1100 | B16: Fabricação de bebidas | C16: 29.789357 | D16: 7.9365174 | E16: 0.50304841 | F16: 33.65391 | G16: 33.588506 | H16: 42.53833 | I16: 5.972537 | J16: 752.53967 | K16: 4.6220815 | L16: 179.52372 | M16: 15135.858 | N16: 0.96680965 | O16: 6.1929172 | P16: 4.8743695 | Q16: 3.9318069 | R16: 18.148816 | S16: 20.082511 | T16: 3.5172706 | U16: 62.660143 | V16: 11.240144 | W16: 27.376207 | X16: 64.754223 | Y16: 24.176303 | Z16: 21.223355 | AA16: 30.875647 | AB16: 15.064902 | AC16: 25.525583 | AD16: 3.6609027 | AE16: 58.981366 | AF16: 9.6060861 | AG16: 20.716714 | AH16: 104.08794 | AI16: 27.140103 | AJ16: 13.944417 | AK16: 8.6418463 | AL16: 16.756168 | AM16: 39.833349 | AN16: 14.553523 | AO16: 11.313155 | AP16: 127.74025 | AQ16: 401.67342 | AR16: 34.937775 | AS16: 1.273937 | AT16: 10.04534 | AU16: 27.525678 | AV16: 898.41355 | AW16: 51534.511 | AX16: 1.9005902 | AY16: 4.3774105 | AZ16: 19.609664 | BA16: 19.80799 | BB16: 151.9373 | BC16: 15.055192 | BD16: 38.899817 | BE16: 7.392457 | BF16: 11.886788 | BG16: 10.789061 | BH16: 33.577809 | BI16: 3.3481481 | BJ16: 274.89409 | BK16: 151.31601 | BL16: 47.559639 | BM16: 213.47491 | BN16: 269.39209 | BO16: 72.303747 | BP16: 39.16073 | BQ16: 0 | BR16: 71319.176 | BS16: 4450.8909 | BT16: 0.52454047 | BU16: 0 | BV16: 105256.7 | BW16: 158.65431 | BX16: 1594.1754 | BY16: 111460.95 | BZ16: 182780.12
A17: 1200 | B17: Fabricação de produtos do fumo | C17: 12.445479 | D17: 1.311102 | E17: 0.093345236 | F17: 0.029789157 | G17: 1.6259145 | H17: 2.593272 | I17: 0.20231841 | J17: 3.1026139 | K17: 0.1529166 | L17: 2.8049378 | M17: 0.30074728 | N17: 1953.1315 | O17: 0.43274466 | P17: 0.29170654 | Q17: 0.42436732 | R17: 1.0535838 | S17: 5.8479955 | T17: 0.63577308 | U17: 0.16634306 | V17: 0.15640531 | W17: 0.78139312 | X17: 0.30796561 | Y17: 0.99297294 | Z17: 1.0827888 | AA17: 1.6784622 | AB17: 1.3957584 | AC17: 0.25883577 | AD17: 0.28888867 | AE17: 0.96925641 | AF17: 0.61574008 | AG17: 0.68196543 | AH17: 6.080907 | AI17: 0.87809798 | AJ17: 0.61639666 | AK17: 0.16569873 | AL17: 0.68640026 | AM17: 2.1184511 | AN17: 0.16518914 | AO17: 0.17792177 | AP17: 1.0745092 | AQ17: 6.9000903 | AR17: 0.92364294 | AS17: 0.088726185 | AT17: 0.0072994784 | AU17: 0.43084586 | AV17: 0.11036157 | AW17: 0.76407903 | AX17: 0.42387077 | AY17: 0.13164979 | AZ17: 0.44528009 | BA17: 0.87178913 | BB17: 0.86529598 | BC17: 0.2094792 | BD17: 0.99761153 | BE17: 1.6499756 | BF17: 0.42768856 | BG17: 0.48777209 | BH17: 1.7578269 | BI17: 0.057017967 | BJ17: 0.64633811 | BK17: 0.35818905 | BL17: 0.44307928 | BM17: 0.29736913 | BN17: 0.52234689 | BO17: 0.14872013 | BP17: 0.40059235 | BQ17: 0 | BR17: 2028.1874 | BS17: 7614.007 | BT17: 0 | BU17: 0 | BV17: 40628.587 | BW17: 88.438054 | BX17: -79.166052 | BY17: 48251.866 | BZ17: 50280.054
... A72: 9700 | B72: Serviços domésticos | C72: 0 | D72: 0 | E72: 0 | F72: 0 | G72: 0 | H72: 0 | I72: 0 | J72: 0 | K72: 0 | L72: 0 | M72: 0 | N72: 0 | O72: 0 | P72: 0 | Q72: 0 | R72: 0 | S72: 0 | T72: 0 | U72: 0 | V72: 0 | W72: 0 | X72: 0 | Y72: 0 | Z72: 0 | AA72: 0 | AB72: 0 | AC72: 0 | AD72: 0 | AE72: 0 | AF72: 0 | AG72: 0 | AH72: 0 | AI72: 0 | AJ72: 0 | AK72: 0 | AL72: 0 | AM72: 0 | AN72: 0 | AO72: 0 | AP72: 0 | AQ72: 0 | AR72: 0 | AS72: 0 | AT72: 0 | AU72: 0 | AV72: 0 | AW72: 0 | AX72: 0 | AY72: 0 | AZ72: 0 | BA72: 0 | BB72: 0 | BC72: 0 | BD72: 0 | BE72: 0 | BF72: 0 | BG72: 0 | BH72: 0 | BI72: 0 | BJ72: 0 | BK72: 0 | BL72: 0 | BM72: 0 | BN72: 0 | BO72: 0 | BP72: 0 | BQ72: 0 | BR72: 0 | BS72: 0 | BT72: 0 | BU72: 0 | BV72: 61371 | BW72: 0 | BX72: 0 | BY72: 61371 | BZ72: 61371
A74: Total | C74: 348051 | D74: 141796 | E74: 15212 | F74: 18520 | G74: 174814 | H74: 111869 | I74: 16523 | J74: 435454 | K74: 75667 | L74: 435519 | M74: 83915 | N74: 15547 | O74: 63466 | P74: 51836 | Q74: 34396 | R74: 41952 | S74: 127062 | T74: 14213 | U74: 588162 | V74: 84734 | W74: 290927 | X74: 118525 | Y74: 56532 | Z74: 53734 | AA74: 160394 | AB74: 100211 | AC74: 209604 | AD74: 91739 | AE74: 138051 | AF74: 126429 | AG74: 108153 | AH74: 183858 | AI74: 216145 | AJ74: 113059 | AK74: 41613 | AL74: 68465 | AM74: 70840 | AN74: 298398 | AO74: 43404 | AP74: 429230 | AQ74: 702500 | AR74: 322829 | AS74: 20090 | AT74: 32676 | AU74: 85194 | AV74: 15307 | AW74: 166632 | AX74: 9631 | AY74: 29129 | AZ74: 103332 | BA74: 107503 | BB74: 270799 | BC74: 58848 | BD74: 89956 | BE74: 34915 | BF74: 92519 | BG74: 25361 | BH74: 105540 | BI74: 10513 | BJ74: 273272 | BK74: 64020 | BL74: 49718 | BM74: 120477 | BN74: 160147 | BO74: 19915 | BP74: 99032 | BQ74: 0 | BR74: 8867874 | BS74: 1722169 | BT74: 1671535 | BU74: 115048 | BV74: 5415523 | BW74: 1614782 | BX74: 144558 | BY74: 10683615 | BZ74: 19551489
A76: (1) Exportação de bens e serviços líquida de ajuste CIF/FOB.
A79: Valor adicionado
A80: Operações | C80: Valor adicionado | I80: Valor adicionado | Y80: Valor adicionado | AP80: Valor adicionado | BB80: Valor adicionado
C81: 0191 | D81: 0192 | E81: 0280 | F81: 0580 | G81: 0680 | H81: 0791 | I81: 0792 | J81: 1091 | K81: 1092 | L81: 1093 | M81: 1100 | N81: 1200 | O81: 1300 | P81: 1400 | Q81: 1500 | R81: 1600 | S81: 1700 | T81: 1800 | U81: 1991 | V81: 1992 | W81: 2091 | X81: 2092 | Y81: 2093 | Z81: 2100 | AA81: 2200 | AB81: 2300 | AC81: 2491 | AD81: 2492 | AE81: 2500 | AF81: 2600 | AG81: 2700 | AH81: 2800 | AI81: 2991 | AJ81: 2992 | AK81: 3000 | AL81: 3180 | AM81: 3300 | AN81: 3500 | AO81: 3680 | AP81: 4180 | AQ81: 4580 | AR81: 4900 | AS81: 5000 | AT81: 5100 | AU81: 5280 | AV81: 5500 | AW81: 5600 | AX81: 5800 | AY81: 5980 | AZ81: 6100 | BA81: 6280 | BB81: 6480 | BC81: 6800 | BD81: 6980 | BE81: 7180 | BF81: 7380 | BG81: 7700 | BH81: 7880 | BI81: 8000 | BJ81: 8400 | BK81: 8591 | BL81: 8592 | BM81: 8691 | BN81: 8692 | BO81: 9080 | BP81: 9480 | BQ81: 9700 | BR81: Total
C82: Agricultura, inclusive o apoio à agricultura e a pós-colheita | D82: Pecuária, inclusive o apoio à pecuária | E82: Produção florestal; pesca e aquicultura | F82: Extração de carvão mineral e de minerais não metálicos | G82: Extração de petróleo e gás, inclusive as atividades de apoio | H82: Extração de minério de ferro, inclusive beneficiamentos e a aglomeração | I82: Extração de minerais metálicos não ferrosos, inclusive beneficiamentos | J82: Abate e produtos de carne, inclusive os produtos do laticínio e da pesca | K82: Fabricação e refino de açúcar | L82: Outros produtos alimentares | M82: Fabricação de bebidas | N82: Fabricação de produtos do fumo | O82: Fabricação de produtos têxteis | P82: Confecção de artefatos do vestuário e acessórios | Q82: Fabricação de calçados e de artefatos de couro | R82: Fabricação de produtos da madeira | S82: Fabricação de celulose, papel e produtos de papel | T82: Impressão e reprodução de gravações | U82: Refino de petróleo e coquerias | V82: Fabricação de biocombustíveis | W82: Fabricação de químicos orgânicos e inorgânicos, resinas e elastômeros | X82: Fabricação de defensivos, desinfestantes, tintas e químicos diversos | Y82: Fabricação de produtos de limpeza, cosméticos/perfumaria e higiene pessoal | Z82: Fabricação de produtos farmoquímicos e farmacêuticos | AA82: Fabricação de produtos de borracha e de material plástico | AB82: Fabricação de produtos de minerais não metálicos | AC82: Produção de ferro gusa/ferroligas, siderurgia e tubos de aço sem costura | AD82: Metalurgia de metais não ferosos e a fundição de metais | AE82: Fabricação de produtos de metal, exceto máquinas e equipamentos | AF82: Fabricação de equipamentos de informática, produtos eletrônicos e ópticos | AG82: Fabricação de máquinas e equipamentos elétricos | AH82: Fabricação de máquinas e equipamentos mecânicos | AI82: Fabricação de automóveis, caminhões e ônibus, exceto peças | AJ82: Fabricação de peças e acessórios para veículos automotores | AK82: Fabricação de outros equipamentos de transporte, exceto veículos automotores | AL82: Fabricação de móveis e de produtos de indústrias diversas | AM82: Manutenção, reparação e instalação de máquinas e equipamentos | AN82: Energia elétrica, gás natural e outras utilidades | AO82: Água, esgoto e gestão de resíduos | AP82: Construção | AQ82: Comércio por atacado e varejo | AR82: Transporte terrestre | AS82: Transporte aquaviário | AT82: Transporte aéreo | AU82: Armazenamento, atividades auxiliares dos transportes e correio | AV82: Alojamento | AW82: Alimentação | AX82: Edição e edição integrada à impressão | AY82: Atividades de televisão, rádio, cinema e gravação/edição de som e imagem | AZ82: Telecomunicações | BA82: Desenvolvimento de sistemas e outros serviços de informação | BB82: Intermediação financeira, seguros e previdência complementar | BC82: Atividades imobiliárias | BD82: Atividades jurídicas, contábeis, consultoria e sedes de empresas | BE82: Serviços de arquitetura, engenharia, testes/análises técnicas e P & D | BF82: Outras atividades profissionais, científicas e técnicas | BG82: Aluguéis não imobiliários e gestão de ativos de propriedade intelectual | BH82: Outras atividades administrativas e serviços complementares | BI82: Atividades de vigilância, segurança e investigação | BJ82: Administração pública, defesa e seguridade social | BK82: Educação pública | BL82: Educação privada | BM82: Saúde pública | BN82: Saúde privada | BO82: Atividades artísticas, criativas e de espetáculos | BP82: Organizações associativas e outros serviços pessoais | BQ82: Serviços domésticos | BR82: 1277285
A83: Valor adicionado bruto ( PIB ) | C83: 421109 | D83: 130445 | E83: 39531 | F83: 11561 | G83: 231887 | H83: 167230 | I83: 14189 | J83: 59950 | K83: 18988 | L83: 78319 | M83: 26193 | N83: 3106 | O83: 19370 | P83: 28809 | Q83: 16343 | R83: 19564 | S83: 29864 | T83: 8119 | U83: 90157 | V83: 20994 | W83: 62229 | X83: 19572 | Y83: 11340 | Z83: 45544 | AA83: 37300 | AB83: 42799 | AC83: 96011 | AD83: 29466 | AE83: 51610 | AF83: 19947 | AG83: 29515 | AH83: 59125 | AI83: 25538 | AJ83: 32464 | AK83: 8912 | AL83: 44592 | AM83: 37099 | AN83: 157298 | AO83: 63684 | AP83: 275111 | AQ83: 965702 | AR83: 183535 | AS83: 14616 | AT83: 3073 | AU83: 102818 | AV83: 16415 | AW83: 120712 | AX83: 7995 | AY83: 17533 | AZ83: 79011 | BA83: 159992 | BB83: 447048 | BC83: 699465 | BD83: 195074 | BE83: 50176 | BF83: 53773 | BG83: 49842 | BH83: 213521 | BI83: 36376 | BJ83: 719944 | BK83: 340323 | BL83: 100728 | BM83: 158689 | BN83: 222222 | BO83: 22891 | BP83: 86270 | BQ83: 61371 | BR83: 7713999
A84: Remunerações | C84: 37950 | D84: 25160 | E84: 2882 | F84: 4882 | G84: 21242 | H84: 5777 | I84: 3331 | J84: 40203 | K84: 9426 | L84: 39201 | M84: 11397 | N84: 1988 | O84: 12601 | P84: 19120 | Q84: 10928 | R84: 8175 | S84: 16184 | T84: 5338 | U84: 12103 | V84: 8112 | W84: 15965 | X84: 11824 | Y84: 7306 | Z84: 15775 | AA84: 25874 | AB84: 23721 | AC84: 14974 | AD84: 7744 | AE84: 27076 | AF84: 10741 | AG84: 18582 | AH84: 35143 | AI84: 20439 | AJ84: 22668 | AK84: 8254 | AL84: 20315 | AM84: 18587 | AN84: 20258 | AO84: 25019 | AP84: 130162 | AQ84: 471788 | AR84: 96653 | AS84: 6472 | AT84: 6682 | AU84: 48512 | AV84: 10988 | AW84: 57472 | AX84: 6183 | AY84: 12175 | AZ84: 23331 | BA84: 81702 | BB84: 201153 | BC84: 9646 | BD84: 80109 | BE84: 24050 | BF84: 22628 | BG84: 14950 | BH84: 145387 | BI84: 32583 | BJ84: 603962 | BK84: 323126 | BL84: 87511 | BM84: 149825 | BN84: 122204 | BO84: 13514 | BP84: 44244 | BQ84: 61371 | BR84: 3534648
A85: Salários | C85: 32130 | D85: 21953 | E85: 2497 | F85: 3819 | G85: 16134 | H85: 4505 | I85: 2646 | J85: 31659 | K85: 6714 | L85: 30796 | M85: 8785 | N85: 1508 | O85: 10276 | P85: 15412 | Q85: 9104 | R85: 6732 | S85: 12680 | T85: 4388 | U85: 8760 | V85: 6140 | W85: 12076 | X85: 9101 | Y85: 5723 | Z85: 12102 | AA85: 20045 | AB85: 18923 | AC85: 11307 | AD85: 6216 | AE85: 21508 | AF85: 8468 | AG85: 14383 | AH85: 27444 | AI85: 15764 | AJ85: 18860 | AK85: 6705 | AL85: 16300 | AM85: 15342 | AN85: 14733 | AO85: 18965 | AP85: 107355 | AQ85: 373643 | AR85: 78295 | AS85: 5296 | AT85: 5574 | AU85: 37541 | AV85: 9134 | AW85: 48793 | AX85: 5210 | AY85: 10231 | AZ85: 17555 | BA85: 65562 | BB85: 153797 | BC85: 7572 | BD85: 65440 | BE85: 19296 | BF85: 18734 | BG85: 11963 | BH85: 117177 | BI85: 25808 | BJ85: 429084 | BK85: 260257 | BL85: 73352 | BM85: 122956 | BN85: 105371 | BO85: 11720 | BP85: 37798 | BQ85: 59897 | BR85: 2795014
A86: Contribuições sociais efetivas | C86: 5820 | D86: 3207 | E86: 385 | F86: 1063 | G86: 5108 | H86: 1272 | I86: 685 | J86: 8544 | K86: 2712 | L86: 8405 | M86: 2612 | N86: 480 | O86: 2325 | P86: 3708 | Q86: 1824 | R86: 1443 | S86: 3504 | T86: 950 | U86: 3343 | V86: 1972 | W86: 3889 | X86: 2723 | Y86: 1583 | Z86: 3673 | AA86: 5829 | AB86: 4798 | AC86: 3667 | AD86: 1528 | AE86: 5568 | AF86: 2273 | AG86: 4199 | AH86: 7699 | AI86: 4675 | AJ86: 3808 | AK86: 1549 | AL86: 4015 | AM86: 3245 | AN86: 5525 | AO86: 6054 | AP86: 22807 | AQ86: 98145 | AR86: 18358 | AS86: 1176 | AT86: 1108 | AU86: 10971 | AV86: 1854 | AW86: 8679 | AX86: 973 | AY86: 1944 | AZ86: 5776 | BA86: 16140 | BB86: 47356 | BC86: 2074 | BD86: 14669 | BE86: 4754 | BF86: 3894 | BG86: 2987 | BH86: 28210 | BI86: 6775 | BJ86: 88731 | BK86: 55672 | BL86: 14159 | BM86: 19588 | BN86: 16833 | BO86: 1794 | BP86: 6446 | BQ86: 1474 | BR86: 639009
A87: Previdência oficial /FGTS | C87: 5820 | D87: 3207 | E87: 385 | F87: 1053 | G87: 4097 | H87: 1223 | I87: 647 | J87: 8291 | K87: 2655 | L87: 8085 | M87: 2516 | N87: 435 | O87: 2271 | P87: 3666 | Q87: 1802 | R87: 1384 | S87: 3122 | T87: 910 | U87: 2000 | V87: 1952 | W87: 3494 | X87: 2411 | Y87: 1546 | Z87: 3417 | AA87: 5648 | AB87: 4653 | AC87: 3355 | AD87: 1443 | AE87: 5407 | AF87: 2206 | AG87: 4021 | AH87: 7342 | AI87: 4427 | AJ87: 3642 | AK87: 1454 | AL87: 3899 | AM87: 3124 | AN87: 4041 | AO87: 5385 | AP87: 22210 | AQ87: 96961 | AR87: 17574 | AS87: 1128 | AT87: 1085 | AU87: 9486 | AV87: 1807 | AW87: 8628 | AX87: 943 | AY87: 1873 | AZ87: 4576 | BA87: 15121 | BB87: 41014 | BC87: 2015 | BD87: 13441 | BE87: 4573 | BF87: 3792 | BG87: 2904 | BH87: 27696 | BI87: 6725 | BJ87: 86596 | BK87: 55338 | BL87: 14077 | BM87: 19567 | BN87: 16723 | BO87: 1741 | BP87: 6349 | BQ87: 1474 | BR87: 611853
A88: Previdência privada | C88: 0 | D88: 0 | E88: 0 | F88: 10 | G88: 1011 | H88: 49 | I88: 38 | J88: 253 | K88: 57 | L88: 320 | M88: 96 | N88: 45 | O88: 54 | P88: 42 | Q88: 22 | R88: 59 | S88: 382 | T88: 40 | U88: 1343 | V88: 20 | W88: 395 | X88: 312 | Y88: 37 | Z88: 256 | AA88: 181 | AB88: 145 | AC88: 312 | AD88: 85 | AE88: 161 | AF88: 67 | AG88: 178 | AH88: 357 | AI88: 248 | AJ88: 166 | AK88: 95 | AL88: 116 | AM88: 121 | AN88: 1484 | AO88: 669 | AP88: 597 | AQ88: 1184 | AR88: 784 | AS88: 48 | AT88: 23 | AU88: 1485 | AV88: 47 | AW88: 51 | AX88: 30 | AY88: 71 | AZ88: 1200 | BA88: 1019 | BB88: 6342 | BC88: 59 | BD88: 1228 | BE88: 181 | BF88: 102 | BG88: 83 | BH88: 514 | BI88: 50 | BJ88: 2135 | BK88: 334 | BL88: 82 | BM88: 21 | BN88: 110 | BO88: 53 | BP88: 97 | BQ88: 0 | BR88: 27156
A89: Contribuições sociais imputadas | C89: 0 | D89: 0 | E89: 0 | F89: 0 | G89: 0 | H89: 0 | I89: 0 | J89: 0 | K89: 0 | L89: 0 | M89: 0 | N89: 0 | O89: 0 | P89: 0 | Q89: 0 | R89: 0 | S89: 0 | T89: 0 | U89: 0 | V89: 0 | W89: 0 | X89: 0 | Y89: 0 | Z89: 0 | AA89: 0 | AB89: 0 | AC89: 0 | AD89: 0 | AE89: 0 | AF89: 0 | AG89: 0 | AH89: 0 | AI89: 0 | AJ89: 0 | AK89: 0 | AL89: 0 | AM89: 0 | AN89: 0 | AO89: 0 | AP89: 0 | AQ89: 0 | AR89: 0 | AS89: 0 | AT89: 0 | AU89: 0 | AV89: 0 | AW89: 0 | AX89: 0 | AY89: 0 | AZ89: 0 | BA89: 0 | BB89: 0 | BC89: 0 | BD89: 0 | BE89: 0 | BF89: 0 | BG89: 0 | BH89: 0 | BI89: 0 | BJ89: 86147 | BK89: 7197 | BL89: 0 | BM89: 7281 | BN89: 0 | BO89: 0 | BP89: 0 | BQ89: 0 | BR89: 100625
A90: Excedente operacional bruto e rendimento misto bruto | C90: 387668 | D90: 104422 | E90: 36464 | F90: 6459 | G90: 208581 | H90: 159899 | I90: 10623 | J90: 16083 | K90: 8407 | L90: 34467 | M90: 13705 | N90: 983 | O90: 6140 | P90: 9028 | Q90: 4952 | R90: 10843 | S90: 12579 | T90: 2534 | U90: 76087 | V90: 12070 | W90: 44152 | X90: 6759 | Y90: 3494 | Z90: 28971 | AA90: 9935 | AB90: 17937 | AC90: 79135 | AD90: 20949 | AE90: 23055 | AF90: 7925 | AG90: 9878 | AH90: 22082 | AI90: 3503 | AJ90: 8612 | AK90: 249 | AL90: 23406 | AM90: 17962 | AN90: 133278 | AO90: 37659 | AP90: 141157 | AQ90: 478681 | AR90: 83255 | AS90: 7668 | AT90: -4181 | AU90: 52461 | AV90: 5073 | AW90: 61681 | AX90: 1631 | AY90: 4481 | AZ90: 52994 | BA90: 75511 | BB90: 239754 | BC90: 689238 | BD90: 111759 | BE90: 25863 | BF90: 30311 | BG90: 34254 | BH90: 63863 | BI90: 2789 | BJ90: 115808 | BK90: 17197 | BL90: 10805 | BM90: 8864 | BN90: 96532 | BO90: 9097 | BP90: 40908 | BQ90: 0 | BR90: 4078389
A91: Rendimento misto bruto | C91: 184642 | D91: 69026 | E91: 16923 | F91: 269 | G91: 0 | H91: 0 | I91: 0 | J91: 406 | K91: 0 | L91: 4027 | M91: 27 | N91: 0 | O91: 1035 | P91: 4774 | Q91: 733 | R91: 1708 | S91: 309 | T91: 522 | U91: 0 | V91: 0 | W91: 0 | X91: 0 | Y91: 613 | Z91: 0 | AA91: 389 | AB91: 856 | AC91: 0 | AD91: -19 | AE91: 2556 | AF91: 0 | AG91: 0 | AH91: 0 | AI91: 0 | AJ91: 32 | AK91: 1 | AL91: 1416 | AM91: 4388 | AN91: 0 | AO91: 1511 | AP91: 66152 | AQ91: 82623 | AR91: 24784 | AS91: 271 | AT91: 0 | AU91: 1972 | AV91: 1448 | AW91: 39681 | AX91: 22 | AY91: 1137 | AZ91: 388 | BA91: 13885 | BB91: 3201 | BC91: 3741 | BD91: 37402 | BE91: 10984 | BF91: 6539 | BG91: 588 | BH91: 6740 | BI91: 924 | BJ91: 0 | BK91: 0 | BL91: 8883 | BM91: 0 | BN91: 58199 | BO91: 5814 | BP91: 29999 | BQ91: 0 | BR91: 701521
A92: Excedente operacional bruto (EOB) | C92: 203026 | D92: 35396 | E92: 19541 | F92: 6190 | G92: 208581 | H92: 159899 | I92: 10623 | J92: 15677 | K92: 8407 | L92: 30440 | M92: 13678 | N92: 983 | O92: 5105 | P92: 4254 | Q92: 4219 | R92: 9135 | S92: 12270 | T92: 2012 | U92: 76087 | V92: 12070 | W92: 44152 | X92: 6759 | Y92: 2881 | Z92: 28971 | AA92: 9546 | AB92: 17081 | AC92: 79135 | AD92: 20968 | AE92: 20499 | AF92: 7925 | AG92: 9878 | AH92: 22082 | AI92: 3503 | AJ92: 8580 | AK92: 248 | AL92: 21990 | AM92: 13574 | AN92: 133278 | AO92: 36148 | AP92: 75005 | AQ92: 396058 | AR92: 58471 | AS92: 7397 | AT92: -4181 | AU92: 50489 | AV92: 3625 | AW92: 22000 | AX92: 1609 | AY92: 3344 | AZ92: 52606 | BA92: 61626 | BB92: 236553 | BC92: 685497 | BD92: 74357 | BE92: 14879 | BF92: 23772 | BG92: 33666 | BH92: 57123 | BI92: 1865 | BJ92: 115808 | BK92: 17197 | BL92: 1922 | BM92: 8864 | BN92: 38333 | BO92: 3283 | BP92: 10909 | BQ92: 0 | BR92: 3376868
A93: Outros impostos sobre a produção | C93: 3349 | D93: 909 | E93: 219 | F93: 237 | G93: 2064 | H93: 1561 | I93: 235 | J93: 3687 | K93: 1186 | L93: 4679 | M93: 1100 | N93: 135 | O93: 635 | P93: 661 | Q93: 463 | R93: 555 | S93: 1123 | T93: 247 | U93: 2008 | V93: 838 | W93: 2120 | X93: 989 | Y93: 540 | Z93: 804 | AA93: 1524 | AB93: 1168 | AC93: 1916 | AD93: 781 | AE93: 1497 | AF93: 1281 | AG93: 1075 | AH93: 1953 | AI93: 1655 | AJ93: 1233 | AK93: 423 | AL93: 879 | AM93: 550 | AN93: 3794 | AO93: 1014 | AP93: 3891 | AQ93: 15409 | AR93: 4071 | AS93: 476 | AT93: 579 | AU93: 1858 | AV93: 354 | AW93: 1559 | AX93: 181 | AY93: 877 | AZ93: 2703 | BA93: 2779 | BB93: 6141 | BC93: 581 | BD93: 3206 | BE93: 857 | BF93: 834 | BG93: 680 | BH93: 4284 | BI93: 1004 | BJ93: 174 | BK93: 0 | BL93: 2412 | BM93: 0 | BN93: 3523 | BO93: 280 | BP93: 1118 | BQ93: 0 | BR93: 110918
A94: Outros subsídios à produção | C94: -7858 | D94: -46 | E94: -34 | F94: -17 | G94: 0 | H94: -7 | I94: 0 | J94: -23 | K94: -31 | L94: -28 | M94: -9 | N94: 0 | O94: -6 | P94: 0 | Q94: 0 | R94: -9 | S94: -22 | T94: 0 | U94: -41 | V94: -26 | W94: -8 | X94: 0 | Y94: 0 | Z94: -6 | AA94: -33 | AB94: -27 | AC94: -14 | AD94: -8 | AE94: -18 | AF94: 0 | AG94: -20 | AH94: -53 | AI94: -59 | AJ94: -49 | AK94: -14 | AL94: -8 | AM94: 0 | AN94: -32 | AO94: -8 | AP94: -99 | AQ94: -176 | AR94: -444 | AS94: 0 | AT94: -7 | AU94: -13 | AV94: 0 | AW94: 0 | AX94: 0 | AY94: 0 | AZ94: -17 | BA94: 0 | BB94: 0 | BC94: 0 | BD94: 0 | BE94: -594 | BF94: 0 | BG94: -42 | BH94: -13 | BI94: 0 | BJ94: 0 | BK94: 0 | BL94: 0 | BM94: 0 | BN94: -37 | BO94: 0 | BP94: 0 | BQ94: 0 | BR94: -9956
... A96: Fator trabalho (ocupações) | C96: 6934294 | D96: 5393173 | E96: 815655 | F96: 110127 | G96: 55195 | H96: 42815 | I96: 35085 | J96: 860656 | K96: 139807 | L96: 1272409 | M96: 188767 | N96: 17515 | O96: 638518 | P96: 1655089 | Q96: 455637 | R96: 389391 | S96: 216547 | T96: 168568 | U96: 22483 | V96: 108126 | W96: 112336 | X96: 97429 | Y96: 138125 | Z96: 113456 | AA96: 444332 | AB96: 609593 | AC96: 131519 | AD96: 108045 | AE96: 702971 | AF96: 122788 | AG96: 228003 | AH96: 436572 | AI96: 155333 | AJ96: 304453 | AK96: 87198 | AL96: 773017 | AM96: 673031 | AN96: 174830 | AO96: 606919 | AP96: 8267084 | AQ96: 18825573 | AR96: 4123552 | AS96: 48865 | AT96: 51770 | AU96: 937458 | AV96: 402267 | AW96: 4980988 | AX96: 126997 | AY96: 154532 | AZ96: 322694 | BA96: 962675 | BB96: 1519655 | BC96: 518258 | BD96: 2206221 | BE96: 777044 | BF96: 850029 | BG96: 320139 | BH96: 4539907 | BI96: 785372 | BJ96: 4692057 | BK96: 4226629 | BL96: 2757268 | BM96: 2306888 | BN96: 3908377 | BO96: 937222 | BP96: 4342454 | BQ96: 5633396 | BR96: 105065178

Sheet Usos Nacional
A1: Tabela 3 - Demanda da produção nacional a preços básicos - 2021 (Preços correntes)
A2: Unidade de Medida: R$ 1.000.000,00
A3: Código da Atividade Nível 67 | B3: Descrição da Atividade Nível 67 | C3: Consumo intermediário das atividades | L3: Consumo intermediário das atividades | U3: Consumo intermediário das atividades | AD3: Consumo intermediário das atividades | AM3: Consumo intermediário das atividades | AV3: Consumo intermediário das atividades | BE3: Consumo intermediário das atividades | BR3: Consumo intermediário das atividades | BS3: Demanda final | BZ3: Demanda Total
C4: 0191 | D4: 0192 | E4: 0280 | F4: 0580 | G4: 0680 | H4: 0791 | I4: 0792 | J4: 1091 | K4: 1092 | L4: 1093 | M4: 1100 | N4: 1200 | O4: 1300 | P4: 1400 | Q4: 1500 | R4: 1600 | S4: 1700 | T4: 1800 | U4: 1991 | V4: 1992 | W4: 2091 | X4: 2092 | Y4: 2093 | Z4: 2100 | AA4: 2200 | AB4: 2300 | AC4: 2491 | AD4: 2492 | AE4: 2500 | AF4: 2600 | AG4: 2700 | AH4: 2800 | AI4: 2991 | AJ4: 2992 | AK4: 3000 | AL4: 3180 | AM4: 3300 | AN4: 3500 | AO4: 3680 | AP4: 4180 | AQ4: 4580 | AR4: 4900 | AS4: 5000 | AT4: 5100 | AU4: 5280 | AV4: 5500 | AW4: 5600 | AX4: 5800 | AY4: 5980 | AZ4: 6100 | BA4: 6280 | BB4: 6480 | BC4: 6800 | BD4: 6980 | BE4: 7180 | BF4: 7380 | BG4: 7700 | BH4: 7880 | BI4: 8000 | BJ4: 8400 | BK4: 8591 | BL4: 8592 | BM4: 8691 | BN4: 8692 | BO4: 9080 | BP4: 9480 | BQ4: 9700 | BR4: Total do produto | BS4: Exportação de bens e serviços (1) | BT4: Consumo do governo | BU4: Consumo das ISFLSF | BV4: Consumo das famílias | BW4: Formação bruta de capital fixo | BX4: Variação de estoque | BY4: Demanda final
C5: Agricultura, inclusive o apoio à agricultura e a pós-colheita | D5: Pecuária, inclusive o apoio à pecuária | E5: Produção florestal; pesca e aquicultura | F5: Extração de carvão mineral e de minerais não metálicos | G5: Extração de petróleo e gás, inclusive as atividades de apoio | H5: Extração de minério de ferro, inclusive beneficiamentos e a aglomeração | I5: Extração de minerais metálicos não ferrosos, inclusive beneficiamentos | J5: Abate e produtos de carne, inclusive os produtos do laticínio e da pesca | K5: Fabricação e refino de açúcar | L5: Outros produtos alimentares | M5: Fabricação de bebidas | N5: Fabricação de produtos do fumo | O5: Fabricação de produtos têxteis | P5: Confecção de artefatos do vestuário e acessórios | Q5: Fabricação de calçados e de artefatos de couro | R5: Fabricação de produtos da madeira | S5: Fabricação de celulose, papel e produtos de papel | T5: Impressão e reprodução de gravações | U5: Refino de petróleo e coquerias | V5: Fabricação de biocombustíveis | W5: Fabricação de químicos orgânicos e inorgânicos, resinas e elastômeros | X5: Fabricação de defensivos, desinfestantes, tintas e químicos diversos | Y5: Fabricação de produtos de limpeza, cosméticos/perfumaria e higiene pessoal | Z5: Fabricação de produtos farmoquímicos e farmacêuticos | AA5: Fabricação de produtos de borracha e de material plástico | AB5: Fabricação de produtos de minerais não metálicos | AC5: Produção de ferro gusa/ferroligas, siderurgia e tubos de aço sem costura | AD5: Metalurgia de metais não ferosos e a fundição de metais | AE5: Fabricação de produtos de metal, exceto máquinas e equipamentos | AF5: Fabricação de equipamentos de informática, produtos eletrônicos e ópticos | AG5: Fabricação de máquinas e equipamentos elétricos | AH5: Fabricação de máquinas e equipamentos mecânicos | AI5: Fabricação de automóveis, caminhões e ônibus, exceto peças | AJ5: Fabricação de peças e acessórios para veículos automotores | AK5: Fabricação de outros equipamentos de transporte, exceto veículos automotores | AL5: Fabricação de móveis e de produtos de indústrias diversas | AM5: Manutenção, reparação e instalação de máquinas e equipamentos | AN5: Energia elétrica, gás natural e outras utilidades | AO5: Água, esgoto e gestão de resíduos | AP5: Construção | AQ5: Comércio por atacado e varejo | AR5: Transporte terrestre | AS5: Transporte aquaviário | AT5: Transporte aéreo | AU5: Armazenamento, atividades auxiliares dos transportes e correio | AV5: Alojamento | AW5: Alimentação | AX5: Edição e edição integrada à impressão | AY5: Atividades de televisão, rádio, cinema e gravação/edição de som e imagem | AZ5: Telecomunicações | BA5: Desenvolvimento de sistemas e outros serviços de informação | BB5: Intermediação financeira, seguros e previdência complementar | BC5: Atividades imobiliárias | BD5: Atividades jurídicas, contábeis, consultoria e sedes de empresas | BE5: Serviços de arquitetura, engenharia, testes/análises técnicas e P & D | BF5: Outras atividades profissionais, científicas e técnicas | BG5: Aluguéis não imobiliários e gestão de ativos de propriedade intelectual | BH5: Outras atividades administrativas e serviços complementares | BI5: Atividades de vigilância, segurança e investigação | BJ5: Administração pública, defesa e seguridade social | BK5: Educação pública | BL5: Educação privada | BM5: Saúde pública | BN5: Saúde privada | BO5: Atividades artísticas, criativas e de espetáculos | BP5: Organizações associativas e outros serviços pessoais | BQ5: Serviços domésticos
A6: 0191 | B6: Agricultura, inclusive o apoio à agricultura e a pós-colheita | C6: 16983.248 | D6: 11985.712 | E6: 219.75068 | F6: 2.4446189 | G6: 10.070758 | H6: 18.831943 | I6: 2.5990457 | J6: 13773.569 | K6: 40352.239 | L6: 144426.08 | M6: 3476.913 | N6: 7355.7567 | O6: 12151.148 | P6: 826.38093 | Q6: 8.2014628 | R6: 139.51108 | S6: 262.77827 | T6: 0.304826 | U6: 17.25054 | V6: 36913.89 | W6: 18.947496 | X6: 22.664833 | Y6: 4.2399617 | Z6: 28.012324 | AA6: 38.054853 | AB6: 24.278499 | AC6: 61.220022 | AD6: 39.645899 | AE6: 6.2489184 | AF6: 0.42540657 | AG6: 0.50577092 | AH6: 1.4629336 | AI6: 0.727852 | AJ6: 0.6072642 | AK6: 0.62477459 | AL6: 17.623419 | AM6: 0.12588053 | AN6: 0.96140956 | AO6: 77.1686 | AP6: 415.16463 | AQ6: 19996.859 | AR6: 2.0821477 | AS6: 0.11349113 | AT6: 0.34712637 | AU6: 19.797532 | AV6: 436.34999 | AW6: 5788.0274 | AX6: 0.21432553 | AY6: 0.95087961 | AZ6: 45.613297 | BA6: 5.3546602 | BB6: 16.327988 | BC6: 19.471191 | BD6: 13.650209 | BE6: 16.444522 | BF6: 2.0917106 | BG6: 1.4085659 | BH6: 215.55613 | BI6: 0.48304966 | BJ6: 1299.8306 | BK6: 517.26448 | BL6: 92.627137 | BM6: 674.39034 | BN6: 279.3363 | BO6: 5.6342112 | BP6: 421.3359 | BQ6: 0 | BR6: 319556.96 | BS6: 281689.04 | BT6: 103.83756 | BU6: 0 | BV6: 109557.21 | BW6: 4584.3616 | BX6: 53668.597 | BY6: 449603.04 | BZ6: 769160
A7: 0192 | B7: Pecuária, inclusive o apoio à pecuária | C7: 1874.4991 | D7: 10816.761 | E7: 281.81532 | F7: 6.1725583 | G7: 24.822897 | H7: 33.799522 | I7: 4.7537388 | J7: 160629.4 | K7: 227.40568 | L7: 8330.1001 | M7: 86.564137 | N7: 341.71434 | O7: 481.1748 | P7: 385.60221 | Q7: 8.8757715 | R7: 279.87373 | S7: 466.44825 | T7: 0.52309191 | U7: 1.3173976 | V7: 426.28389 | W7: 52.668934 | X7: 11.010084 | Y7: 10.846313 | Z7: 13.774988 | AA7: 57.558185 | AB7: 110.71892 | AC7: 130.39124 | AD7: 76.286199 | AE7: 5.0184879 | AF7: 0.86395703 | AG7: 1.5189714 | AH7: 2.8508173 | AI7: 1.3332407 | AJ7: 1.3350736 | AK7: 0.94154857 | AL7: 10.494813 | AM7: 0.29735101 | AN7: 1.2626597 | AO7: 12.046952 | AP7: 818.19236 | AQ7: 717.91888 | AR7: 2.069901 | AS7: 0.09428022 | AT7: 0.35233015 | AU7: 32.880639 | AV7: 518.2171 | AW7: 2589.1852 | AX7: 0.32953478 | AY7: 1.4691327 | AZ7: 81.394049 | BA7: 8.7423479 | BB7: 25.271438 | BC7: 35.848426 | BD7: 10.594616 | BE7: 21.314907 | BF7: 9.587625 | BG7: 1.9193137 | BH7: 40.599942 | BI7: 0.59076754 | BJ7: 428.53962 | BK7: 152.29689 | BL7: 29.553771 | BM7: 187.68002 | BN7: 133.61652 | BO7: 5.0786782 | BP7: 59.635323 | BQ7: 0 | BR7: 191122.1 | BS7: 12861.731 | BT7: 5.7739432 | BU7: 0 | BV7: 38242.643 | BW7: 28770.17 | BX7: 1238.5801 | BY7: 81118.898 | BZ7: 272241
A8: 0280 | B8: Produção florestal; pesca e aquicultura | C8: 1688.505 | D8: 1700.0692 | E8: 2524.3458 | F8: 2.4213056 | G8: 1.9440342 | H8: 2.5696446 | I8: 0.35119115 | J8: 2907.4262 | K8: 1.2932914 | L8: 339.88065 | M8: 17.352535 | N8: 17.945642 | O8: 26.683225 | P8: 6.6290399 | Q8: 4.5406797 | R8: 3296.8902 | S8: 5362.179 | T8: 0.041243098 | U8: 0.10967613 | V8: 13.029998 | W8: 334.06231 | X8: 3.5972105 | Y8: 0.14048076 | Z8: 0.20953324 | AA8: 606.36748 | AB8: 116.63391 | AC8: 1428.9898 | AD8: 5.6256292 | AE8: 5.7305413 | AF8: 0.092514461 | AG8: 0.14463256 | AH8: 0.31847275 | AI8: 0.14276052 | AJ8: 0.1289516 | AK8: 0.080979667 | AL8: 2.0563199 | AM8: 0.035468854 | AN8: 0.17288639 | AO8: 0.82680888 | AP8: 959.18056 | AQ8: 176.83439 | AR8: 0.22782768 | AS8: 0.010855826 | AT8: 0.03237169 | AU8: 2.5500623 | AV8: 42.962256 | AW8: 473.16136 | AX8: 0.03913256 | AY8: 0.15461913 | AZ8: 6.0155938 | BA8: 0.84624151 | BB8: 2.0933957 | BC8: 2.7185941 | BD8: 0.95679367 | BE8: 3.9464391 | BF8: 0.24312274 | BG8: 0.1953608 | BH8: 2.8141439 | BI8: 0.060217608 | BJ8: 114.75741 | BK8: 71.48497 | BL8: 7.0629457 | BM8: 93.786223 | BN8: 15.585997 | BO8: 0.48511086 | BP8: 4.3423871 | BQ8: 0 | BR8: 22402.113 | BS8: 6680.5288 | BT8: 2.8092416 | BU8: 0 | BV8: 24518.908 | BW8: 2061.3206 | BX8: -922.67916 | BY8: 32340.887 | BZ8: 54743
A9: 0580 | B9: Extração de carvão mineral e de minerais não metálicos | C9: 149.30588 | D9: 819.54278 | E9: 22.086799 | F9: 411.91151 | G9: 820.36059 | H9: 1.353807 | I9: 5.7939027 | J9: 104.86371 | K9: 20.752811 | L9: 326.85423 | M9: 27.084261 | N9: 0.028390051 | O9: 0.43891063 | P9: 0.20827377 | Q9: 0.32981256 | R9: 0.18427365 | S9: 15.974644 | T9: 1.0945434 | U9: 11.368187 | V9: 586.10946 | W9: 1865.4502 | X9: 133.68133 | Y9: 6.0951226 | Z9: 1.3907623 | AA9: 6.6222774 | AB9: 7666.4636 | AC9: 1964.2616 | AD9: 625.11207 | AE9: 14.376461 | AF9: 0.72291195 | AG9: 81.703797 | AH9: 8.7163353 | AI9: 24.680999 | AJ9: 56.982151 | AK9: 4.3157239 | AL9: 47.668446 | AM9: 4.5992116 | AN9: 360.93967 | AO9: 625.18773 | AP9: 7223.8027 | AQ9: 135.8118 | AR9: 0.71747171 | AS9: 0.14348154 | AT9: 0.047165095 | AU9: 8.6290968 | AV9: 2.9290383 | AW9: 14.153068 | AX9: 0.098858205 | AY9: 0.13386898 | AZ9: 0.58754712 | BA9: 0.90582523 | BB9: 1.2183112 | BC9: 264.72213 | BD9: 1.3763689 | BE9: 1.3755185 | BF9: 0.49763655 | BG9: 0.372002 | BH9: 1.968481 | BI9: 0.10602792 | BJ9: 97.280215 | BK9: 21.476332 | BL9: 1.4444516 | BM9: 14.347021 | BN9: 4.4411685 | BO9: 0.99521823 | BP9: 2.7906141 | BQ9: 0 | BR9: 24626.989 | BS9: 3920.876 | BT9: 0.062149683 | BU9: 0 | BV9: 184.28283 | BW9: 19.98871 | BX9: 1328.8016 | BY9: 5454.0114 | BZ9: 30081
A10: 0680 | B10: Extração de petróleo e gás, inclusive as atividades de apoio | C10: 29.49878 | D10: 18.332812 | E10: 1.3232854 | F10: 4.3985043 | G10: 9720.6025 | H10: 1297.6564 | I10: 66.366476 | J10: 36.20082 | K10: 1.2469837 | L10: 316.2072 | M10: 65.334294 | N10: 0.24801618 | O10: 54.769255 | P10: 1.1817856 | Q10: 1.7218888 | R10: 28.81376 | S10: 360.28359 | T10: 0.60773737 | U10: 162686.39 | V10: 1.7993496 | W10: 942.57373 | X10: 50.767453 | Y10: 15.10105 | Z10: 16.846368 | AA10: 65.127525 | AB10: 340.86298 | AC10: 237.59364 | AD10: 156.27751 | AE10: 179.13834 | AF10: 0.9111877 | AG10: 22.558512 | AH10: 60.532043 | AI10: 28.301664 | AJ10: 66.047687 | AK10: 1.5220496 | AL10: 2.6674614 | AM10: 23.018644 | AN10: 10436.112 | AO10: 1553.9862 | AP10: 1775.4246 | AQ10: 211.91325 | AR10: 147.80096 | AS10: 2.551954 | AT10: 0.32073307 | AU10: 144.30287 | AV10: 3.1956247 | AW10: 38.591914 | AX10: 0.61893466 | AY10: 1.3472219 | AZ10: 193.39728 | BA10: 8.1188392 | BB10: 13.10314 | BC10: 4.8264331 | BD10: 14.2719 | BE10: 80.371917 | BF10: 4.7809737 | BG10: 5.9231612 | BH10: 15.500035 | BI10: 0.93974617 | BJ10: 3256.2142 | BK10: 38.204307 | BL10: 14.315439 | BM10: 3.3085933 | BN10: 8.1286354 | BO10: 10.547889 | BP10: 35.877657 | BQ10: 0 | BR10: 194926.82 | BS10: 165143.33 | BT10: 0 | BU10: 0 | BV10: 540.1911 | BW10: 56116.761 | BX10: -10026.109 | BY10: 211774.18 | BZ10: 406701
A11: 0791 | B11: Extração de minério de ferro, inclusive beneficiamentos e a aglomeração | C11: 0.57938893 | D11: 1.1251802 | E11: 0.072169608 | F11: 0.076912666 | G11: 13.183717 | H11: 7085.1147 | I11: 96.663036 | J11: 1.1569486 | K11: 0.10384379 | L11: 1.3084139 | M11: 0.36478133 | N11: 0.10093587 | O11: 0.21336357 | P11: 0.086208664 | Q11: 0.095419597 | R11: 0.19038569 | S11: 0.91082844 | T11: 0.62982936 | U11: 0.29501346 | V11: 0.01756351 | W11: 0.53316218 | X11: 0.53170564 | Y11: 0.26368343 | Z11: 0.99040312 | AA11: 0.46420167 | AB11: 359.91118 | AC11: 53412.974 | AD11: 93.64361 | AE11: 5.540624 | AF11: 0.50556913 | AG11: 13.293703 | AH11: 21.480475 | AI11: 3.9077494 | AJ11: 6.2448253 | AK11: 1.927061 | AL11: 4.6684771 | AM11: 8.1808277 | AN11: 0.31495945 | AO11: 20.41212 | AP11: 177.92838 | AQ11: 4.3795196 | AR11: 1.3879322 | AS11: 0.20282441 | AT11: 0.00429307 | AU11: 9.8628108 | AV11: 0.34065219 | AW11: 3.2937783 | AX11: 0.015945303 | AY11: 0.021579946 | AZ11: 24.521045 | BA11: 0.776436 | BB11: 5.1043242 | BC11: 8.2290382 | BD11: 1.9471677 | BE11: 13.594755 | BF11: 0.12079092 | BG11: 0.20164959 | BH11: 9.0296511 | BI11: 0.080307835 | BJ11: 57.497406 | BK11: 2.7379924 | BL11: 0.25688564 | BM11: 18.170858 | BN11: 0.16365502 | BO11: 0.89916666 | BP11: 0.55834767 | BQ11: 0 | BR11: 61499.405 | BS11: 223601.7 | BT11: 0 | BU11: 0 | BV11: 12.07304 | BW11: 1676.7646 | BX11: -7690.9424 | BY11: 217599.6 | BZ11: 279099
A12: 0792 | B12: Extração de minerais metálicos não ferrosos, inclusive beneficiamentos | C12: 2.1655422 | D12: 0.90008044 | E12: 0.032068865 | F12: 0.041061086 | G12: 84.367646 | H12: 45.880089 | I12: 1118.6471 | J12: 6.0059433 | K12: 0.10754783 | L12: 10.739416 | M12: 1.0615946 | N12: 0.01030973 | O12: 0.051172839 | P12: 0.033658592 | Q12: 0.044480465 | R12: 0.022742834 | S12: 6.0892226 | T12: 4.4153165 | U12: 0.019045003 | V12: 0.015104694 | W12: 5.8977151 | X12: 4.1912476 | Y12: 0.34820229 | Z12: 0.34250802 | AA12: 2.2227501 | AB12: 76.716171 | AC12: 3239.7423 | AD12: 6179.2444 | AE12: 46.301518 | AF12: 2.5968499 | AG12: 107.1882 | AH12: 18.783825 | AI12: 12.598912 | AJ12: 63.086285 | AK12: 13.310796 | AL12: 40.447 | AM12: 5.9567097 | AN12: 0.31379227 | AO12: 1.7287655 | AP12: 35.099867 | AQ12: 0.72400194 | AR12: 0.38967243 | AS12: 0.0031921229 | AT12: 0.001654412 | AU12: 0.0078616196 | AV12: 0.094119893 | AW12: 0.37689696 | AX12: 0.0053356851 | AY12: 0.0039184165 | AZ12: 0.025889595 | BA12: 0.047137503 | BB12: 0.011482987 | BC12: 0.67079816 | BD12: 0.0091292269 | BE12: 1.1874369 | BF12: 0.022013134 | BG12: 0.016737153 | BH12: 0.067187298 | BI12: 0.0019909712 | BJ12: 0.27972888 | BK12: 0.10290386 | BL12: 0.006321713 | BM12: 0.20327234 | BN12: 0.20872474 | BO12: 0.0024562729 | BP12: 0.084460187 | BQ12: 0 | BR12: 11141.321 | BS12: 22406.65 | BT12: 0.011762298 | BU12: 0 | BV12: 9.584355 | BW12: 11.059945 | BX12: -2856.6269 | BY12: 19570.679 | BZ12: 30712
A13: 1091 | B13: Abate e produtos de carne, inclusive os produtos do laticínio e da pesca | C13: 136.21376 | D13: 3742.7747 | E13: 43.042407 | F13: 13.343762 | G13: 26.276405 | H13: 29.104733 | I13: 3.9926176 | J13: 49307.519 | K13: 4.2868967 | L13: 5384.7848 | M13: 87.335647 | N13: 2.632209 | O13: 16.246749 | P13: 16.040822 | Q13: 2163.3049 | R13: 13.445183 | S13: 44.594234 | T13: 4.5450933 | U13: 12.253028 | V13: 1651.9569 | W13: 120.03882 | X13: 104.02358 | Y13: 4300.0108 | Z13: 23.906052 | AA13: 45.150497 | AB13: 22.565238 | AC13: 43.104933 | AD13: 24.759095 | AE13: 154.37462 | AF13: 21.867359 | AG13: 33.293451 | AH13: 60.79784 | AI13: 46.120428 | AJ13: 26.34768 | AK13: 7.3882532 | AL13: 25.703959 | AM13: 21.306485 | AN13: 11.932754 | AO13: 8.0272317 | AP13: 91.941222 | AQ13: 840.88235 | AR13: 50.824007 | AS13: 1.1806123 | AT13: 1.1425436 | AU13: 9.7052381 | AV13: 770.44717 | AW13: 27183.738 | AX13: 2.6103824 | AY13: 2.5734043 | AZ13: 10.191194 | BA13: 10.62026 | BB13: 13.167844 | BC13: 5.7644768 | BD13: 12.429631 | BE13: 10.525853 | BF13: 14.839884 | BG13: 5.8961914 | BH13: 15.535367 | BI13: 1.5355256 | BJ13: 4104.9441 | BK13: 2006.4323 | BL13: 403.54655 | BM13: 2722.3547 | BN13: 1170.964 | BO13: 13.324956 | BP13: 330.03943 | BQ13: 0 | BR13: 107611.57 | BS13: 114882.43 | BT13: 70.217559 | BU13: 0 | BV13: 270103.11 | BW13: 427.82258 | BX13: 2308.8532 | BY13: 387792.43 | BZ13: 495404
A14: 1092 | B14: Fabricação e refino de açúcar | C14: 90.728566 | D14: 140.50226 | E14: 5.4568608 | F14: 3.1733891 | G14: 444.37559 | H14: 29.612264 | I14: 4.2537674 | J14: 539.34238 | K14: 2290.1806 | L14: 5421.2738 | M14: 1269.664 | N14: 0.59231108 | O14: 3.1506205 | P14: 3.5323977 | Q14: 1.9130326 | R14: 55.472191 | S14: 12.798776 | T14: 0.77068982 | U14: 15960.357 | V14: 2092.1556 | W14: 221.80144 | X14: 760.26757 | Y14: 1008.0422 | Z14: 469.90668 | AA14: 7.1123186 | AB14: 5.4721386 | AC14: 8.4230472 | AD14: 5.3009613 | AE14: 30.39397 | AF14: 4.7139805 | AG14: 10.074713 | AH14: 77.560745 | AI14: 23.212165 | AJ14: 6.5795129 | AK14: 2.8624136 | AL14: 6.9335699 | AM14: 31.720875 | AN14: 8.7337847 | AO14: 37.711324 | AP14: 275.17903 | AQ14: 848.72802 | AR14: 506.35664 | AS14: 9.6730084 | AT14: 16.807293 | AU14: 55.676507 | AV14: 18.972679 | AW14: 1053.2817 | AX14: 6.3573846 | AY14: 12.064268 | AZ14: 28.282193 | BA14: 48.622071 | BB14: 81.947024 | BC14: 24.108709 | BD14: 91.360629 | BE14: 112.115 | BF14: 40.765186 | BG14: 105.10253 | BH14: 130.35174 | BI14: 51.440529 | BJ14: 470.73815 | BK14: 116.79621 | BL14: 20.075405 | BM14: 127.42724 | BN14: 82.845465 | BO14: 27.0218 | BP14: 118.46907 | BQ14: 0 | BR14: 35576.695 | BS14: 41898.62 | BT14: 1.1864416 | BU14: 0 | BV14: 16229.303 | BW14: 419.37535 | BX14: 529.82024 | BY14: 59078.305 | BZ14: 94655
A15: 1093 | B15: Outros produtos alimentares | C15: 3807.8645 | D15: 25100.827 | E15: 1866.0999 | F15: 239.28199 | G15: 336.80538 | H15: 171.20655 | I15: 27.248698 | J15: 50391.391 | K15: 70.350487 | L15: 53685.329 | M15: 3898.3971 | N15: 10.629717 | O15: 77.471686 | P15: 67.575224 | Q15: 61.306273 | R15: 124.12229 | S15: 1584.3168 | T15: 31.563225 | U15: 5745.3708 | V15: 9950.4345 | W15: 1063.6459 | X15: 1595.858 | Y15: 1765.3907 | Z15: 327.19688 | AA15: 283.15825 | AB15: 166.57773 | AC15: 235.08283 | AD15: 102.88165 | AE15: 269.44887 | AF15: 83.841801 | AG15: 146.75012 | AH15: 285.84438 | AI15: 200.27273 | AJ15: 132.32522 | AK15: 32.595007 | AL15: 135.451 | AM15: 106.39838 | AN15: 49.407444 | AO15: 65.968274 | AP15: 556.52505 | AQ15: 6793.1773 | AR15: 372.14949 | AS15: 8.2242144 | AT15: 37.073184 | AU15: 77.409484 | AV15: 342.96535 | AW15: 15847.239 | AX15: 12.200224 | AY15: 13.858754 | AZ15: 56.956867 | BA15: 54.102776 | BB15: 219.11292 | BC15: 47.112003 | BD15: 108.1253 | BE15: 73.234057 | BF15: 137.41367 | BG15: 61.523043 | BH15: 112.08746 | BI15: 23.913334 | BJ15: 2669.6796 | BK15: 1670.2387 | BL15: 257.73315 | BM15: 3356.8053 | BN15: 944.66893 | BO15: 72.327304 | BP15: 1149.2398 | BQ15: 0 | BR15: 199370.78 | BS15: 77106.36 | BT15: 88.140545 | BU15: 0 | BV15: 227312.15 | BW15: 1037.9258 | BX15: 8922.6411 | BY15: 314467.22 | BZ15: 513838
A16: 1100 | B16: Fabricação de bebidas | C16: 85.531334 | D16: 41.633263 | E16: 3.1642292 | F16: 20.500362 | G16: 39.744404 | H16: 42.582993 | I16: 6.0942845 | J16: 665.18744 | K16: 6.8436188 | L16: 182.94739 | M16: 11254.462 | N16: 3.1672467 | O16: 18.809279 | P16: 19.88288 | Q16: 11.473347 | R16: 19.013764 | S16: 41.117011 | T16: 6.1558924 | U16: 62.088242 | V16: 13.383064 | W16: 56.019072 | X16: 57.898283 | Y16: 27.872455 | Z16: 23.791517 | AA16: 51.282686 | AB16: 29.283901 | AC16: 58.979819 | AD16: 28.172648 | AE16: 69.635033 | AF16: 28.869686 | AG16: 46.056218 | AH16: 102.37369 | AI16: 64.777377 | AJ16: 37.209383 | AK16: 12.458144 | AL16: 31.260211 | AM16: 38.053617 | AN16: 20.974714 | AO16: 12.617817 | AP16: 164.62422 | AQ16: 431.91083 | AR16: 71.529081 | AS16: 2.0217305 | AT16: 4.8039406 | AU16: 28.549051 | AV16: 554.76229 | AW16: 28692.89 | AX16: 3.8808298 | AY16: 5.1784291 | AZ16: 20.61972 | BA16: 24.330831 | BB16: 120.4679 | BC16: 15.254434 | BD16: 40.164703 | BE16: 10.231844 | BF16: 22.309774 | BG16: 10.849933 | BH16: 37.402943 | BI16: 3.5596007 | BJ16: 225.64458 | BK16: 126.60631 | BL16: 45.614288 | BM16: 184.40784 | BN16: 227.6293 | BO16: 51.444157 | BP16: 41.986084 | BQ16: 0 | BR16: 44510.044 | BS16: 4505.4091 | BT16: 7.0030882 | BU16: 0 | BV16: 59461.758 | BW16: 303.98517 | BX16: 1319.8005 | BY16: 65597.956 | BZ16: 110108
A17: 1200 | B17: Fabricação de produtos do fumo | C17: 11.703952 | D17: 2.4525136 | E17: 0.18668056 | F17: 0.10992015 | G17: 1.4239832 | H17: 2.1427722 | I17: 0.19648759 | J17: 5.2286196 | K17: 0.2513572 | L17: 5.4368854 | M17: 0.78670177 | N17: 1159.5021 | O17: 0.91756204 | P17: 0.87099422 | Q17: 0.70247423 | R17: 1.0900639 | S17: 5.0446459 | T17: 0.59596589 | U17: 0.51841263 | V17: 0.32784857 | W17: 2.2141087 | X17: 1.0848205 | Y17: 1.2785608 | Z17: 1.3336186 | AA17: 2.5177282 | AB17: 1.8841641 | AC17: 1.8374244 | AD17: 1.3370819 | AE17: 1.8654848 | AF17: 1.3849226 | AG17: 1.8178364 | AH17: 4.2812198 | AI17: 2.584409 | AJ17: 1.6253305 | AK17: 0.35686415 | AL17: 1.3561526 | AM17: 1.4233622 | AN17: 0.55321957 | AO17: 0.30567607 | AP17: 3.9493841 | AQ17: 7.9220524 | AR17: 2.4933952 | AS17: 0.088823967 | AT17: 0.044895928 | AU17: 0.43656833 | AV17: 0.15689437 | AW17: 2.2644883 | AX17: 0.32267065 | AY17: 0.14029127 | AZ17: 0.49103246 | BA17: 0.89145594 | BB17: 0.76938341 | BC17: 0.27024925 | BD17: 0.78671625 | BE17: 1.6584944 | BF17: 0.75862148 | BG17: 0.44226984 | BH17: 1.4080182 | BI17: 0.068941674 | BJ17: 1.038207 | BK17: 0.67382173 | BL17: 0.45948648 | BM17: 1.2367028 | BN17: 1.8270459 | BO17: 0.18522605 | BP17: 0.67957642 | BQ17: 0 | BR17: 1261.9966 | BS17: 7600.173 | BT17: 0.27837438 | BU17: 0 | BV17: 9772.5831 | BW17: 91.02225 | BX17: -73.053342 | BY17: 17391.003 | BZ17: 18653
... A72: 9700 | B72: Serviços domésticos | C72: 0 | D72: 0 | E72: 0 | F72: 0 | G72: 0 | H72: 0 | I72: 0 | J72: 0 | K72: 0 | L72: 0 | M72: 0 | N72: 0 | O72: 0 | P72: 0 | Q72: 0 | R72: 0 | S72: 0 | T72: 0 | U72: 0 | V72: 0 | W72: 0 | X72: 0 | Y72: 0 | Z72: 0 | AA72: 0 | AB72: 0 | AC72: 0 | AD72: 0 | AE72: 0 | AF72: 0 | AG72: 0 | AH72: 0 | AI72: 0 | AJ72: 0 | AK72: 0 | AL72: 0 | AM72: 0 | AN72: 0 | AO72: 0 | AP72: 0 | AQ72: 0 | AR72: 0 | AS72: 0 | AT72: 0 | AU72: 0 | AV72: 0 | AW72: 0 | AX72: 0 | AY72: 0 | AZ72: 0 | BA72: 0 | BB72: 0 | BC72: 0 | BD72: 0 | BE72: 0 | BF72: 0 | BG72: 0 | BH72: 0 | BI72: 0 | BJ72: 0 | BK72: 0 | BL72: 0 | BM72: 0 | BN72: 0 | BO72: 0 | BP72: 0 | BQ72: 0 | BR72: 0 | BS72: 0 | BT72: 0 | BU72: 0 | BV72: 61371 | BW72: 0 | BX72: 0 | BY72: 61371 | BZ72: 61371
A74: Total | C74: 267696.18 | D74: 117914 | E74: 12044.581 | F74: 14919.073 | G74: 125505.51 | H74: 88951.956 | I74: 12644.582 | J74: 411719.85 | K74: 71068.651 | L74: 385720.33 | M74: 75762.029 | N74: 14612.443 | O74: 49543.071 | P74: 40491.606 | Q74: 28536.543 | R74: 35523.047 | S74: 102820.28 | T74: 11181.089 | U74: 455337.28 | V74: 80447.196 | W74: 170302.07 | X74: 75248.819 | Y74: 43105.762 | Z74: 36844.539 | AA74: 114071.08 | AB74: 84487.561 | AC74: 175953.59 | AD74: 66521.512 | AE74: 112845.23 | AF74: 50493.5 | AG74: 77404.173 | AH74: 129315.29 | AI74: 156953.28 | AJ74: 85136.654 | AK74: 18672.9 | AL74: 53162.504 | AM74: 42847.65 | AN74: 240027.69 | AO74: 35662.779 | AP74: 340516.66 | AQ74: 592897.91 | AR74: 278463 | AS74: 14841.582 | AT74: 19741.553 | AU74: 70766.946 | AV74: 13227.462 | AW74: 135460.59 | AX74: 7465.1085 | AY74: 24239.063 | AZ74: 88739.856 | BA74: 78891.467 | BB74: 231762.31 | BC74: 45383.345 | BD74: 72963.425 | BE74: 25675.101 | BF74: 80909.81 | BG74: 19275.816 | BH74: 82699.152 | BI74: 8388.2897 | BJ74: 231281.6 | BK74: 55586.978 | BL74: 41094.956 | BM74: 93156.64 | BN74: 126446.97 | BO74: 17011.308 | BP74: 78127.118 | BQ74: 0 | BR74: 7046509.9 | BS74: 1708558.6 | BT74: 1664998.8 | BU74: 115048 | BV74: 4577557.5 | BW74: 1337749.2 | BX74: 131451.02 | BY74: 9535363.1 | BZ74: 16581873
A76: (1) Exportação de bens e serviços líquida de ajuste CIF/FOB.

Sheet Usos Importado
A1: Tabela 4 - Demanda por bens importados a preços básicos - 2021 (Preços correntes)
A2: Unidade de Medida: R$ 1.000.000,00
A3: Código da Atividade Nível 67 | B3: Descrição da Atividade Nível 67 | C3: Consumo intermediário das atividades | L3: Consumo intermediário das atividades | U3: Consumo intermediário das atividades | AD3: Consumo intermediário das atividades | AM3: Consumo intermediário das atividades | AV3: Consumo intermediário das atividades | BE3: Consumo intermediário das atividades | BR3: Consumo intermediário das atividades | BS3: Demanda final | BZ3: Demanda Total
C4: 0191 | D4: 0192 | E4: 0280 | F4: 0580 | G4: 0680 | H4: 0791 | I4: 0792 | J4: 1091 | K4: 1092 | L4: 1093 | M4: 1100 | N4: 1200 | O4: 1300 | P4: 1400 | Q4: 1500 | R4: 1600 | S4: 1700 | T4: 1800 | U4: 1991 | V4: 1992 | W4: 2091 | X4: 2092 | Y4: 2093 | Z4: 2100 | AA4: 2200 | AB4: 2300 | AC4: 2491 | AD4: 2492 | AE4: 2500 | AF4: 2600 | AG4: 2700 | AH4: 2800 | AI4: 2991 | AJ4: 2992 | AK4: 3000 | AL4: 3180 | AM4: 3300 | AN4: 3500 | AO4: 3680 | AP4: 4180 | AQ4: 4580 | AR4: 4900 | AS4: 5000 | AT4: 5100 | AU4: 5280 | AV4: 5500 | AW4: 5600 | AX4: 5800 | AY4: 5980 | AZ4: 6100 | BA4: 6280 | BB4: 6480 | BC4: 6800 | BD4: 6980 | BE4: 7180 | BF4: 7380 | BG4: 7700 | BH4: 7880 | BI4: 8000 | BJ4: 8400 | BK4: 8591 | BL4: 8592 | BM4: 8691 | BN4: 8692 | BO4: 9080 | BP4: 9480 | BQ4: 9700 | BR4: Total do produto | BS4: Exportação de bens e serviços (1) | BT4: Consumo do governo | BU4: Consumo das ISFLSF | BV4: Consumo das famílias | BW4: Formação bruta de capital fixo | BX4: Variação de estoque | BY4: Demanda final
C5: Agricultura, inclusive o apoio à agricultura e a pós-colheita | D5: Pecuária, inclusive o apoio à pecuária | E5: Produção florestal; pesca e aquicultura | F5: Extração de carvão mineral e de minerais não metálicos | G5: Extração de petróleo e gás, inclusive as atividades de apoio | H5: Extração de minério de ferro, inclusive beneficiamentos e a aglomeração | I5: Extração de minerais metálicos não ferrosos, inclusive beneficiamentos | J5: Abate e produtos de carne, inclusive os produtos do laticínio e da pesca | K5: Fabricação e refino de açúcar | L5: Outros produtos alimentares | M5: Fabricação de bebidas | N5: Fabricação de produtos do fumo | O5: Fabricação de produtos têxteis | P5: Confecção de artefatos do vestuário e acessórios | Q5: Fabricação de calçados e de artefatos de couro | R5: Fabricação de produtos da madeira | S5: Fabricação de celulose, papel e produtos de papel | T5: Impressão e reprodução de gravações | U5: Refino de petróleo e coquerias | V5: Fabricação de biocombustíveis | W5: Fabricação de químicos orgânicos e inorgânicos, resinas e elastômeros | X5: Fabricação de defensivos, desinfestantes, tintas e químicos diversos | Y5: Fabricação de produtos de limpeza, cosméticos/perfumaria e higiene pessoal | Z5: Fabricação de produtos farmoquímicos e farmacêuticos | AA5: Fabricação de produtos de borracha e de material plástico | AB5: Fabricação de produtos de minerais não metálicos | AC5: Produção de ferro gusa/ferroligas, siderurgia e tubos de aço sem costura | AD5: Metalurgia de metais não ferosos e a fundição de metais | AE5: Fabricação de produtos de metal, exceto máquinas e equipamentos | AF5: Fabricação de equipamentos de informática, produtos eletrônicos e ópticos | AG5: Fabricação de máquinas e equipamentos elétricos | AH5: Fabricação de máquinas e equipamentos mecânicos | AI5: Fabricação de automóveis, caminhões e ônibus, exceto peças | AJ5: Fabricação de peças e acessórios para veículos automotores | AK5: Fabricação de outros equipamentos de transporte, exceto veículos automotores | AL5: Fabricação de móveis e de produtos de indústrias diversas | AM5: Manutenção, reparação e instalação de máquinas e equipamentos | AN5: Energia elétrica, gás natural e outras utilidades | AO5: Água, esgoto e gestão de resíduos | AP5: Construção | AQ5: Comércio por atacado e varejo | AR5: Transporte terrestre | AS5: Transporte aquaviário | AT5: Transporte aéreo | AU5: Armazenamento, atividades auxiliares dos transportes e correio | AV5: Alojamento | AW5: Alimentação | AX5: Edição e edição integrada à impressão | AY5: Atividades de televisão, rádio, cinema e gravação/edição de som e imagem | AZ5: Telecomunicações | BA5: Desenvolvimento de sistemas e outros serviços de informação | BB5: Intermediação financeira, seguros e previdência complementar | BC5: Atividades imobiliárias | BD5: Atividades jurídicas, contábeis, consultoria e sedes de empresas | BE5: Serviços de arquitetura, engenharia, testes/análises técnicas e P & D | BF5: Outras atividades profissionais, científicas e técnicas | BG5: Aluguéis não imobiliários e gestão de ativos de propriedade intelectual | BH5: Outras atividades administrativas e serviços complementares | BI5: Atividades de vigilância, segurança e investigação | BJ5: Administração pública, defesa e seguridade social | BK5: Educação pública | BL5: Educação privada | BM5: Saúde pública | BN5: Saúde privada | BO5: Atividades artísticas, criativas e de espetáculos | BP5: Organizações associativas e outros serviços pessoais | BQ5: Serviços domésticos
A6: 0191 | B6: Agricultura, inclusive o apoio à agricultura e a pós-colheita | C6: 1048.4146 | D6: 1194.0373 | E6: 46.986612 | F6: 0.069282444 | G6: 0.14006215 | H6: 0.075487628 | I6: 0.0070315284 | J6: 354.31798 | K6: 0.055528921 | L6: 21093.365 | M6: 612.23556 | N6: 50.815629 | O6: 271.58866 | P6: 159.71023 | Q6: 1.1789919 | R6: 1.5637413 | S6: 4.0622333 | T6: 0.0048006305 | U6: 0.17537318 | V6: 252.84682 | W6: 10.157374 | X6: 1.461388 | Y6: 0.34430016 | Z6: 5.6061577 | AA6: 14.775499 | AB6: 0.97997667 | AC6: 0.98492574 | AD6: 0.20380157 | AE6: 0.98590908 | AF6: 0.052607795 | AG6: 0.080588279 | AH6: 0.15796896 | AI6: 0.05497379 | AJ6: 0.046811889 | AK6: 0.019107794 | AL6: 2.2860813 | AM6: 0.027347019 | AN6: 0.09266796 | AO6: 4.8314782 | AP6: 39.827368 | AQ6: 1794.1113 | AR6: 0.17228743 | AS6: 0.0041224556 | AT6: 0.027648099 | AU6: 0.18074885 | AV6: 20.821989 | AW6: 295.49021 | AX6: 0.025978351 | AY6: 0.064975452 | AZ6: 0.075030291 | BA6: 0.44803537 | BB6: 0.39288024 | BC6: 0.28896167 | BD6: 0.45555051 | BE6: 0.29538511 | BF6: 0.19957929 | BG6: 0.31367854 | BH6: 10.63331 | BI6: 0.028453127 | BJ6: 244.21627 | BK6: 35.850961 | BL6: 2.7654708 | BM6: 43.606951 | BN6: 16.809914 | BO6: 0.1455447 | BP6: 25.114021 | BQ6: 0 | BR6: 27667.167 | BS6: 0.0025130854 | BT6: 42.43198 | BU6: 0 | BV6: 4419.4098 | BW6: 5.062739 | BX6: -7316.3888 | BY6: -2849.4817 | BZ6: 24817.685
A7: 0192 | B7: Pecuária, inclusive o apoio à pecuária | C7: 81.613205 | D7: 139.0558 | E7: 86.067357 | F7: 0.036477 | G7: 0.43279059 | H7: 0.24186688 | I7: 0.020991412 | J7: 270.10943 | K7: 0.1095157 | L7: 739.42961 | M7: 23.092611 | N7: 3.1416399 | O7: 90.563673 | P7: 74.601395 | Q7: 0.72152781 | R7: 3.1100091 | S7: 4.139431 | T7: 0.012456687 | U7: 0.045167685 | V7: 10.373233 | W7: 45.927398 | X7: 0.96167105 | Y7: 1.1445611 | Z7: 2.8891546 | AA7: 26.273117 | AB7: 5.0564844 | AC7: 2.6508936 | AD7: 1.0370319 | AE7: 0.9685563 | AF7: 0.17025401 | AG7: 0.30342376 | AH7: 0.49825871 | AI7: 0.17717882 | AJ7: 0.15701608 | AK7: 0.050731797 | AL7: 1.3421213 | AM7: 0.088442131 | AN7: 0.2631969 | AO7: 0.24099423 | AP7: 75.779119 | AQ7: 68.47946 | AR7: 0.32732423 | AS7: 0.010366925 | AT7: 0.078023407 | AU7: 0.39459586 | AV7: 7.4204904 | AW7: 66.337018 | AX7: 0.08000793 | AY7: 0.18382867 | AZ7: 0.14167602 | BA7: 1.1563733 | BB7: 1.2025256 | BC7: 0.22749224 | BD7: 0.66867309 | BE7: 0.61003191 | BF7: 0.38780852 | BG7: 0.39324343 | BH7: 0.9068431 | BI7: 0.071083484 | BJ7: 11.387378 | BK7: 2.7673321 | BL7: 0.9034525 | BM7: 3.1608731 | BN7: 1.157688 | BO7: 0.25432048 | BP7: 9.1010751 | BQ7: 0 | BR7: 1870.7068 | BS7: 0.0041694372 | BT7: 1.347521 | BU7: 0 | BV7: 468.30645 | BW7: 85.446244 | BX7: -204.89565 | BY7: 350.20874 | BZ7: 2220.9155
A8: 0280 | B8: Produção florestal; pesca e aquicultura | C8: 485.44199 | D8: 437.30693 | E8: 1128.4701 | F8: 0.012321196 | G8: 0.051334284 | H8: 0.028690012 | I8: 0.0024929626 | J8: 817.60624 | K8: 0.010910054 | L8: 70.006005 | M8: 1.3371911 | N8: 1.4528016 | O8: 10.153961 | P8: 2.4967035 | Q8: 2.0113896 | R8: 36.147265 | S8: 37.056393 | T8: 0.0014834039 | U8: 0.0053914909 | V8: 0.34918426 | W8: 58.109877 | X8: 0.26626999 | Y8: 0.017217886 | Z8: 0.053423862 | AA8: 296.80725 | AB8: 0.4068356 | AC8: 17.749608 | AD8: 0.084823423 | AE8: 3.875726 | AF8: 0.020192 | AG8: 0.031351999 | AH8: 0.059518525 | AI8: 0.021120123 | AJ8: 0.017354758 | AK8: 0.0061903762 | AL8: 0.82684907 | AM8: 0.010489178 | AN8: 0.031786062 | AO8: 0.012125003 | AP8: 5.6493092 | AQ8: 69.017761 | AR8: 0.039962407 | AS8: 0.0012348623 | AT8: 0.008633719 | AU8: 0.047165664 | AV8: 13.714538 | AW8: 145.70666 | AX8: 0.0094965457 | AY8: 0.022076956 | AZ8: 0.016992756 | BA8: 0.13772182 | BB8: 0.14118116 | BC8: 0.028850254 | BD8: 0.080862679 | BE8: 1.2774057 | BF8: 0.046487092 | BG8: 0.047824606 | BH8: 0.074513154 | BI8: 0.0084594475 | BJ8: 36.728034 | BK8: 22.948137 | BL8: 2.4977256 | BM8: 23.298805 | BN8: 5.2050654 | BO8: 0.027997118 | BP8: 1.0030072 | BQ8: 0 | BR8: 3736.1427 | BS8: 5.7115578e-05 | BT8: 0.03253795 | BU8: 0 | BV8: 2124.4097 | BW8: 0.21148823 | BX8: -28.727695 | BY8: 2095.9261 | BZ8: 5832.0688
A9: 0580 | B9: Extração de carvão mineral e de minerais não metálicos | C9: 37.385769 | D9: 10.507568 | E9: 6.6717131 | F9: 0.19413267 | G9: 2.9519344 | H9: 0.818346 | I9: 12.557139 | J9: 30.288985 | K9: 4.3048447 | L9: 72.718606 | M9: 4.7731549 | N9: 0.00067650782 | O9: 0.2312264 | P9: 0.0065570054 | Q9: 0.20779516 | R9: 0.022552448 | S9: 8.4193946 | T9: 0.53853477 | U9: 82.338656 | V9: 97.506434 | W9: 3345.246 | X9: 22.423397 | Y9: 2.1450091 | Z9: 0.49616818 | AA9: 2.4894295 | AB9: 394.70705 | AC9: 12628.549 | AD9: 1073.8473 | AE9: 9.0468293 | AF9: 0.62667095 | AG9: 35.463453 | AH9: 7.2533734 | AI9: 5.6011124 | AJ9: 107.39166 | AK9: 2.1166293 | AL9: 14.623132 | AM9: 2.7636673 | AN9: 3488.6665 | AO9: 1.4100663 | AP9: 358.29793 | AQ9: 2.4013184 | AR9: 0.072886182 | AS9: 0.024042 | AT9: 0.0014087693 | AU9: 0.091692928 | AV9: 0.26786559 | AW9: 1.1461962 | AX9: 0.0062766093 | AY9: 0.0054395812 | AZ9: 0.025723333 | BA9: 0.064732076 | BB9: 0.0057369958 | BC9: 0.9782458 | BD9: 0.10653501 | BE9: 10.121006 | BF9: 0.041011738 | BG9: 0.087921158 | BH9: 0.29567477 | BI9: 0.0047334447 | BJ9: 0.47833017 | BK9: 0.29336037 | BL9: 0.03896961 | BM9: 0.71254609 | BN9: 0.28277332 | BO9: 0.027576525 | BP9: 0.66512688 | BQ9: 0 | BR9: 21893.855 | BS9: 0 | BT9: 0.0015561352 | BU9: 0 | BV9: 9.3166823 | BW9: 4.0709915 | BX9: -229.14471 | BY9: -215.75548 | BZ9: 21678.1
A10: 0680 | B10: Extração de petróleo e gás, inclusive as atividades de apoio | C10: 16.844194 | D10: 9.4696957 | E10: 0.86243124 | F10: 0.33785636 | G10: 72.411233 | H10: 147.7419 | I10: 8.8517758 | J10: 60.988034 | K10: 0.0795513 | L10: 575.53239 | M10: 119.91586 | N10: 0.004874367 | O10: 98.345246 | P10: 0.046251326 | Q10: 0.8244219 | R10: 54.416159 | S10: 659.80367 | T10: 0.064722488 | U10: 26895.286 | V10: 0.14291045 | W10: 1729.4218 | X10: 73.955264 | Y10: 20.162956 | Z10: 28.832649 | AA10: 86.079995 | AB10: 561.4615 | AC10: 319.03388 | AD10: 258.84212 | AE10: 327.14203 | AF10: 0.23197531 | AG10: 24.748367 | AH10: 90.83765 | AI10: 45.003283 | AJ10: 115.54841 | AK10: 1.1891235 | AL10: 0.84413192 | AM10: 31.175841 | AN10: 19647.289 | AO10: 1.7666054 | AP10: 18.631166 | AQ10: 48.208953 | AR10: 32.336608 | AS10: 1.4010293 | AT10: 0.008731546 | AU10: 2.1049855 | AV10: 0.17425635 | AW10: 11.294907 | AX10: 0.028612603 | AY10: 0.088790178 | AZ10: 0.27856141 | BA10: 0.53512266 | BB10: 0.057765254 | BC10: 0.92952228 | BD10: 1.1081317 | BE10: 3.4277246 | BF10: 0.48421084 | BG10: 1.9077801 | BH10: 2.9833185 | BI10: 0.035077111 | BJ10: 3.9909885 | BK10: 0.71946584 | BL10: 0.31371874 | BM10: 0.39959808 | BN10: 0.61789334 | BO10: 0.2995999 | BP10: 1.740923 | BQ10: 0 | BR10: 52219.643 | BS10: 0 | BT10: 0 | BU10: 0 | BV10: 112.48187 | BW10: 124.91646 | BX10: -2632.2478 | BY10: -2394.8495 | BZ10: 49824.793
A11: 0791 | B11: Extração de minério de ferro, inclusive beneficiamentos e a aglomeração | C11: 0.01043888 | D11: 0.029330215 | E11: 0.0049650709 | F11: 0.065808618 | G11: 7.7778545 | H11: 9.1067815 | I11: 7.5570608 | J11: 0.40073212 | K11: 0.00039804711 | L11: 0.66117379 | M11: 0.00014391792 | N11: 5.6548691e-05 | O11: 0.00031712009 | P11: 0.00055047844 | Q11: 0.00022828191 | R11: 0.10705881 | S11: 0.36275082 | T11: 0.27660199 | U11: 0.00044554383 | V11: 0.00053072548 | W11: 0.04014846 | X11: 0.28941351 | Y11: 0.00024207671 | Z11: 0.010063668 | AA11: 0.23824566 | AB11: 0.27701604 | AC11: 41.851028 | AD11: 51.316486 | AE11: 4.4186226 | AF11: 0.41120342 | AG11: 14.168084 | AH11: 31.364552 | AI11: 2.1170892 | AJ11: 4.1338234 | AK11: 1.4075744 | AL11: 4.4831449 | AM11: 12.560705 | AN11: 0.044857314 | AO11: 0.25927139 | AP11: 24.996746 | AQ11: 0.72639227 | AR11: 0.064529228 | AS11: 0.24180004 | AT11: 9.2364822e-05 | AU11: 0.25674451 | AV11: 0.0076934803 | AW11: 0.023853295 | AX11: 0.00016437869 | AY11: 0.00065800685 | AZ11: 0.051449817 | BA11: 0.0077993105 | BB11: 0.0051078126 | BC11: 0.076403356 | BD11: 0.018766575 | BE11: 0.0091677025 | BF11: 0.010236319 | BG11: 0.014174742 | BH11: 0.75020574 | BI11: 0.000404282 | BJ11: 0.054613173 | BK11: 0.0086160664 | BL11: 0.0055427339 | BM11: 0.08346571 | BN11: 0.0077472821 | BO11: 0.004199895 | BP11: 0.0084871058 | BQ11: 0 | BR11: 223.18986 | BS11: 328.02988 | BT11: 0 | BU11: 0 | BV11: 1.1698618 | BW11: 50.730817 | BX11: -1.8928592 | BY11: 378.0377 | BZ11: 601.22756
A12: 0792 | B12: Extração de minerais metálicos não ferrosos, inclusive beneficiamentos | C12: 2.3881041 | D12: 0.60069519 | E12: 0.027345556 | F12: 0.013521413 | G12: 0.25598336 | H12: 14.756074 | I12: 851.95365 | J12: 3.5362682 | K12: 0.076573004 | L12: 6.1067465 | M12: 0.1800608 | N12: 6.1746635e-05 | O12: 0.020682937 | P12: 0.00020429786 | Q12: 0.018765453 | R12: 0.00081947661 | S12: 3.8491692 | T12: 2.44729 | U12: 0.00018149227 | V12: 0.0022990761 | W12: 8.7751288 | X12: 3.1879634 | Y12: 0.15654904 | Z12: 0.12270016 | AA12: 1.2459196 | AB12: 9.2973974 | AC12: 825.32596 | AD12: 4145.6707 | AE12: 38.330999 | AF12: 2.9530782 | AG12: 121.07889 | AH12: 19.61786 | AI12: 7.3249778 | AJ12: 39.112569 | AK12: 8.587603 | AL12: 39.726859 | AM12: 6.4250148 | AN12: 0.14566891 | AO12: 1.4779336 | AP12: 35.75209 | AQ12: 0.49405896 | AR12: 0.19242637 | AS12: 0.0014921481 | AT12: 0 | AU12: 0.0015557453 | AV12: 0.0097078183 | AW12: 0.031364062 | AX12: 8.3339831e-05 | AY12: 0.00013144311 | AZ12: 0.00097830917 | BA12: 0.00014687593 | BB12: 3.5409484e-05 | BC12: 0.56309033 | BD12: 0.00010057714 | BE12: 0.00082827915 | BF12: 0.0005379307 | BG12: 0 | BH12: 0.0091806634 | BI12: 1.6415223e-05 | BJ12: 0.14518823 | BK12: 0.039183364 | BL12: 5.1047792e-06 | BM12: 0.026885542 | BN12: 0.013127362 | BO12: 4.1159928e-06 | BP12: 0.048654871 | BQ12: 0 | BR12: 6202.1292 | BS12: 0.022540932 | BT12: 0 | BU12: 0 | BV12: 0.21463103 | BW12: 0.31315319 | BX12: -427.33081 | BY12: -426.78048 | BZ12: 5775.3487
A13: 1091 | B13: Abate e produtos de carne, inclusive os produtos do laticínio e da pesca | C13: 4.7685357 | D13: 338.42697 | E13: 1.3137472 | F13: 5.5567337 | G13: 8.5815987 | H13: 4.3154694 | I13: 0.84818848 | J13: 1431.1378 | K13: 0.26917168 | L13: 472.54172 | M13: 5.4996006 | N13: 0.05320949 | O13: 4.3378161 | P13: 0.94429721 | Q13: 9.8910599 | R13: 2.5189516 | S13: 10.010462 | T13: 0.52540537 | U13: 1.2316859 | V13: 150.19837 | W13: 58.379017 | X13: 45.252506 | Y13: 457.61343 | Z13: 18.118132 | AA13: 11.39902 | AB13: 1.8200438 | AC13: 3.6243925 | AD13: 1.6441396 | AE13: 16.108643 | AF13: 0.29675294 | AG13: 1.4574541 | AH13: 3.045735 | AI13: 1.1151867 | AJ13: 0.44890676 | AK13: 0.295871 | AL13: 2.6072742 | AM13: 1.6982042 | AN13: 0.48284476 | AO13: 1.3280296 | AP13: 3.0723275 | AQ13: 14.395874 | AR13: 0.25063698 | AS13: 0.035314682 | AT13: 0.0096051905 | AU13: 0.34944761 | AV13: 22.099242 | AW13: 826.39648 | AX13: 0.045843131 | AY13: 0.095025268 | AZ13: 0.4769539 | BA13: 0.32134021 | BB13: 0.15318483 | BC13: 0.57647656 | BD13: 0.65512029 | BE13: 0.377684 | BF13: 0.46940306 | BG13: 0.53051145 | BH13: 0.97063464 | BI13: 0.040321939 | BJ13: 87.58557 | BK13: 44.620259 | BL13: 10.128485 | BM13: 85.044579 | BN13: 32.090867 | BO13: 0.20550723 | BP13: 12.233483 | BQ13: 0 | BR13: 4222.9366 | BS13: 2.213914 | BT13: 4.5517433 | BU13: 0 | BV13: 6352.9846 | BW13: 4.5406209 | BX13: 36.936905 | BY13: 6401.2278 | BZ13: 10624.164
A14: 1092 | B14: Fabricação e refino de açúcar | C14: 1.5806838 | D14: 1.6277177 | E14: 0.0173471 | F14: 0.23370625 | G14: 32.551443 | H14: 29.567456 | I14: 3.1000573 | J14: 4.5983091 | K14: 7.9070635 | L14: 26.051369 | M14: 5.6870133 | N14: 0.0073785889 | O14: 0.057167853 | P14: 0.060909511 | Q14: 0.026539283 | R14: 0.42042876 | S14: 0.18783049 | T14: 0.0042273621 | U14: 151.4466 | V14: 12.933992 | W14: 30.066398 | X14: 3.8279073 | Y14: 13.537593 | Z14: 5.9353432 | AA14: 0.4709834 | AB14: 0.11678689 | AC14: 0.081094118 | AD14: 0.11739974 | AE14: 0.96524597 | AF14: 0.31808322 | AG14: 1.7491715 | AH14: 102.03593 | AI14: 4.5749816 | AJ14: 0.23348793 | AK14: 1.5434525 | AL14: 0.031891063 | AM14: 41.402955 | AN14: 0.13129407 | AO14: 0.41819184 | AP14: 15.702086 | AQ14: 12.157187 | AR14: 7.8608994 | AS14: 0.92965402 | AT14: 0.0020504991 | AU14: 1.0773207 | AV14: 0.22215127 | AW14: 11.98876 | AX14: 0.072675967 | AY14: 0.06606481 | AZ14: 0.36112673 | BA14: 0.22034126 | BB14: 3.3172244 | BC14: 0.54636847 | BD14: 4.3003893 | BE14: 3.2757145 | BF14: 1.4109857 | BG14: 5.8298198 | BH14: 7.5744919 | BI14: 1.8815114 | BJ14: 3.7424802 | BK14: 0.48408479 | BL14: 0.24655826 | BM14: 0.46705396 | BN14: 2.2535009 | BO14: 0.38925882 | BP14: 6.5407381 | BQ14: 0 | BR14: 578.54593 | BS14: 0 | BT14: 0.00099837709 | BU14: 0 | BV14: 124.94567 | BW14: 177.24471 | BX14: -26.040638 | BY14: 276.15074 | BZ14: 854.69667
A15: 1093 | B15: Outros produtos alimentares | C15: 269.5848 | D15: 801.24564 | E15: 62.569884 | F15: 96.50101 | G15: 89.827177 | H15: 47.69953 | I15: 10.501481 | J15: 1777.2128 | K15: 3.6340858 | L15: 5451.7191 | M15: 239.92373 | N15: 0.4273562 | O15: 37.745175 | P15: 8.9525216 | Q15: 18.606705 | R15: 35.872027 | S15: 180.70181 | T15: 8.8430823 | U15: 74.012493 | V15: 344.48044 | W15: 624.76381 | X15: 486.149 | Y15: 290.94583 | Z15: 130.046 | AA15: 112.52456 | AB15: 26.75857 | AC15: 46.094743 | AD15: 15.674706 | AE15: 39.739753 | AF15: 1.4970039 | AG15: 13.136864 | AH15: 29.576226 | AI15: 10.538527 | AJ15: 7.4044225 | AK15: 2.2863331 | AL15: 29.360717 | AM15: 18.010807 | AN15: 3.1567418 | AO15: 16.430871 | AP15: 39.034904 | AQ15: 316.43697 | AR15: 5.1186676 | AS15: 0.45575244 | AT15: 0.08183202 | AU15: 4.3745617 | AV15: 16.45793 | AW15: 1958.4026 | AX15: 0.26945944 | AY15: 0.4737397 | AZ15: 3.3192289 | BA15: 1.5195599 | BB15: 6.8059641 | BC15: 3.0028484 | BD15: 4.4722981 | BE15: 4.6986269 | BF15: 5.1283991 | BG15: 5.3483989 | BH15: 9.5218707 | BI15: 0.85217147 | BJ15: 335.96246 | BK15: 206.14366 | BL15: 25.532807 | BM15: 448.64722 | BN15: 109.13061 | BO15: 1.6467315 | BP15: 37.806291 | BQ15: 0 | BR15: 15014.802 | BS15: 0.010452151 | BT15: 16.419142 | BU15: 0 | BV15: 9846.8354 | BW15: 40.105722 | BX15: -20.576023 | BY15: 9882.7947 | BZ15: 24897.596
A16: 1100 | B16: Fabricação de bebidas | C16: 7.1899715 | D16: 1.2972352 | E16: 0.055943968 | F16: 8.969057 | G16: 8.0837067 | H16: 9.8592449 | I16: 1.4686416 | J16: 11.38839 | K16: 0.39550126 | L16: 43.247539 | M16: 909.6784 | N16: 0.082218488 | O16: 0.75383937 | P16: 0.24525148 | Q16: 0.5143547 | R16: 4.5618383 | S16: 3.4232828 | T16: 0.86422133 | U16: 2.4643401 | V16: 1.5597965 | W16: 5.5094012 | X16: 17.184632 | Y16: 4.2258429 | Z16: 4.0931599 | AA16: 6.3867851 | AB16: 2.3434124 | AC16: 2.7696272 | AD16: 0.56499745 | AE16: 6.9500601 | AF16: 0.76096063 | AG16: 2.4489885 | AH16: 27.249573 | AI16: 4.1989075 | AJ16: 1.2017251 | AK16: 1.1228154 | AL16: 3.0592673 | AM16: 12.290607 | AN16: 1.3598789 | AO16: 1.2305755 | AP16: 10.994314 | AQ16: 18.966955 | AR16: 0.8693508 | AS16: 0.19337345 | AT16: 2.3015826 | AU16: 0.99305761 | AV16: 96.235101 | AW16: 6718.7591 | AX16: 0.069590098 | AY16: 0.17297627 | AZ16: 0.75488027 | BA16: 1.1267472 | BB16: 0.904143 | BC16: 2.3874863 | BD16: 2.5821575 | BE16: 0.97465183 | BF16: 0.94018241 | BG16: 1.910233 | BH16: 3.92999 | BI16: 0.10888272 | BJ16: 8.4966926 | BK16: 3.5807513 | BL16: 1.1182385 | BM16: 7.9983471 | BN16: 2.8119904 | BO16: 9.8318861 | BP16: 1.2934191 | BQ16: 0 | BR16: 8021.3601 | BS16: 0 | BT16: 0.046757391 | BU16: 0 | BV16: 3705.8908 | BW16: 43.379916 | BX16: 274.37487 | BY16: 4023.6924 | BZ16: 12045.052
A17: 1200 | B17: Fabricação de produtos do fumo | C17: 1.2255877 | D17: 0.12477653 | E17: 0.0088260071 | F17: 0.0055626286 | G17: 0.62645393 | H17: 0.68363708 | I17: 0.071714578 | J17: 0.082064129 | K17: 0.0093668505 | L17: 0.057484972 | M17: 0.0058629089 | N17: 110.20976 | O17: 0.0095473571 | P17: 0.0085161969 | Q17: 0.0081171944 | R17: 0.064913482 | S17: 0.41364281 | T17: 0.044886059 | U17: 0.011466292 | V17: 0.0091740936 | W17: 0.051689496 | X17: 0.011796283 | Y17: 0.007597525 | Z17: 0.015242051 | AA17: 0.093731438 | AB17: 0.035510825 | AC17: 0.01193615 | AD17: 0.004721635 | AE17: 0.028766289 | AF17: 0.02033404 | AG17: 0.05681714 | AH17: 2.3677593 | AI17: 0.11726626 | AJ17: 0.011877747 | AK17: 0.036757267 | AL17: 0.028840234 | AM17: 0.95066711 | AN17: 0.0035266053 | AO17: 0.010243872 | AP17: 0.19540986 | AQ17: 0.27591279 | AR17: 0.010992875 | AS17: 0.01983949 | AT17: 6.4655376e-05 | AU17: 0.026112837 | AV17: 0.0024876596 | AW17: 0.02639221 | AX17: 0.032788289 | AY17: 0.0090444289 | AZ17: 0.022275728 | BA17: 0.040895823 | BB17: 0.051894078 | BC17: 0.0231016 | BD17: 0.058958763 | BE17: 0.020526127 | BF17: 0.024203334 | BG17: 0.031762707 | BH17: 0.15013085 | BI17: 0.0012915862 | BJ17: 0.025030109 | BK17: 0.018292843 | BL17: 0.022621281 | BM17: 0.01045877 | BN17: 0.03136011 | BO17: 0.0032452459 | BP17: 0.019040315 | BQ17: 0 | BR17: 118.70058 | BS17: 0 | BT17: 0 | BU17: 0 | BV17: 11106.876 | BW17: 4.0709915 | BX17: -6.112721 | BY17: 11104.835 | BZ17: 11223.535
... A72: 9700 | B72: Serviços domésticos | C72: 0 | D72: 0 | E72: 0 | F72: 0 | G72: 0 | H72: 0 | I72: 0 | J72: 0 | K72: 0 | L72: 0 | M72: 0 | N72: 0 | O72: 0 | P72: 0 | Q72: 0 | R72: 0 | S72: 0 | T72: 0 | U72: 0 | V72: 0 | W72: 0 | X72: 0 | Y72: 0 | Z72: 0 | AA72: 0 | AB72: 0 | AC72: 0 | AD72: 0 | AE72: 0 | AF72: 0 | AG72: 0 | AH72: 0 | AI72: 0 | AJ72: 0 | AK72: 0 | AL72: 0 | AM72: 0 | AN72: 0 | AO72: 0 | AP72: 0 | AQ72: 0 | AR72: 0 | AS72: 0 | AT72: 0 | AU72: 0 | AV72: 0 | AW72: 0 | AX72: 0 | AY72: 0 | AZ72: 0 | BA72: 0 | BB72: 0 | BC72: 0 | BD72: 0 | BE72: 0 | BF72: 0 | BG72: 0 | BH72: 0 | BI72: 0 | BJ72: 0 | BK72: 0 | BL72: 0 | BM72: 0 | BN72: 0 | BO72: 0 | BP72: 0 | BQ72: 0 | BR72: 0 | BS72: 0 | BT72: 0 | BU72: 0 | BV72: 0 | BW72: 0 | BX72: 0 | BY72: 0 | BZ72: 0
A74: Total | C74: 54235.166 | D74: 12103.253 | E74: 2039.3349 | F74: 2393.3072 | G74: 38519.265 | H74: 17524.468 | I74: 3047.4772 | J74: 12075.499 | K74: 2564.1012 | L74: 39371.156 | M74: 4605.5832 | N74: 502.41239 | O74: 10208.355 | P74: 6575.8262 | Q74: 4100.3072 | R74: 3861.8222 | S74: 18526.783 | T74: 2325.3592 | U74: 73029.595 | V74: 2498.813 | W74: 107816.44 | X74: 37850.236 | Y74: 10860.913 | Z74: 14523.712 | AA74: 38374.416 | AB74: 11380.815 | AC74: 27730.932 | AD74: 21487.126 | AE74: 18266.498 | AF74: 69377.217 | AG74: 25710.376 | AH74: 45294.807 | AI74: 48440.602 | AJ74: 22738.707 | AK74: 21551.107 | AL74: 11529.652 | AM74: 24115.164 | AN74: 46351.275 | AO74: 4014.901 | AP74: 37447.283 | AQ74: 57662.139 | AR74: 21847.859 | AS74: 3615.5328 | AT74: 7651.6073 | AU74: 9442.2172 | AV74: 713.42556 | AW74: 15276.234 | AX74: 1021.1938 | AY74: 2851.4262 | AZ74: 7961.1004 | BA74: 17888.199 | BB74: 15645.833 | BC74: 3782.3488 | BD74: 7703.9297 | BE74: 5345.7956 | BF74: 5770.5545 | BG74: 3349.091 | BH74: 7932.5529 | BI74: 810.12615 | BJ74: 27759.776 | BK74: 4977.6075 | BL74: 4010.7848 | BM74: 19245.997 | BN74: 15650.236 | BO74: 1251.4479 | BP74: 9643.5165 | BQ74: 0 | BR74: 1233780.6 | BS74: 13469.27 | BT74: 4012.9879 | BU74: 0 | BV74: 202805.34 | BW74: 204297.83 | BX74: 13106.977 | BY74: 437692.41 | BZ74: 1671473
A76: (1) Exportação de bens e serviços líquida de ajuste CIF/FOB.

Sheet Impostos
A1: Tabela 5 - Destino dos impostos sobre produtos nacionais e importados (soma das Tabels 5 e 6 do SCN 2010, IBGE) - 2021 (Preços correntes)
A2: Unidade de Medida: R$ 1.000.000,00
A3: Código da Atividade Nível 67 | B3: Descrição da Atividade Nível 67 | C3: Consumo intermediário das atividades | L3: Consumo intermediário das atividades | U3: Consumo intermediário das atividades | AD3: Consumo intermediário das atividades | AM3: Consumo intermediário das atividades | AV3: Consumo intermediário das atividades | BE3: Consumo intermediário das atividades | BR3: Consumo intermediário das atividades | BS3: Demanda final | BZ3: Demanda Total
C4: 0191 | D4: 0192 | E4: 0280 | F4: 0580 | G4: 0680 | H4: 0791 | I4: 0792 | J4: 1091 | K4: 1092 | L4: 1093 | M4: 1100 | N4: 1200 | O4: 1300 | P4: 1400 | Q4: 1500 | R4: 1600 | S4: 1700 | T4: 1800 | U4: 1991 | V4: 1992 | W4: 2091 | X4: 2092 | Y4: 2093 | Z4: 2100 | AA4: 2200 | AB4: 2300 | AC4: 2491 | AD4: 2492 | AE4: 2500 | AF4: 2600 | AG4: 2700 | AH4: 2800 | AI4: 2991 | AJ4: 2992 | AK4: 3000 | AL4: 3180 | AM4: 3300 | AN4: 3500 | AO4: 3680 | AP4: 4180 | AQ4: 4580 | AR4: 4900 | AS4: 5000 | AT4: 5100 | AU4: 5280 | AV4: 5500 | AW4: 5600 | AX4: 5800 | AY4: 5980 | AZ4: 6100 | BA4: 6280 | BB4: 6480 | BC4: 6800 | BD4: 6980 | BE4: 7180 | BF4: 7380 | BG4: 7700 | BH4: 7880 | BI4: 8000 | BJ4: 8400 | BK4: 8591 | BL4: 8592 | BM4: 8691 | BN4: 8692 | BO4: 9080 | BP4: 9480 | BQ4: 9700 | BR4: Total do produto | BS4: Exportação de bens e serviços (1) | BT4: Consumo do governo | BU4: Consumo das ISFLSF | BV4: Consumo das famílias | BW4: Formação bruta de capital fixo | BX4: Variação de estoque | BY4: Demanda final
C5: Agricultura, inclusive o apoio à agricultura e a pós-colheita | D5: Pecuária, inclusive o apoio à pecuária | E5: Produção florestal; pesca e aquicultura | F5: Extração de carvão mineral e de minerais não metálicos | G5: Extração de petróleo e gás, inclusive as atividades de apoio | H5: Extração de minério de ferro, inclusive beneficiamentos e a aglomeração | I5: Extração de minerais metálicos não ferrosos, inclusive beneficiamentos | J5: Abate e produtos de carne, inclusive os produtos do laticínio e da pesca | K5: Fabricação e refino de açúcar | L5: Outros produtos alimentares | M5: Fabricação de bebidas | N5: Fabricação de produtos do fumo | O5: Fabricação de produtos têxteis | P5: Confecção de artefatos do vestuário e acessórios | Q5: Fabricação de calçados e de artefatos de couro | R5: Fabricação de produtos da madeira | S5: Fabricação de celulose, papel e produtos de papel | T5: Impressão e reprodução de gravações | U5: Refino de petróleo e coquerias | V5: Fabricação de biocombustíveis | W5: Fabricação de químicos orgânicos e inorgânicos, resinas e elastômeros | X5: Fabricação de defensivos, desinfestantes, tintas e químicos diversos | Y5: Fabricação de produtos de limpeza, cosméticos/perfumaria e higiene pessoal | Z5: Fabricação de produtos farmoquímicos e farmacêuticos | AA5: Fabricação de produtos de borracha e de material plástico | AB5: Fabricação de produtos de minerais não metálicos | AC5: Produção de ferro gusa/ferroligas, siderurgia e tubos de aço sem costura | AD5: Metalurgia de metais não ferosos e a fundição de metais | AE5: Fabricação de produtos de metal, exceto máquinas e equipamentos | AF5: Fabricação de equipamentos de informática, produtos eletrônicos e ópticos | AG5: Fabricação de máquinas e equipamentos elétricos | AH5: Fabricação de máquinas e equipamentos mecânicos | AI5: Fabricação de automóveis, caminhões e ônibus, exceto peças | AJ5: Fabricação de peças e acessórios para veículos automotores | AK5: Fabricação de outros equipamentos de transporte, exceto veículos automotores | AL5: Fabricação de móveis e de produtos de indústrias diversas | AM5: Manutenção, reparação e instalação de máquinas e equipamentos | AN5: Energia elétrica, gás natural e outras utilidades | AO5: Água, esgoto e gestão de resíduos | AP5: Construção | AQ5: Comércio por atacado e varejo | AR5: Transporte terrestre | AS5: Transporte aquaviário | AT5: Transporte aéreo | AU5: Armazenamento, atividades auxiliares dos transportes e correio | AV5: Alojamento | AW5: Alimentação | AX5: Edição e edição integrada à impressão | AY5: Atividades de televisão, rádio, cinema e gravação/edição de som e imagem | AZ5: Telecomunicações | BA5: Desenvolvimento de sistemas e outros serviços de informação | BB5: Intermediação financeira, seguros e previdência complementar | BC5: Atividades imobiliárias | BD5: Atividades jurídicas, contábeis, consultoria e sedes de empresas | BE5: Serviços de arquitetura, engenharia, testes/análises técnicas e P & D | BF5: Outras atividades profissionais, científicas e técnicas | BG5: Aluguéis não imobiliários e gestão de ativos de propriedade intelectual | BH5: Outras atividades administrativas e serviços complementares | BI5: Atividades de vigilância, segurança e investigação | BJ5: Administração pública, defesa e seguridade social | BK5: Educação pública | BL5: Educação privada | BM5: Saúde pública | BN5: Saúde privada | BO5: Atividades artísticas, criativas e de espetáculos | BP5: Organizações associativas e outros serviços pessoais | BQ5: Serviços domésticos
A6: 0191 | B6: Agricultura, inclusive o apoio à agricultura e a pós-colheita | C6: 701.39596 | D6: 576.42459 | E6: 18.785134 | F6: 0.040092483 | G6: 0.44116017 | H6: 0.20168411 | I6: 0.076301195 | J6: 210.58367 | K6: 808.04684 | L6: 1356.3562 | M6: 89.058865 | N6: 21.508226 | O6: 431.40669 | P6: 107.70317 | Q6: 0.86090683 | R6: 6.4034456 | S6: 6.5902347 | T6: 0 | U6: 1.043149 | V6: 627.74841 | W6: 0.80471505 | X6: 0.77941894 | Y6: 0.18263071 | Z6: 1.8229667 | AA6: 1.126301 | AB6: 0.77084116 | AC6: 0.66414896 | AD6: 1.2409647 | AE6: 0.056249584 | AF6: 0.035391413 | AG6: 0.032801605 | AH6: 0.078502464 | AI6: 0.067073203 | AJ6: 0.024366225 | AK6: 0.046249223 | AL6: 1.3564599 | AM6: 0.012208674 | AN6: 0.042576959 | AO6: 0.04120903 | AP6: 26.887601 | AQ6: 194.34922 | AR6: 0.1509297 | AS6: 0 | AT6: 0.031290646 | AU6: 0.6061009 | AV6: 6.3671126 | AW6: 280.47968 | AX6: 0.011873468 | AY6: 0.063413091 | AZ6: 1.3986433 | BA6: 0.4312274 | BB6: 0.6496027 | BC6: 0.77994916 | BD6: 1.4813836 | BE6: 0.4713234 | BF6: 0.16346328 | BG6: 0.14343746 | BH6: 10.922055 | BI6: 0.024431682 | BJ6: 41.530464 | BK6: 11.461934 | BL6: 9.1941722 | BM6: 14.971003 | BN6: 19.370512 | BO6: 0.10468092 | BP6: 39.559724 | BQ6: 0 | BR6: 5635.4651 | BS6: 0.19892039 | BT6: 4.5139039 | BU6: 0 | BV6: 5671.0836 | BW6: 150.62635 | BX6: 0 | BY6: 5826.4227 | BZ6: 11461.888
A7: 0192 | B7: Pecuária, inclusive o apoio à pecuária | C7: 96.134 | D7: 611.36945 | E7: 19.231922 | F7: 0.21123353 | G7: 1.0735245 | H7: 0.43791404 | I7: 0.14460095 | J7: 3304.2798 | K7: 4.5441043 | L7: 164.57324 | M7: 5.2237053 | N7: 2.210002 | O7: 47.768858 | P7: 50.244488 | Q7: 0.56410015 | R7: 12.6566 | S7: 10.507924 | T7: 0 | U7: 0.026753154 | V7: 4.8637388 | W7: 3.1067322 | X7: 0.40703208 | Y7: 0.42514571 | Z7: 0.96562149 | AA7: 2.3384389 | AB7: 3.8793959 | AC7: 1.5894457 | AD7: 2.4258718 | AE7: 0.13934226 | AF7: 0.10105938 | AG7: 0.12427046 | AH7: 0.24014321 | AI7: 0.15630443 | AJ7: 0.068268827 | AK7: 0.093418891 | AL7: 0.78122691 | AM7: 0.041204273 | AN7: 0.11789922 | AO7: 0.20398094 | AP7: 61.189204 | AQ7: 11.272651 | AR7: 0.14272987 | AS7: 0 | AT7: 0.042870577 | AU7: 1.1544296 | AV7: 12.043467 | AW7: 149.81928 | AX7: 0.035210621 | AY7: 0.14722942 | AZ7: 2.5711417 | BA7: 0.95584403 | BB7: 1.2783604 | BC7: 1.7693362 | BD7: 0.52512635 | BE7: 0.87409095 | BF7: 1.5848003 | BG7: 0.21896149 | BH7: 1.810072 | BI7: 0.02635516 | BJ7: 21.437766 | BK7: 6.3969163 | BL7: 4.0879651 | BM7: 7.4948682 | BN7: 17.536194 | BO7: 0.21444302 | BP7: 6.9568685 | BQ7: 0 | BR7: 4664.8569 | BS7: 0.10922861 | BT7: 1.1763738 | BU7: 0 | BV7: 2427.813 | BW7: 944.07218 | BX7: 0 | BY7: 3373.1708 | BZ7: 8038.0277
A8: 0280 | B8: Produção florestal; pesca e aquicultura | C8: 243.77036 | D8: 257.88162 | E8: 316.63193 | F8: 0.016755068 | G8: 0.088773783 | H8: 0.036810535 | I8: 0.010985801 | J8: 85.936739 | K8: 0.02700934 | L8: 11.065342 | M8: 0.70076253 | N8: 0.052280936 | O8: 2.2728011 | P8: 0.64873939 | Q8: 0.0058646987 | R8: 147.84438 | S8: 116.51408 | T8: 0 | U8: 0.0031707442 | V8: 0.069931375 | W8: 6.8887422 | X8: 0.13512777 | Y8: 0.0068980528 | Z8: 0.02249987 | AA8: 26.751433 | AB8: 1.3446821 | AC8: 13.752544 | AD8: 0.17999148 | AE8: 0.01663291 | AF8: 0.01088666 | AG8: 0.013248942 | AH8: 0.02815554 | AI8: 0.015618734 | AJ8: 0.0076812272 | AK8: 0.007880733 | AL8: 0.06862681 | AM8: 0.0048834694 | AN8: 0.014871636 | AO8: 0.015351575 | AP8: 150.76846 | AQ8: 12.374088 | AR8: 0.016737862 | AS8: 0 | AT8: 0.0038998461 | AU8: 0.091539747 | AV8: 2.3696174 | AW8: 104.59791 | AX8: 0.0040048654 | AY8: 0.014570622 | AZ8: 0.19072124 | BA8: 0.090563581 | BB8: 0.11306962 | BC8: 0.14470335 | BD8: 0.048769082 | BE8: 0.073457219 | BF8: 0.025068323 | BG8: 0.022377999 | BH8: 0.12721873 | BI8: 0.0031235745 | BJ8: 11.862411 | BK8: 7.6760451 | BL8: 5.0304167 | BM8: 12.89235 | BN8: 7.1523095 | BO8: 0.01924434 | BP8: 0.55898118 | BQ8: 0 | BR8: 1549.1358 | BS8: 0.00088803745 | BT8: 1.4077462 | BU8: 0 | BV8: 2871.0798 | BW8: 67.661625 | BX8: 0 | BY8: 2940.15 | BZ8: 4489.2858
A9: 0580 | B9: Extração de carvão mineral e de minerais não metálicos | C9: 26.754099 | D9: 90.904715 | E9: 2.1472501 | F9: 16.123875 | G9: 26.161088 | H9: 0.15978233 | I9: 0.30725647 | J9: 4.3351384 | K9: 0.1447875 | L9: 15.17968 | M9: 1.6387843 | N9: 3.5704358e-05 | O9: 0.041312451 | P9: 0.0017004077 | Q9: 0.023990452 | R9: 0.0067162347 | S9: 1.0117229 | T9: 0.30004085 | U9: 0.04428313 | V9: 21.670142 | W9: 189.80105 | X9: 3.906006 | Y9: 0.46535412 | Z9: 0.059459596 | AA9: 0.44371686 | AB9: 286.14076 | AC9: 23.498501 | AD9: 23.566255 | AE9: 1.4791883 | AF9: 0.046903675 | AG9: 5.5772732 | AH9: 0.89108812 | AI9: 1.4656741 | AJ9: 0.93347663 | AK9: 0.28491628 | AL9: 1.564353 | AM9: 0.51805268 | AN9: 0.20795166 | AO9: 14.991574 | AP9: 1505.291 | AQ9: 4.3118881 | AR9: 0.0092809303 | AS9: 0.0096832809 | AT9: 0.0013481172 | AU9: 0.025578815 | AV9: 0.22585619 | AW9: 1.2775755 | AX9: 0.0023280449 | AY9: 0.00095144466 | AZ9: 0.0050753485 | BA9: 0.014565714 | BB9: 0.0025940561 | BC9: 53.204881 | BD9: 0.01846123 | BE9: 0.011605287 | BF9: 0.012469843 | BG9: 0.015828042 | BH9: 0.38502859 | BI9: 0.0013495591 | BJ9: 7.5382401 | BK9: 1.3222752 | BL9: 0.022835019 | BM9: 0.47877495 | BN9: 0.74175717 | BO9: 0.0078217003 | BP9: 0.46041648 | BQ9: 0 | BR9: 2338.1974 | BS9: 0 | BT9: 0.0025132103 | BU9: 0 | BV9: 38.158079 | BW9: 0.67334715 | BX9: 0 | BY9: 38.833939 | BZ9: 2377.0314
A10: 0680 | B10: Extração de petróleo e gás, inclusive as atividades de apoio | C10: 8.1490093 | D10: 5.8187968 | E10: 0.27463355 | F10: 0.1231307 | G10: 132.9831 | H10: 58.55838 | I10: 3.1572929 | J10: 0.1110284 | K10: 0.02096373 | L10: 8.2768536 | M10: 1.845937 | N10: 0 | O10: 1.7852143 | P10: 0.0094914968 | Q10: 0.20855172 | R10: 0.095315952 | S10: 10.444763 | T10: 0.022549662 | U10: 3070.0733 | V10: 0.032832036 | W10: 26.729669 | X10: 2.0299421 | Y10: 0.64844262 | Z10: 0.019447156 | AA10: 3.7861436 | AB10: 13.233902 | AC10: 12.021181 | AD10: 5.1943248 | AE10: 4.6095199 | AF10: 0.025212949 | AG10: 1.7482602 | AH10: 10.4314 | AI10: 0.79605678 | AJ10: 2.5521557 | AK10: 0.15356477 | AL10: 0.18091403 | AM10: 4.945892 | AN10: 268.48397 | AO10: 72.231467 | AP10: 96.50729 | AQ10: 12.212483 | AR10: 16.566167 | AS10: 0.35374014 | AT10: 0.0049880335 | AU10: 6.4395136 | AV10: 0.039594444 | AW10: 6.1037074 | AX10: 0.0099994648 | AY10: 0.0032914756 | AZ10: 8.6839239 | BA10: 0.0907965 | BB10: 0.013570275 | BC10: 0.20641042 | BD10: 0.1595544 | BE10: 0.83486971 | BF10: 0.2944402 | BG10: 1.3883193 | BH10: 1.6993241 | BI10: 0.0081606452 | BJ10: 152.57745 | BK10: 0.22844464 | BL10: 0.038293835 | BM10: 0.21958277 | BN10: 0.19601753 | BO10: 0.084374911 | BP10: 2.2625397 | BQ10: 0 | BR10: 4039.0395 | BS10: 0.011031353 | BT10: 0 | BU10: 0 | BV10: 157.61984 | BW10: 2317.5962 | BX10: 0 | BY10: 2475.2271 | BZ10: 6514.2666
A11: 0791 | B11: Extração de minério de ferro, inclusive beneficiamentos e a aglomeração | C11: 0.0048551698 | D11: 0.036405871 | E11: 0 | F11: 0.010811469 | G11: 1.7167522 | H11: 99.615894 | I11: 0.79046819 | J11: 0.078023531 | K11: 0 | L11: 0.17496309 | M11: 0.009357684 | N11: 0 | O11: 7.1196945e-05 | P11: 7.2093268e-05 | Q11: 0 | R11: 0.019350834 | S11: 0.055572568 | T11: 0.15863771 | U11: 0 | V11: 0 | W11: 0.010062367 | X11: 0.026126427 | Y11: 0.0077152872 | Z11: 0.019043703 | AA11: 0.044191017 | AB11: 5.8814577 | AC11: 699.23654 | AD11: 5.9286185 | AE11: 0.68318422 | AF11: 0.030450112 | AG11: 1.386593 | AH11: 4.2306756 | AI11: 0.33427654 | AJ11: 0.50102342 | AK11: 0.17684516 | AL11: 0.58726468 | AM11: 1.8714314 | AN11: 0.0048320429 | AO11: 0.97241903 | AP11: 10.810965 | AQ11: 0.23452917 | AR11: 0.053228985 | AS11: 0.041069872 | AT11: 0 | AU11: 0.35766733 | AV11: 0.013289407 | AW11: 0.093209064 | AX11: 4.3055627e-05 | AY11: 0 | AZ11: 0.80654517 | BA11: 0.00097086862 | BB11: 0.14778803 | BC11: 0.27370666 | BD11: 0.047865552 | BE11: 0.2705667 | BF11: 0.00080171432 | BG11: 0.0018319653 | BH11: 0.8145662 | BI11: 0 | BJ11: 2.4595754 | BK11: 0.067430119 | BL11: 0.00067656953 | BM11: 0.59303529 | BN11: 0.00095869683 | BO11: 0.028971499 | BP11: 0.012870552 | BQ11: 0 | BR11: 841.73615 | BS11: 0 | BT11: 0 | BU11: 0 | BV11: 3.0003311 | BW11: 65.500131 | BX11: 0 | BY11: 68.500462 | BZ11: 910.23661
A12: 0792 | B12: Extração de minerais metálicos não ferrosos, inclusive beneficiamentos | C12: 0.39485386 | D12: 0.17772475 | E12: 0.0052894836 | F12: 0.0036586546 | G12: 2.5366724 | H12: 0.019489291 | I12: 70.079035 | J12: 0.58190257 | K12: 0.007112711 | L12: 1.6126917 | M12: 0.062591508 | N12: 1.2601538e-05 | O12: 0.0036864572 | P12: 5.8177745e-05 | Q12: 0.0021520831 | R12: 0.00016273574 | S12: 0.56313555 | T12: 1.4034772 | U12: 4.9386374e-05 | V12: 5.7097927e-05 | W12: 0.59752923 | X12: 0.29333035 | Y12: 0.026468884 | Z12: 0.0045957029 | AA12: 0.25231618 | AB12: 3.4376174 | AC12: 127.17495 | AD12: 389.74249 | AE12: 6.0567456 | AF12: 0.21902033 | AG12: 11.606824 | AH12: 1.9325072 | AI12: 0.9405052 | AJ12: 4.2636395 | AK12: 1.0857537 | AL12: 5.2154594 | AM12: 0.81431796 | AN12: 0.0061715549 | AO12: 0.2438791 | AP12: 21.162771 | AQ12: 0.030553728 | AR12: 0.00090933149 | AS12: 0.00025351773 | AT12: 0 | AU12: 0.00035023932 | AV12: 0.008219894 | AW12: 0.036215012 | AX12: 2.4297682e-05 | AY12: 4.0644721e-05 | AZ12: 0.0005457187 | BA12: 3.1552756e-05 | BB12: 8.4444515e-06 | BC12: 0.31263041 | BD12: 2.5657807e-05 | BE12: 0.0056966671 | BF12: 0.00031667547 | BG12: 0.0001217992 | BH12: 0.015852005 | BI12: 2.2333963e-05 | BJ12: 0.057551864 | BK12: 0.0038700843 | BL12: 0 | BM12: 0.015510454 | BN12: 0.044242422 | BO12: 2.1525262e-05 | BP12: 0.024055285 | BQ12: 0 | BR12: 653.08778 | BS12: 0 | BT12: 0 | BU12: 0 | BV12: 0.9157322 | BW12: 0.047118958 | BX12: 0 | BY12: 0.96285116 | BZ12: 654.05063
A13: 1091 | B13: Abate e produtos de carne, inclusive os produtos do laticínio e da pesca | C13: 4.4783006 | D13: 256.39295 | E13: 3.5393014 | F13: 1.7951975 | G13: 1.2747307 | H13: 1.1200003 | I13: 0.19569754 | J13: 1084.8285 | K13: 0.027672686 | L13: 211.95003 | M13: 4.6792737 | N13: 0.0060739414 | O13: 0.5425782 | P13: 0.22094669 | Q13: 68.075521 | R13: 0.71400178 | S13: 1.5106008 | T13: 0.082982612 | U13: 0.2309148 | V13: 26.413809 | W13: 6.6122442 | X13: 5.4247854 | Y13: 163.42366 | Z13: 1.8264635 | AA13: 1.5568106 | AB13: 0.36124248 | AC13: 0.56345223 | AD13: 0.23959301 | AE13: 1.1294254 | AF13: 0.10183279 | AG13: 0.32968576 | AH13: 0.9599502 | AI13: 0.4165779 | AJ13: 0.17640309 | AK13: 0.097000222 | AL13: 0.47451454 | AM13: 0.50092608 | AN13: 0.26438967 | AO13: 0.30217189 | AP13: 4.476544 | AQ13: 27.66613 | AR13: 0.5067035 | AS13: 0.01670581 | AT13: 0.019677848 | AU13: 0.09521855 | AV13: 29.401307 | AW13: 1632.4436 | AX13: 0.013824706 | AY13: 0.029105953 | AZ13: 0.10791166 | BA13: 0.07632409 | BB13: 0.20833117 | BC13: 0.18682982 | BD13: 0.21798616 | BE13: 0.2618512 | BF13: 0.46276867 | BG13: 0.27188415 | BH13: 0.53891183 | BI13: 0.050811085 | BJ13: 172.21377 | BK13: 83.764659 | BL13: 48.387987 | BM13: 114.59685 | BN13: 164.94872 | BO13: 0.27936835 | BP13: 44.751032 | BQ13: 0 | BR13: 4178.8351 | BS13: 0.07139224 | BT13: 7.5796762 | BU13: 0 | BV13: 44326.071 | BW13: 0.91750504 | BX13: 0 | BY13: 44334.64 | BZ13: 48513.475
A14: 1092 | B14: Fabricação e refino de açúcar | C14: 13.799412 | D14: 22.753942 | E14: 0.88332446 | F14: 0.038824738 | G14: 30.46551 | H14: 6.3030455 | I14: 0.63103917 | J14: 13.540922 | K14: 20.279964 | L14: 87.008293 | M14: 7.7890612 | N14: 0.0012496525 | O14: 0.0058654881 | P14: 0.0073697636 | Q14: 0.0055770749 | R14: 0.071901012 | S14: 0.063637573 | T14: 0 | U14: 1004.803 | V14: 41.189824 | W14: 24.549196 | X14: 15.580062 | Y14: 61.560964 | Z14: 28.11399 | AA14: 0.079920956 | AB14: 0.013742049 | AC14: 0.011334329 | AD14: 0.034419441 | AE14: 1.9553241 | AF14: 0.029755044 | AG14: 0.2467296 | AH14: 14.098006 | AI14: 1.8803063 | AJ14: 0.037263028 | AK14: 0.19143792 | AL14: 0.0056101639 | AM14: 6.2259683 | AN14: 0.010665345 | AO14: 0.076282543 | AP14: 87.515449 | AQ14: 92.803028 | AR14: 97.282726 | AS14: 0.14349104 | AT14: 5.7289574 | AU14: 4.7632117 | AV14: 0.061519123 | AW14: 73.314798 | AX14: 0.0087412151 | AY14: 0.047123487 | AZ14: 0.10781034 | BA14: 20.420872 | BB14: 25.235102 | BC14: 0.046704769 | BD14: 26.891798 | BE14: 34.032122 | BF14: 14.66769 | BG14: 34.33321 | BH14: 43.134553 | BI14: 16.138876 | BJ14: 42.623621 | BK14: 7.2321216 | BL14: 1.7880717 | BM14: 7.1753002 | BN14: 22.416319 | BO14: 0.22730927 | BP14: 34.954703 | BQ14: 0 | BR14: 2097.4379 | BS14: 0 | BT14: 0.0032530811 | BU14: 0 | BV14: 5458.8601 | BW14: 26.66933 | BX14: 0 | BY14: 5485.5327 | BZ14: 7582.9706
A15: 1093 | B15: Outros produtos alimentares | C15: 276.63398 | D15: 2170.0597 | E15: 169.87652 | F15: 30.633809 | G15: 23.803744 | H15: 11.811356 | I15: 2.4377356 | J15: 1812.4548 | K15: 2.0118126 | L15: 2355.8071 | M15: 172.61168 | N15: 0.044116004 | O15: 4.8628669 | P15: 2.4856603 | Q15: 2.8651337 | R15: 9.950329 | S15: 70.875684 | T15: 1.4787602 | U15: 361.3039 | V15: 110.59072 | W15: 75.975928 | X15: 88.10081 | Y15: 75.156334 | Z15: 24.671971 | AA15: 16.062261 | AB15: 6.3942576 | AC15: 7.4304684 | AD15: 2.2511822 | AE15: 12.835817 | AF15: 0.46922227 | AG15: 2.7729176 | AH15: 7.6142661 | AI15: 3.6838904 | AJ15: 2.5491313 | AK15: 0.63081135 | AL15: 5.2575784 | AM15: 4.7371622 | AN15: 1.3048678 | AO15: 3.5226832 | AP15: 75.286289 | AQ15: 277.49645 | AR15: 36.760842 | AS15: 0.22794856 | AT15: 3.6545462 | AU15: 2.5642313 | AV15: 11.947061 | AW15: 1259.3824 | AX15: 0.23350258 | AY15: 0.21298061 | AZ15: 0.4406852 | BA15: 8.039884 | BB15: 18.152614 | BC15: 2.8865435 | BD15: 13.794036 | BE15: 13.8175 | BF15: 17.275119 | BG15: 15.062728 | BH15: 21.833267 | BI15: 5.9361785 | BJ15: 146.55325 | BK15: 94.1811 | BL15: 32.855814 | BM15: 193.56605 | BN15: 150.16163 | BO15: 8.4073727 | BP15: 173.2602 | BQ15: 0 | BR15: 10518.011 | BS15: 0.28024113 | BT15: 10.752196 | BU15: 0 | BV15: 45327.981 | BW15: 7.5658491 | BX15: 0 | BY15: 45346.58 | BZ15: 55864.591
A16: 1100 | B16: Fabricação de bebidas | C16: 2.3464285 | D16: 0.77740468 | E16: 0.048213103 | F16: 2.9041175 | G16: 2.3178787 | H16: 2.856055 | I16: 0.42653714 | J16: 51.662443 | K16: 0.050992818 | L16: 7.2754746 | M16: 1026.9412 | N16: 0.0071786762 | O16: 0.20162417 | P16: 0.061754126 | Q16: 0.085831768 | R16: 1.3891357 | S16: 0.66622329 | T16: 0.13760224 | U16: 3.1897033 | V16: 0.3072276 | W16: 1.0336557 | X16: 2.8673923 | Y16: 1.0497788 | Z16: 0.75987805 | AA16: 1.1411293 | AB16: 0.53052055 | AC16: 0.76271965 | AD16: 0.18249439 | AE16: 3.0044316 | AF16: 0.23901322 | AG16: 0.69768399 | AH16: 4.9383514 | AI16: 1.2188069 | AJ16: 0.51190943 | AK16: 0.32765863 | AL16: 0.80024227 | AM16: 2.5363264 | AN16: 0.80231222 | AO16: 0.43675201 | AP16: 15.969046 | AQ16: 5.8988818 | AR16: 1.5055224 | AS16: 0.031182681 | AT16: 2.5844076 | AU16: 0.20780284 | AV16: 124.62688 | AW16: 7992.0223 | AX16: 0.019598117 | AY16: 0.026560513 | AZ16: 0.15338124 | BA16: 0.20855189 | BB16: 23.738742 | BC16: 0.55116823 | BD16: 0.43766248 | BE16: 0.21649907 | BF16: 0.18486716 | BG16: 0.40908038 | BH16: 1.5177061 | BI16: 0.11626363 | BJ16: 24.449576 | BK16: 15.04264 | BL16: 2.1763686 | BM16: 21.344616 | BN16: 47.766943 | BO16: 6.7620444 | BP16: 3.8149704 | BQ16: 0 | BR16: 9419.2774 | BS16: 0.19054154 | BT16: 0.058800312 | BU16: 0 | BV16: 23548.795 | BW16: 7.1404372 | BX16: 0 | BY16: 23556.185 | BZ16: 32975.462
A17: 1200 | B17: Fabricação de produtos do fumo | C17: 0.8726003 | D17: 0.11248349 | E17: 0.0037820879 | F17: 0.0011184936 | G17: 0.11941356 | H17: 0.17029381 | I17: 0.01515971 | J17: 0.074153461 | K17: 0.0024078502 | L17: 0.097272364 | M17: 0.0073948268 | N17: 195.30952 | O17: 0.020499067 | P17: 0.019943323 | Q17: 0.0098198458 | R17: 0.056868039 | S17: 0.23788707 | T17: 0.022656444 | U17: 0.0031836929 | V17: 0.0013513176 | W17: 0.019478511 | X17: 0.0048465639 | Y17: 0.040549963 | Z17: 0.022849294 | AA17: 0.049627864 | AB17: 0.034259148 | AC17: 0.0027049994 | AD17: 0.0063290767 | AE17: 0.056686149 | AF17: 0.011457674 | AG17: 0.016502518 | AH17: 0.33907262 | AI17: 0.032343213 | AJ17: 0.012847477 | AK17: 0.0046769112 | AL17: 0.021123429 | AM17: 0.14319023 | AN17: 0.0040902125 | AO17: 0.0046008735 | AP17: 0.16381087 | AQ17: 0.42999046 | AR17: 0.028781519 | AS17: 0.0042723668 | AT17: 0.00081626578 | AU17: 0.023981088 | AV17: 0.0033848169 | AW17: 0.070560601 | AX17: 0.076726181 | AY17: 0.011438857 | AZ17: 0.0082496436 | BA17: 0.092482083 | BB17: 0.13802617 | BC17: 0.029214768 | BD17: 0.17559768 | BE17: 0.087188115 | BF17: 0.058396344 | BG17: 0.059212765 | BH17: 0.33322134 | BI17: 0.0047864451 | BJ17: 0.02989789 | BK17: 0.020927615 | BL17: 0.050924244 | BM17: 0.012021715 | BN17: 0.056065014 | BO17: 0.0022927713 | BP17: 0.044946011 | BQ17: 0 | BR17: 200.00226 | BS17: 16.315024 | BT17: 0 | BU17: 0 | BV17: 15017.526 | BW17: 0.61254646 | BX17: 0 | BY17: 15034.453 | BZ17: 15234.455
... A72: 9700 | B72: Serviços domésticos | C72: 0 | D72: 0 | E72: 0 | F72: 0 | G72: 0 | H72: 0 | I72: 0 | J72: 0 | K72: 0 | L72: 0 | M72: 0 | N72: 0 | O72: 0 | P72: 0 | Q72: 0 | R72: 0 | S72: 0 | T72: 0 | U72: 0 | V72: 0 | W72: 0 | X72: 0 | Y72: 0 | Z72: 0 | AA72: 0 | AB72: 0 | AC72: 0 | AD72: 0 | AE72: 0 | AF72: 0 | AG72: 0 | AH72: 0 | AI72: 0 | AJ72: 0 | AK72: 0 | AL72: 0 | AM72: 0 | AN72: 0 | AO72: 0 | AP72: 0 | AQ72: 0 | AR72: 0 | AS72: 0 | AT72: 0 | AU72: 0 | AV72: 0 | AW72: 0 | AX72: 0 | AY72: 0 | AZ72: 0 | BA72: 0 | BB72: 0 | BC72: 0 | BD72: 0 | BE72: 0 | BF72: 0 | BG72: 0 | BH72: 0 | BI72: 0 | BJ72: 0 | BK72: 0 | BL72: 0 | BM72: 0 | BN72: 0 | BO72: 0 | BP72: 0 | BQ72: 0 | BR72: 0 | BS72: 0 | BT72: 0 | BU72: 0 | BV72: 0 | BW72: 0 | BX72: 0 | BY72: 0 | BZ72: 0
A74: Total | C74: 26119.65 | D74: 11778.745 | E74: 1128.0842 | F74: 1207.6198 | G74: 10789.225 | H74: 5392.5773 | I74: 830.94001 | J74: 11658.652 | K74: 2034.2483 | L74: 10427.515 | M74: 3547.3877 | N74: 432.14497 | O74: 3714.5741 | P74: 4768.5682 | Q74: 1759.1492 | R74: 2567.1304 | S74: 5714.9361 | T74: 706.55224 | U74: 59795.134 | V74: 1787.9911 | W74: 12808.49 | X74: 5425.9452 | Y74: 2565.3249 | Z74: 2365.7507 | AA74: 7948.5075 | AB74: 4342.6236 | AC74: 5919.4817 | AD74: 3730.3617 | AE74: 6939.2756 | AF74: 6558.2846 | AG74: 5038.4535 | AH74: 9247.9006 | AI74: 10751.113 | AJ74: 5183.639 | AK74: 1388.994 | AL74: 3772.8451 | AM74: 3877.1867 | AN74: 12019.044 | AO74: 3726.3202 | AP74: 51266.061 | AQ74: 51939.952 | AR74: 22518.142 | AS74: 1632.885 | AT74: 5282.84 | AU74: 4984.837 | AV74: 1366.1121 | AW74: 15895.179 | AX74: 1144.6976 | AY74: 2038.5104 | AZ74: 6631.0429 | BA74: 10723.334 | BB74: 23390.859 | BC74: 9682.3064 | BD74: 9288.6452 | BE74: 3894.1034 | BF74: 5838.6358 | BG74: 2736.0934 | BH74: 14908.295 | BI74: 1314.5841 | BJ74: 14230.628 | BK74: 3455.4143 | BL74: 4612.2586 | BM74: 8074.3635 | BN74: 18049.791 | BO74: 1652.2443 | BP74: 11261.366 | BQ74: 0 | BR74: 587583.55 | BS74: 141.17558 | BT74: 2523.1904 | BU74: 0 | BV74: 635160.16 | BW74: 72734.929 | BX74: 0 | BY74: 710559.45 | BZ74: 1298143
A76: (1) Exportação de bens e serviços líquida de ajuste CIF/FOB.

Sheet Comércio
A1: Tabela 6 - Destino da margem de comércio sobre produtos nacionais e importados (soma das Tabels 7 e 8 do SCN 2010, IBGE) - 2021 (Preços correntes)
A2: Unidade de Medida: R$ 1.000.000,00
A3: Código da Atividade Nível 67 | B3: Descrição da Atividade Nível 67 | C3: Consumo intermediário das atividades | L3: Consumo intermediário das atividades | U3: Consumo intermediário das atividades | AD3: Consumo intermediário das atividades | AM3: Consumo intermediário das atividades | AV3: Consumo intermediário das atividades | BE3: Consumo intermediário das atividades | BR3: Consumo intermediário das atividades | BS3: Demanda final | BZ3: Demanda Total
C4: 0191 | D4: 0192 | E4: 0280 | F4: 0580 | G4: 0680 | H4: 0791 | I4: 0792 | J4: 1091 | K4: 1092 | L4: 1093 | M4: 1100 | N4: 1200 | O4: 1300 | P4: 1400 | Q4: 1500 | R4: 1600 | S4: 1700 | T4: 1800 | U4: 1991 | V4: 1992 | W4: 2091 | X4: 2092 | Y4: 2093 | Z4: 2100 | AA4: 2200 | AB4: 2300 | AC4: 2491 | AD4: 2492 | AE4: 2500 | AF4: 2600 | AG4: 2700 | AH4: 2800 | AI4: 2991 | AJ4: 2992 | AK4: 3000 | AL4: 3180 | AM4: 3300 | AN4: 3500 | AO4: 3680 | AP4: 4180 | AQ4: 4580 | AR4: 4900 | AS4: 5000 | AT4: 5100 | AU4: 5280 | AV4: 5500 | AW4: 5600 | AX4: 5800 | AY4: 5980 | AZ4: 6100 | BA4: 6280 | BB4: 6480 | BC4: 6800 | BD4: 6980 | BE4: 7180 | BF4: 7380 | BG4: 7700 | BH4: 7880 | BI4: 8000 | BJ4: 8400 | BK4: 8591 | BL4: 8592 | BM4: 8691 | BN4: 8692 | BO4: 9080 | BP4: 9480 | BQ4: 9700 | BR4: Total do produto | BS4: Exportação de bens e serviços (1) | BT4: Consumo do governo | BU4: Consumo das ISFLSF | BV4: Consumo das famílias | BW4: Formação bruta de capital fixo | BX4: Variação de estoque | BY4: Demanda final
C5: Agricultura, inclusive o apoio à agricultura e a pós-colheita | D5: Pecuária, inclusive o apoio à pecuária | E5: Produção florestal; pesca e aquicultura | F5: Extração de carvão mineral e de minerais não metálicos | G5: Extração de petróleo e gás, inclusive as atividades de apoio | H5: Extração de minério de ferro, inclusive beneficiamentos e a aglomeração | I5: Extração de minerais metálicos não ferrosos, inclusive beneficiamentos | J5: Abate e produtos de carne, inclusive os produtos do laticínio e da pesca | K5: Fabricação e refino de açúcar | L5: Outros produtos alimentares | M5: Fabricação de bebidas | N5: Fabricação de produtos do fumo | O5: Fabricação de produtos têxteis | P5: Confecção de artefatos do vestuário e acessórios | Q5: Fabricação de calçados e de artefatos de couro | R5: Fabricação de produtos da madeira | S5: Fabricação de celulose, papel e produtos de papel | T5: Impressão e reprodução de gravações | U5: Refino de petróleo e coquerias | V5: Fabricação de biocombustíveis | W5: Fabricação de químicos orgânicos e inorgânicos, resinas e elastômeros | X5: Fabricação de defensivos, desinfestantes, tintas e químicos diversos | Y5: Fabricação de produtos de limpeza, cosméticos/perfumaria e higiene pessoal | Z5: Fabricação de produtos farmoquímicos e farmacêuticos | AA5: Fabricação de produtos de borracha e de material plástico | AB5: Fabricação de produtos de minerais não metálicos | AC5: Produção de ferro gusa/ferroligas, siderurgia e tubos de aço sem costura | AD5: Metalurgia de metais não ferosos e a fundição de metais | AE5: Fabricação de produtos de metal, exceto máquinas e equipamentos | AF5: Fabricação de equipamentos de informática, produtos eletrônicos e ópticos | AG5: Fabricação de máquinas e equipamentos elétricos | AH5: Fabricação de máquinas e equipamentos mecânicos | AI5: Fabricação de automóveis, caminhões e ônibus, exceto peças | AJ5: Fabricação de peças e acessórios para veículos automotores | AK5: Fabricação de outros equipamentos de transporte, exceto veículos automotores | AL5: Fabricação de móveis e de produtos de indústrias diversas | AM5: Manutenção, reparação e instalação de máquinas e equipamentos | AN5: Energia elétrica, gás natural e outras utilidades | AO5: Água, esgoto e gestão de resíduos | AP5: Construção | AQ5: Comércio por atacado e varejo | AR5: Transporte terrestre | AS5: Transporte aquaviário | AT5: Transporte aéreo | AU5: Armazenamento, atividades auxiliares dos transportes e correio | AV5: Alojamento | AW5: Alimentação | AX5: Edição e edição integrada à impressão | AY5: Atividades de televisão, rádio, cinema e gravação/edição de som e imagem | AZ5: Telecomunicações | BA5: Desenvolvimento de sistemas e outros serviços de informação | BB5: Intermediação financeira, seguros e previdência complementar | BC5: Atividades imobiliárias | BD5: Atividades jurídicas, contábeis, consultoria e sedes de empresas | BE5: Serviços de arquitetura, engenharia, testes/análises técnicas e P & D | BF5: Outras atividades profissionais, científicas e técnicas | BG5: Aluguéis não imobiliários e gestão de ativos de propriedade intelectual | BH5: Outras atividades administrativas e serviços complementares | BI5: Atividades de vigilância, segurança e investigação | BJ5: Administração pública, defesa e seguridade social | BK5: Educação pública | BL5: Educação privada | BM5: Saúde pública | BN5: Saúde privada | BO5: Atividades artísticas, criativas e de espetáculos | BP5: Organizações associativas e outros serviços pessoais | BQ5: Serviços domésticos
A6: 0191 | B6: Agricultura, inclusive o apoio à agricultura e a pós-colheita | C6: 2203.7293 | D6: 2613.4658 | E6: 34.035754 | F6: 0.50104252 | G6: 0.39312561 | H6: 0 | I6: 0 | J6: 1202.5318 | K6: 1.7225319 | L6: 18029.76 | M6: 86.774579 | N6: 240.64219 | O6: 1295.841 | P6: 191.43995 | Q6: 1.212991 | R6: 11.286938 | S6: 27.076896 | T6: 0 | U6: 0.93037307 | V6: 491.8099 | W6: 3.2194008 | X6: 4.6048394 | Y6: 0.696919 | Z6: 5.172553 | AA6: 5.7181837 | AB6: 3.213903 | AC6: 1.7050284 | AD6: 0.16480797 | AE6: 0.64294815 | AF6: 0 | AG6: 0.021734821 | AH6: 0.047434821 | AI6: 0.015866566 | AJ6: 0.030909451 | AK6: 0.012429806 | AL6: 3.2095074 | AM6: 0 | AN6: 0.029688826 | AO6: 4.3274762 | AP6: 5.0319053 | AQ6: 1484.6799 | AR6: 0.057837597 | AS6: 0 | AT6: 0.022306842 | AU6: 0.031917992 | AV6: 73.288787 | AW6: 1072.795 | AX6: 0 | AY6: 0.021303244 | AZ6: 0.0021193585 | BA6: 0.0038439346 | BB6: 0.13479688 | BC6: 0.17280646 | BD6: 0.027470945 | BE6: 0.40975138 | BF6: 0.077792675 | BG6: 0.0073606291 | BH6: 14.435153 | BI6: 0.0040588315 | BJ6: 154.8504 | BK6: 50.138032 | BL6: 6.3072229 | BM6: 67.069086 | BN6: 21.904395 | BO6: 0.0094914726 | BP6: 107.75168 | BQ6: 0 | BR6: 29525.223 | BS6: 7245.4443 | BT6: 22.32894 | BU6: 0 | BV6: 47432.395 | BW6: 249.78684 | BX6: 0 | BY6: 54949.955 | BZ6: 84475.178
A7: 0192 | B7: Pecuária, inclusive o apoio à pecuária | C7: 259.47791 | D7: 1520.2817 | E7: 44.895957 | F7: 1.1594288 | G7: 1.9097495 | H7: 0 | I7: 0 | J7: 11179.307 | K7: 0.73705411 | L7: 768.36524 | M7: 12.100665 | N7: 13.857309 | O7: 99.810124 | P7: 89.253495 | Q7: 0.93259329 | R7: 21.976366 | S7: 40.847354 | T7: 0 | U7: 0 | V7: 16.954421 | W7: 14.278303 | X7: 1.9464975 | Y7: 2.2981554 | Z7: 2.3951845 | AA7: 8.294194 | AB7: 16.671075 | AC7: 4.2791149 | AD7: 0.8683166 | AE7: 0.39222589 | AF7: 0 | AG7: 0.1127898 | AH7: 0.034785536 | AI7: 0.011331731 | AJ7: 0.082095326 | AK7: 0.009115191 | AL7: 1.843404 | AM7: 0 | AN7: 0.021335908 | AO7: 1.5156424 | AP7: 18.679669 | AQ7: 53.396635 | AR7: 0.00017004457 | AS7: 0 | AT7: 0.010668609 | AU7: 0.033023726 | AV7: 27.252554 | AW7: 298.45857 | AX7: 0 | AY7: 0.015622379 | AZ7: 0.0013673822 | BA7: 0 | BB7: 0.069091474 | BC7: 0.58265575 | BD7: 0.0095368635 | BE7: 0.015505896 | BF7: 1.1666438 | BG7: 0 | BH7: 0.6674212 | BI7: 0 | BJ7: 40.076525 | BK7: 15.135944 | BL7: 1.278923 | BM7: 7.9625131 | BN7: 5.797536 | BO7: 0.011934775 | BP7: 6.390159 | BQ7: 0 | BR7: 14603.933 | BS7: 266.92844 | BT7: 2.1714238 | BU7: 0 | BV7: 8914.3958 | BW7: 1500.9753 | BX7: 0 | BY7: 10684.471 | BZ7: 25288.404
A8: 0280 | B8: Produção florestal; pesca e aquicultura | C8: 327.44785 | D8: 354.46228 | E8: 486.50854 | F8: 0.13358495 | G8: 0.15148154 | H8: 0 | I8: 0 | J8: 664.04459 | K8: 0.047758622 | L8: 39.80926 | M8: 3.0266066 | N8: 1.0275273 | O8: 3.28023 | P8: 0.79156836 | Q8: 0.61006889 | R8: 254.517 | S8: 450.07539 | T8: 0 | U8: 0 | V8: 0.47502054 | W8: 20.433716 | X8: 0.71566358 | Y8: 0.020775389 | Z8: 0.013854798 | AA8: 86.820268 | AB8: 2.9272138 | AC8: 35.541712 | AD8: 0.068874971 | AE8: 0.39889478 | AF8: 0 | AG8: 0.0090003986 | AH8: 0.0094869643 | AI8: 0.003090472 | AJ8: 0.0090372694 | AK8: 0.0024859612 | AL8: 0.22758541 | AM8: 0 | AN8: 0.005818884 | AO8: 0.11362315 | AP8: 37.915347 | AQ8: 26.979528 | AR8: 1.7004457e-05 | AS8: 0 | AT8: 0.00019754743 | AU8: 0.0062082126 | AV8: 10.524194 | AW8: 150.7395 | AX8: 0 | AY8: 0.0042606488 | AZ8: 0.00013673822 | BA8: 0 | BB8: 0.0013051985 | BC8: 0.051033335 | BD8: 0.0002096245 | BE8: 0.00047247882 | BF8: 0.0041559266 | BG8: 0 | BH8: 0.031851434 | BI8: 0 | BJ8: 27.556851 | BK8: 19.896962 | BL8: 3.2954558 | BM8: 22.132338 | BN8: 3.5659266 | BO8: 0.0002963222 | BP8: 0.26034348 | BQ8: 0 | BR8: 3036.6965 | BS8: 8.0980218 | BT8: 0.76913708 | BU8: 0 | BV8: 4904.0012 | BW8: 52.600159 | BX8: 0 | BY8: 4965.4686 | BZ8: 8002.165
A9: 0580 | B9: Extração de carvão mineral e de minerais não metálicos | C9: 29.85883 | D9: 182.14946 | E9: 4.2926266 | F9: 79.895386 | G9: 146.12024 | H9: 0.3916998 | I9: 1.6407692 | J9: 15.085337 | K9: 3.5384421 | L9: 51.153418 | M9: 6.5663858 | N9: 0 | O9: 0.07533321 | P9: 0 | Q9: 0.051063492 | R9: 0.0099791391 | S9: 4.3114673 | T9: 0.45759026 | U9: 0 | V9: 84.32857 | W9: 975.96802 | X9: 19.960639 | Y9: 1.417257 | Z9: 0.26807054 | AA9: 2.5682141 | AB9: 1270.8512 | AC9: 103.4388 | AD9: 98.236809 | AE9: 4.8153206 | AF9: 0.22616753 | AG9: 19.39984 | AH9: 3.4229427 | AI9: 6.3122223 | AJ9: 9.7788086 | AK9: 1.5495131 | AL9: 9.6929345 | AM9: 1.7176142 | AN9: 0.54870298 | AO9: 102.18723 | AP9: 1215.5363 | AQ9: 27.282755 | AR9: 0.023661825 | AS9: 0.015443422 | AT9: 0 | AU9: 1.0368683 | AV9: 0.45915595 | AW9: 2.7482491 | AX9: 0 | AY9: 0 | AZ9: 0.0091629633 | BA9: 0 | BB9: 0.00014643367 | BC9: 43.202409 | BD9: 0.0028564496 | BE9: 0.0077220418 | BF9: 0.01366633 | BG9: 0 | BH9: 0.24198663 | BI9: 0 | BJ9: 15.091139 | BK9: 2.8061185 | BL9: 0.037986236 | BM9: 3.4519371 | BN9: 0.72403642 | BO9: 0.0015992132 | BP9: 0.49914649 | BQ9: 0 | BR9: 4555.4793 | BS9: 20.476325 | BT9: 0.01236766 | BU9: 0 | BV9: 81.08942 | BW9: 1.4798199 | BX9: 0 | BY9: 103.05793 | BZ9: 4658.5372
A10: 0680 | B10: Extração de petróleo e gás, inclusive as atividades de apoio | C10: 11.340195 | D10: 10.416755 | E10: 0.3967337 | F10: 0.15711939 | G10: 10.595586 | H10: 11.792219 | I10: 1.1431821 | J10: 0.93804731 | K10: 0.0068011349 | L10: 2.7775101 | M10: 0.83830214 | N10: 0.03224631 | O10: 0.57988026 | P10: 0.0025827161 | Q10: 0.14624063 | R10: 0.33603605 | S10: 1.6371165 | T10: 0.00026019725 | U10: 4.404573 | V10: 0.054251483 | W10: 4.8294245 | X10: 1.9942032 | Y10: 0.52973772 | Z10: 0.023717883 | AA10: 2.9247418 | AB10: 6.0022322 | AC10: 5.0586397 | AD10: 0.4522441 | AE10: 0.73091851 | AF10: 0.093870459 | AG10: 1.9326347 | AH10: 23.721825 | AI10: 1.1207094 | AJ10: 0.73635619 | AK10: 0.7229941 | AL10: 0.21434906 | AM10: 11.992434 | AN10: 0.32788315 | AO10: 0.51421752 | AP10: 6.8565592 | AQ10: 13.288361 | AR10: 8.9564192 | AS10: 0.60732737 | AT10: 0 | AU10: 0.67742159 | AV10: 0.042515702 | AW10: 18.169974 | AX10: 0 | AY10: 0.00015970731 | AZ10: 0.047931029 | BA10: 0 | BB10: 0.004483123 | BC10: 0.069262121 | BD10: 0 | BE10: 0.30184913 | BF10: 0.30192561 | BG10: 1.7242733 | BH10: 1.4688209 | BI10: 0.0042375432 | BJ10: 1.3511241 | BK10: 0.42135635 | BL10: 0 | BM10: 0.34674835 | BN10: 0.24728637 | BO10: 0 | BP10: 2.54742 | BQ10: 0 | BR10: 178.95423 | BS10: 0.79120839 | BT10: 0 | BU10: 0 | BV10: 304.77345 | BW10: 45.42606 | BX10: 0 | BY10: 350.99072 | BZ10: 529.94494
A11: 0791 | B11: Extração de minério de ferro, inclusive beneficiamentos e a aglomeração | C11: 0 | D11: 0.017857874 | E11: 0.0054963865 | F11: 0.024813711 | G11: 3.7314209 | H11: 1459.5768 | I11: 22.630882 | J11: 0.27568632 | K11: 0 | L11: 0.48597201 | M11: 0 | N11: 0 | O11: 0 | P11: 0 | Q11: 0 | R11: 0.12435543 | S11: 0.24635042 | T11: 0.24537424 | U11: 0 | V11: 0 | W11: 0.02286845 | X11: 0.15278955 | Y11: 0 | Z11: 0.0067392627 | AA11: 0.10675706 | AB11: 76.775248 | AC11: 11047.237 | AD11: 33.510996 | AE11: 2.0471871 | AF11: 0.14399563 | AG11: 5.5034696 | AH11: 10.2134 | AI11: 0.85244176 | AJ11: 2.2668046 | AK11: 0.82445059 | AL11: 1.6854403 | AM11: 4.983951 | AN11: 0.020119365 | AO11: 0.123771 | AP11: 2.6754506 | AQ11: 0.5003742 | AR11: 0.034852364 | AS11: 0.1924488 | AT11: 0 | AU11: 0.18722416 | AV11: 0.0027347051 | AW11: 0 | AX11: 0 | AY11: 0 | AZ11: 0.01933037 | BA11: 0 | BB11: 0.0018247888 | BC11: 0.019707543 | BD11: 0 | BE11: 1.5369172 | BF11: 0 | BG11: 0 | BH11: 0.59274464 | BI11: 0 | BJ11: 0.035817797 | BK11: 0.00372549 | BL11: 0 | BM11: 0.081349913 | BN11: 0 | BO11: 0 | BP11: 0 | BQ11: 0 | BR11: 12679.727 | BS11: 14592.688 | BT11: 0 | BU11: 0 | BV11: 2.3987581 | BW11: 18.440833 | BX11: 0 | BY11: 14613.528 | BZ11: 27293.255
A12: 0792 | B12: Extração de minerais metálicos não ferrosos, inclusive beneficiamentos | C12: 0.7471404 | D12: 0.33767121 | E12: 0.0092135936 | F12: 0.0086329978 | G12: 27.154172 | H12: 0.12724965 | I12: 387.39381 | J12: 2.4390131 | K12: 0.039743275 | L12: 4.5248797 | M12: 0.24843676 | N12: 0 | O12: 0.0068484736 | P12: 0 | Q12: 0.0046421356 | R12: 0.00076762608 | S12: 2.4069243 | T12: 2.1711064 | U12: 0 | V12: 0.00093457674 | W12: 1.4678097 | X12: 1.5074168 | Y12: 0.073963138 | Z12: 0.07381737 | AA12: 0.849302 | AB12: 18.996453 | AC12: 19.571764 | AD12: 2963.1163 | AE12: 18.0313 | AF12: 1.0712162 | AG12: 46.70588 | AH12: 7.5806364 | AI12: 5.031544 | AJ12: 20.047238 | AK12: 5.3057625 | AL12: 14.982867 | AM12: 2.6316973 | AN12: 0.09619094 | AO12: 0.69131772 | AP12: 14.126353 | AQ12: 0.148398 | AR12: 0.099553609 | AS12: 0.0011879556 | AT12: 0 | AU12: 0.0011557047 | AV12: 0.01553355 | AW12: 0.056460172 | AX12: 0 | AY12: 0 | AZ12: 0.00011932327 | BA12: 0 | BB12: 1.1264128e-05 | BC12: 0.25137937 | BD12: 0 | BE12: 0.00049283788 | BF12: 0 | BG12: 0 | BH12: 0.011045722 | BI12: 0 | BJ12: 0.087360098 | BK12: 0.029287403 | BL12: 0 | BM12: 0.042283203 | BN12: 0.045462006 | BO12: 0 | BP12: 0.030335565 | BQ12: 0 | BR12: 3570.4001 | BS12: 3.426109 | BT12: 0 | BU12: 0 | BV12: 5.2000731 | BW12: 0.1138323 | BX12: 0 | BY12: 8.7400144 | BZ12: 3579.1401
A13: 1091 | B13: Abate e produtos de carne, inclusive os produtos do laticínio e da pesca | C13: 9.3738175 | D13: 848.03292 | E13: 7.2762009 | F13: 1.8857398 | G13: 2.1242426 | H13: 1.5004728 | I13: 0.27586557 | J13: 5225.0874 | K13: 0.061818891 | L13: 670.3002 | M13: 12.332486 | N13: 0.0043616289 | O13: 0.88985539 | P13: 0.55456663 | Q13: 152.56139 | R13: 0.88556782 | S13: 3.7541523 | T13: 0.16102362 | U13: 0.4429301 | V13: 270.30041 | W13: 12.537175 | X13: 13.446939 | Y13: 931.19525 | Z13: 4.6251211 | AA13: 2.7799135 | AB13: 0.58467223 | AC13: 1.0060993 | AD13: 0.389591 | AE13: 26.768974 | AF13: 0.21317606 | AG13: 0.69573701 | AH13: 1.5171098 | AI13: 0.9080753 | AJ13: 0.43905045 | AK13: 0.21919988 | AL13: 1.0952632 | AM13: 0.9754958 | AN13: 0.32695747 | AO13: 0.455745 | AP13: 4.4583412 | AQ13: 68.680022 | AR13: 0.12327423 | AS13: 0.049452901 | AT13: 0.023668292 | AU13: 0.34236375 | AV13: 72.641967 | AW13: 3255.347 | AX13: 0.00072507398 | AY13: 0.02611217 | AZ13: 0.25312754 | BA13: 0.033834804 | BB13: 0.21848921 | BC13: 0.16667315 | BD13: 0.21867448 | BE13: 0.14065628 | BF13: 0.65855121 | BG13: 0.1803097 | BH13: 0.38198883 | BI13: 0.041905513 | BJ13: 342.22825 | BK13: 153.08342 | BL13: 24.981901 | BM13: 220.28463 | BN13: 84.495432 | BO13: 0.15741646 | BP13: 21.343023 | BQ13: 0 | BR13: 12458.546 | BS13: 96.705982 | BT13: 24.288586 | BU13: 0 | BV13: 85827.156 | BW13: 2.240149 | BX13: 0 | BY13: 85950.391 | BZ13: 98408.937
A14: 1092 | B14: Fabricação e refino de açúcar | C14: 12.512739 | D14: 50.603866 | E14: 0.0199782 | F14: 0.094474734 | G14: 42.173695 | H14: 14.050146 | I14: 1.3096509 | J14: 106.33828 | K14: 524.79816 | L14: 1368.049 | M14: 292.16981 | N14: 0 | O14: 0.066406807 | P14: 0.054015288 | Q14: 0 | R14: 3.7432546 | S14: 0.30211087 | T14: 0 | U14: 903.08828 | V14: 411.59771 | W14: 16.09493 | X14: 141.99493 | Y14: 73.989923 | Z14: 33.461979 | AA14: 0.12646358 | AB14: 0.10068539 | AC14: 0.045424552 | AD14: 0.12818995 | AE14: 2.9400795 | AF14: 0.12287559 | AG14: 0.81394043 | AH14: 32.76556 | AI14: 1.4877507 | AJ14: 0.045804437 | AK14: 0.7957996 | AL14: 0.0053004523 | AM14: 16.400363 | AN14: 0.62817546 | AO14: 0.26830359 | AP14: 24.598448 | AQ14: 75.623736 | AR14: 56.608635 | AS14: 0.68263115 | AT14: 1.4006373 | AU14: 4.1839553 | AV14: 0.15002005 | AW14: 384.09953 | AX14: 0.0092028621 | AY14: 0.067622617 | AZ14: 1.3891332 | BA14: 3.744018 | BB14: 5.3929328 | BC14: 0.0031865848 | BD14: 7.7094853 | BE14: 8.9530302 | BF14: 4.4688796 | BG14: 7.3119559 | BH14: 11.388485 | BI14: 3.939547 | BJ14: 54.303303 | BK14: 19.730111 | BL14: 1.7229488 | BM14: 22.974868 | BN14: 9.1805328 | BO14: 0.24088743 | BP14: 15.744847 | BQ14: 0 | BR14: 4778.8107 | BS14: 1556.9028 | BT14: 0.010115551 | BU14: 0 | BV14: 6798.1585 | BW14: 64.429083 | BX14: 0 | BY14: 8419.5005 | BZ14: 13198.311
A15: 1093 | B15: Outros produtos alimentares | C15: 535.47955 | D15: 4595.7879 | E15: 349.74607 | F15: 41.407308 | G15: 35.573935 | H15: 15.349602 | I15: 3.2889069 | J15: 5145.1468 | K15: 7.4238811 | L15: 6136.1092 | M15: 726.98425 | N15: 0.19018668 | O15: 8.1468557 | P15: 7.1384098 | Q15: 6.4264577 | R15: 14.357418 | S15: 307.03446 | T15: 3.0426357 | U15: 327.08434 | V15: 240.40715 | W15: 140.87408 | X15: 267.32455 | Y15: 129.33179 | Z15: 45.455947 | AA15: 30.419115 | AB15: 16.159643 | AC15: 15.70965 | AD15: 4.287879 | AE15: 24.59344 | AF15: 1.3290012 | AG15: 6.1743352 | AH15: 16.111231 | AI15: 8.2129513 | AJ15: 6.3703412 | AK15: 1.5775535 | AL15: 13.718721 | AM15: 8.6427864 | AN15: 2.0871396 | AO15: 6.1916871 | AP15: 45.421816 | AQ15: 728.90126 | AR15: 21.950717 | AS15: 0.66977948 | AT15: 3.3895743 | AU15: 8.439329 | AV15: 51.556645 | AW15: 3212.8424 | AX15: 0.17648552 | AY15: 0.3287895 | AZ15: 6.3822237 | BA15: 2.0122984 | BB15: 20.657576 | BC15: 5.9704905 | BD15: 9.5559838 | BE15: 5.1382058 | BF15: 16.560428 | BG15: 5.2942023 | BH15: 8.3923685 | BI15: 1.6086314 | BJ15: 360.92578 | BK15: 272.92238 | BL15: 37.72207 | BM15: 743.32014 | BN15: 193.67779 | BO15: 4.3619435 | BP15: 80.051413 | BQ15: 0 | BR15: 25098.928 | BS15: 776.73935 | BT15: 33.828251 | BU15: 0 | BV15: 106025.77 | BW15: 21.884729 | BX15: 0 | BY15: 106858.23 | BZ15: 131957.15
A16: 1100 | B16: Fabricação de bebidas | C16: 2.7028084 | D16: 1.094908 | E16: 0.052060289 | F16: 2.9756848 | G16: 3.6089176 | H16: 5.2541496 | I16: 0.68892419 | J16: 43.154938 | K16: 0.15478501 | L16: 17.636265 | M16: 1214.1232 | N16: 0.012202884 | O16: 0.22735672 | P16: 0.045228657 | Q16: 0.12250268 | R16: 1.7393756 | S16: 1.2195241 | T16: 0.26886139 | U16: 3.3628147 | V16: 0.560565 | W16: 2.0848017 | X16: 5.5748484 | Y16: 2.1630192 | Z16: 1.4003666 | AA16: 2.0844365 | AB16: 0.98848435 | AC16: 1.2713369 | AD16: 0.24763343 | AE16: 5.8542619 | AF16: 0.68051059 | AG16: 1.8887876 | AH16: 10.416871 | AI16: 2.990567 | AJ16: 1.3445333 | AK16: 0.81803501 | AL16: 1.3354801 | AM16: 5.8074036 | AN16: 0.92765206 | AO16: 0.61591518 | AP16: 16.119568 | AQ16: 4.3646233 | AR16: 0.23136575 | AS16: 0.14611853 | AT16: 0.59804504 | AU16: 0.21699579 | AV16: 95.470816 | AW16: 7099.9848 | AX16: 0 | AY16: 0.0027585808 | AZ16: 0.029001416 | BA16: 0.010357268 | BB16: 5.3787111 | BC16: 0.32650273 | BD16: 0.024983757 | BE16: 0.033881917 | BF16: 0.036153111 | BG16: 0.019832806 | BH16: 0.87698217 | BI16: 0.084130224 | BJ16: 13.148028 | BK16: 7.9447328 | BL16: 1.0093742 | BM16: 11.963788 | BN16: 12.298223 | BO16: 4.10662 | BP16: 0.794374 | BQ16: 0 | BR16: 8622.7207 | BS16: 5.2126844 | BT16: 0.11648359 | BU16: 0 | BV16: 19351.872 | BW16: 16.087988 | BX16: 0 | BY16: 19373.289 | BZ16: 27996.01
A17: 1200 | B17: Fabricação de produtos do fumo | C17: 1.3576041 | D17: 0.1436011 | E17: 0.010537917 | F17: 0.0019912238 | G17: 0.28792503 | H17: 0.33977294 | I17: 0.032363163 | J17: 0.2995692 | K17: 0.0071192413 | L17: 0.33260838 | M17: 0.022373117 | N17: 469.36325 | O17: 0.055740629 | P17: 0.028156234 | Q17: 0.045106474 | R17: 0.19477643 | S17: 1.1655349 | T17: 0.12775412 | U17: 0.019323585 | V17: 0.011105176 | W17: 0.051451129 | X17: 0.018549218 | Y17: 0.13168189 | Z17: 0.080778859 | AA17: 0.25933031 | AB17: 0.18456831 | AC17: 0.002187773 | AD17: 0.0018903692 | AE17: 0.13383124 | AF17: 0.066752706 | AG17: 0.058004507 | AH17: 0.76579654 | AI17: 0.062236538 | AJ17: 0.060816867 | AK17: 0.022018921 | AL17: 0.09865616 | AM17: 0.37781467 | AN17: 0.0037750079 | AO17: 0.0090243074 | AP17: 0.1337648 | AQ17: 0.71446647 | AR17: 0.020291083 | AS17: 0.0215189 | AT17: 0.00067704558 | AU17: 0.043503917 | AV17: 0.013409678 | AW17: 0.10039258 | AX17: 0.072808779 | AY17: 0.011807084 | AZ17: 0.0043374002 | BA17: 0.084860107 | BB17: 0.1242102 | BC17: 0.029690641 | BD17: 0.14442079 | BE17: 0.050345368 | BF17: 0.062574403 | BG17: 0.05120635 | BH17: 0.26838556 | BI17: 0.0040132528 | BJ17: 0.077830221 | BK17: 0.061029007 | BL17: 0.049743302 | BM17: 0.023914187 | BN17: 0.066407817 | BO17: 0.0016146922 | BP17: 0.048271661 | BQ17: 0 | BR17: 478.52087 | BS17: 0.0072017012 | BT17: 0 | BU17: 0 | BV17: 4775.2657 | BW17: 1.4798199 | BX17: 0 | BY17: 4776.7527 | BZ17: 5255.2736
... A72: 9700 | B72: Serviços domésticos | C72: 0 | D72: 0 | E72: 0 | F72: 0 | G72: 0 | H72: 0 | I72: 0 | J72: 0 | K72: 0 | L72: 0 | M72: 0 | N72: 0 | O72: 0 | P72: 0 | Q72: 0 | R72: 0 | S72: 0 | T72: 0 | U72: 0 | V72: 0 | W72: 0 | X72: 0 | Y72: 0 | Z72: 0 | AA72: 0 | AB72: 0 | AC72: 0 | AD72: 0 | AE72: 0 | AF72: 0 | AG72: 0 | AH72: 0 | AI72: 0 | AJ72: 0 | AK72: 0 | AL72: 0 | AM72: 0 | AN72: 0 | AO72: 0 | AP72: 0 | AQ72: 0 | AR72: 0 | AS72: 0 | AT72: 0 | AU72: 0 | AV72: 0 | AW72: 0 | AX72: 0 | AY72: 0 | AZ72: 0 | BA72: 0 | BB72: 0 | BC72: 0 | BD72: 0 | BE72: 0 | BF72: 0 | BG72: 0 | BH72: 0 | BI72: 0 | BJ72: 0 | BK72: 0 | BL72: 0 | BM72: 0 | BN72: 0 | BO72: 0 | BP72: 0 | BQ72: 0 | BR72: 0 | BS72: 0 | BT72: 0 | BU72: 0 | BV72: 0 | BW72: 0 | BX72: 0 | BY72: 0 | BZ72: 0
A74: Total | C74: 31165.406 | D74: 16917.455 | E74: 1291.0479 | F74: 980.69891 | G74: 9376.1841 | H74: 8443.3658 | I74: 1269.799 | J74: 28718.832 | K74: 1298.2807 | L74: 34654.584 | M74: 5768.3803 | N74: 1054.8105 | O74: 6334.39 | P74: 7039.7085 | Q74: 3794.7727 | R74: 4024.0591 | S74: 12143.28 | T74: 1808.8404 | U74: 4271.4967 | V74: 2136.4112 | W74: 17199.233 | X74: 8968.8221 | Y74: 5235.1545 | Z74: 4139.2537 | AA74: 13884.665 | AB74: 8338.9632 | AC74: 17596.253 | AD74: 11703.512 | AE74: 12396.248 | AF74: 9621.8189 | AG74: 14014.29 | AH74: 19201.649 | AI74: 21228.853 | AJ74: 12116.278 | AK74: 2818.5727 | AL74: 9090.2358 | AM74: 8855.8728 | AN74: 4408.3463 | AO74: 1676.7537 | AP74: 37269.859 | AQ74: 27504.98 | AR74: 17986.654 | AS74: 515.09575 | AT74: 431.84371 | AU74: 1126.9177 | AV74: 742.02011 | AW74: 18805.61 | AX74: 948.3101 | AY74: 459.72594 | AZ74: 893.12216 | BA74: 2688.9889 | BB74: 2501.9574 | BC74: 1594.4371 | BD74: 1977.9116 | BE74: 1865.0295 | BF74: 5309.1081 | BG74: 1103.7023 | BH74: 4683.1935 | BI74: 242.80877 | BJ74: 5854.0116 | BK74: 4639.4239 | BL74: 1581.1928 | BM74: 10894.735 | BN74: 16209.38 | BO74: 481.52179 | BP74: 4362.9305 | BQ74: 0 | BR74: 557661.05 | BS74: 27456.413 | BT74: 3070.2597 | BU74: 0 | BV74: 717820.47 | BW74: 97729.81 | BX74: 0 | BY74: 846076.95 | BZ74: 1403738
A76: (1) Exportação de bens e serviços líquida de ajuste CIF/FOB.

Sheet Transporte
A1: Tabela 7 - Destino da margem de transporte sobre produtos nacionais e importados (soma das Tabels 9 e 10 do SCN 2010, IBGE)21 (Preços correntes)
A2: Unidade de Medida: R$ 1.000.000,00
A3: Código da Atividade Nível 67 | B3: Descrição da Atividade Nível 67 | C3: Consumo intermediário das atividades | L3: Consumo intermediário das atividades | U3: Consumo intermediário das atividades | AD3: Consumo intermediário das atividades | AM3: Consumo intermediário das atividades | AV3: Consumo intermediário das atividades | BE3: Consumo intermediário das atividades | BR3: Consumo intermediário das atividades | BS3: Demanda final | BZ3: Demanda Total
C4: 0191 | D4: 0192 | E4: 0280 | F4: 0580 | G4: 0680 | H4: 0791 | I4: 0792 | J4: 1091 | K4: 1092 | L4: 1093 | M4: 1100 | N4: 1200 | O4: 1300 | P4: 1400 | Q4: 1500 | R4: 1600 | S4: 1700 | T4: 1800 | U4: 1991 | V4: 1992 | W4: 2091 | X4: 2092 | Y4: 2093 | Z4: 2100 | AA4: 2200 | AB4: 2300 | AC4: 2491 | AD4: 2492 | AE4: 2500 | AF4: 2600 | AG4: 2700 | AH4: 2800 | AI4: 2991 | AJ4: 2992 | AK4: 3000 | AL4: 3180 | AM4: 3300 | AN4: 3500 | AO4: 3680 | AP4: 4180 | AQ4: 4580 | AR4: 4900 | AS4: 5000 | AT4: 5100 | AU4: 5280 | AV4: 5500 | AW4: 5600 | AX4: 5800 | AY4: 5980 | AZ4: 6100 | BA4: 6280 | BB4: 6480 | BC4: 6800 | BD4: 6980 | BE4: 7180 | BF4: 7380 | BG4: 7700 | BH4: 7880 | BI4: 8000 | BJ4: 8400 | BK4: 8591 | BL4: 8592 | BM4: 8691 | BN4: 8692 | BO4: 9080 | BP4: 9480 | BQ4: 9700 | BR4: Total do produto | BS4: Exportação de bens e serviços (1) | BT4: Consumo do governo | BU4: Consumo das ISFLSF | BV4: Consumo das famílias | BW4: Formação bruta de capital fixo | BX4: Variação de estoque | BY4: Demanda final
C5: Agricultura, inclusive o apoio à agricultura e a pós-colheita | D5: Pecuária, inclusive o apoio à pecuária | E5: Produção florestal; pesca e aquicultura | F5: Extração de carvão mineral e de minerais não metálicos | G5: Extração de petróleo e gás, inclusive as atividades de apoio | H5: Extração de minério de ferro, inclusive beneficiamentos e a aglomeração | I5: Extração de minerais metálicos não ferrosos, inclusive beneficiamentos | J5: Abate e produtos de carne, inclusive os produtos do laticínio e da pesca | K5: Fabricação e refino de açúcar | L5: Outros produtos alimentares | M5: Fabricação de bebidas | N5: Fabricação de produtos do fumo | O5: Fabricação de produtos têxteis | P5: Confecção de artefatos do vestuário e acessórios | Q5: Fabricação de calçados e de artefatos de couro | R5: Fabricação de produtos da madeira | S5: Fabricação de celulose, papel e produtos de papel | T5: Impressão e reprodução de gravações | U5: Refino de petróleo e coquerias | V5: Fabricação de biocombustíveis | W5: Fabricação de químicos orgânicos e inorgânicos, resinas e elastômeros | X5: Fabricação de defensivos, desinfestantes, tintas e químicos diversos | Y5: Fabricação de produtos de limpeza, cosméticos/perfumaria e higiene pessoal | Z5: Fabricação de produtos farmoquímicos e farmacêuticos | AA5: Fabricação de produtos de borracha e de material plástico | AB5: Fabricação de produtos de minerais não metálicos | AC5: Produção de ferro gusa/ferroligas, siderurgia e tubos de aço sem costura | AD5: Metalurgia de metais não ferosos e a fundição de metais | AE5: Fabricação de produtos de metal, exceto máquinas e equipamentos | AF5: Fabricação de equipamentos de informática, produtos eletrônicos e ópticos | AG5: Fabricação de máquinas e equipamentos elétricos | AH5: Fabricação de máquinas e equipamentos mecânicos | AI5: Fabricação de automóveis, caminhões e ônibus, exceto peças | AJ5: Fabricação de peças e acessórios para veículos automotores | AK5: Fabricação de outros equipamentos de transporte, exceto veículos automotores | AL5: Fabricação de móveis e de produtos de indústrias diversas | AM5: Manutenção, reparação e instalação de máquinas e equipamentos | AN5: Energia elétrica, gás natural e outras utilidades | AO5: Água, esgoto e gestão de resíduos | AP5: Construção | AQ5: Comércio por atacado e varejo | AR5: Transporte terrestre | AS5: Transporte aquaviário | AT5: Transporte aéreo | AU5: Armazenamento, atividades auxiliares dos transportes e correio | AV5: Alojamento | AW5: Alimentação | AX5: Edição e edição integrada à impressão | AY5: Atividades de televisão, rádio, cinema e gravação/edição de som e imagem | AZ5: Telecomunicações | BA5: Desenvolvimento de sistemas e outros serviços de informação | BB5: Intermediação financeira, seguros e previdência complementar | BC5: Atividades imobiliárias | BD5: Atividades jurídicas, contábeis, consultoria e sedes de empresas | BE5: Serviços de arquitetura, engenharia, testes/análises técnicas e P & D | BF5: Outras atividades profissionais, científicas e técnicas | BG5: Aluguéis não imobiliários e gestão de ativos de propriedade intelectual | BH5: Outras atividades administrativas e serviços complementares | BI5: Atividades de vigilância, segurança e investigação | BJ5: Administração pública, defesa e seguridade social | BK5: Educação pública | BL5: Educação privada | BM5: Saúde pública | BN5: Saúde privada | BO5: Atividades artísticas, criativas e de espetáculos | BP5: Organizações associativas e outros serviços pessoais | BQ5: Serviços domésticos
A6: 0191 | B6: Agricultura, inclusive o apoio à agricultura e a pós-colheita | C6: 826.52662 | D6: 743.25937 | E6: 6.8484463 | F6: 0.10699838 | G6: 0.20203976 | H6: 0 | I6: 1.4597012e-05 | J6: 322.44443 | K6: 1628.1669 | L6: 8398.1126 | M6: 164.68253 | N6: 23.887006 | O6: 347.28575 | P6: 11.438626 | Q6: 0.18429607 | R6: 4.722684 | S6: 12.632603 | T6: 0 | U6: 0.2888295 | V6: 1448.7573 | W6: 0.87838085 | X6: 0.80914209 | Y6: 0.10828402 | Z6: 0.25160877 | AA6: 0.48583322 | AB6: 2.2913332 | AC6: 2.6797536 | AD6: 0.033306712 | AE6: 0.0064013398 | AF6: 0 | AG6: 0.0034165789 | AH6: 0.0042338259 | AI6: 0.0031883047 | AJ6: 0.0081989975 | AK6: 0.0016460266 | AL6: 0.28973979 | AM6: 2.3355219e-05 | AN6: 0.004716712 | AO6: 1.7798009 | AP6: 2.7937357 | AQ6: 865.47156 | AR6: 0.013383434 | AS6: 0.00010217908 | AT6: 0.012362001 | AU6: 0.001696979 | AV6: 22.377645 | AW6: 352.03857 | AX6: 6.7146254e-05 | AY6: 0.0016866549 | AZ6: 0.00013459306 | BA6: 0 | BB6: 0.082319541 | BC6: 0.089913126 | BD6: 0.013147563 | BE6: 0.0021723478 | BF6: 0.00092879953 | BG6: 0.0032366465 | BH6: 5.6502528 | BI6: 0.00089238314 | BJ6: 85.908112 | BK6: 29.003194 | BL6: 3.7035512 | BM6: 32.098546 | BN6: 11.802614 | BO6: 0.0030216661 | BP6: 16.832841 | BQ6: 0 | BR6: 15377.092 | BS6: 0.11247185 | BT6: 4.4272256 | BU6: 0 | BV6: 1092.001 | BW6: 17.631658 | BX6: 0 | BY6: 1114.1724 | BZ6: 16491.264
A7: 0192 | B7: Pecuária, inclusive o apoio à pecuária | C7: 48.985049 | D7: 194.57541 | E7: 6.7895712 | F7: 0.3046267 | G7: 1.0109878 | H7: 0 | I7: 0 | J7: 1155.6571 | K7: 9.4563378 | L7: 361.38769 | M7: 4.9312146 | N7: 1.2007326 | O7: 6.6894064 | P7: 5.3318672 | Q7: 0.25203093 | R7: 9.5245407 | S7: 23.951409 | T7: 0 | U7: 0 | V7: 15.8478 | W7: 3.1342703 | X7: 0.4120779 | Y7: 0.31145828 | Z7: 0.11212193 | AA7: 0.99394577 | AB7: 11.706478 | AC7: 5.8218529 | AD7: 0.17548163 | AE7: 0.011181234 | AF7: 0 | AG7: 0.018000782 | AH7: 0.0031048057 | AI7: 0.0023380901 | AJ7: 0.040241457 | AK7: 0.0012028044 | AL7: 0.18859439 | AM7: 0 | AN7: 0.0034589221 | AO7: 1.0417283 | AP7: 12.442013 | AQ7: 28.767175 | AR7: 0.0009180498 | AS7: 0 | AT7: 0.0069512171 | AU7: 0.00050978676 | AV7: 13.121681 | AW7: 77.828244 | AX7: 0 | AY7: 0.0012368803 | AZ7: 0.00020188959 | BA7: 0 | BB7: 0.049464627 | BC7: 0.41142967 | BD7: 0.0051558175 | BE7: 0 | BF7: 0 | BG7: 0 | BH7: 0.25783199 | BI7: 0 | BJ7: 6.0048722 | BK7: 2.5177191 | BL7: 0.24463222 | BM7: 4.3640553 | BN7: 0.70758221 | BO7: 0.0034603403 | BP7: 1.6959853 | BQ7: 0 | BR7: 2018.3044 | BS7: 0.00062380872 | BT7: 0.15473223 | BU7: 0 | BV7: 132.13077 | BW7: 31.794321 | BX7: 0 | BY7: 164.08045 | BZ7: 2182.3848
A8: 0280 | B8: Produção florestal; pesca e aquicultura | C8: 32.761565 | D8: 34.325244 | E8: 56.318987 | F8: 0.03144524 | G8: 0.080191667 | H8: 0 | I8: 0 | J8: 74.392211 | K8: 0.069458908 | L8: 13.028681 | M8: 0.56789148 | N8: 0.047566897 | O8: 0.69965642 | P8: 0.030790379 | Q8: 0.0020009012 | R8: 112.53687 | S8: 280.4857 | T8: 0 | U8: 0 | V8: 0.27248146 | W8: 11.268431 | X8: 0.10029241 | Y8: 0.0028507453 | Z8: 0.00064747987 | AA8: 11.837154 | AB8: 3.6749318 | AC8: 62.768703 | AD8: 0.013919223 | AE8: 0.00084858536 | AF8: 0 | AG8: 0.001427824 | AH8: 0.00084676518 | AI8: 0.00063766094 | AJ8: 0.0032844068 | AK8: 0.00032803757 | AL8: 0.0248648 | AM8: 0 | AN8: 0.00094334239 | AO8: 0.08001962 | AP8: 15.146512 | AQ8: 4.295095 | AR8: 0.00085087542 | AS8: 0 | AT8: 0.00013417698 | AU8: 0.00013903275 | AV8: 1.0419339 | AW8: 14.805872 | AX8: 0 | AY8: 0.00033733098 | AZ8: 2.0188959e-05 | BA8: 0 | BB8: 0.0009883924 | BC8: 0.033041117 | BD8: 0.0001050295 | BE8: 0 | BF8: 0 | BG8: 0 | BH8: 0.011500916 | BI8: 0 | BJ8: 2.0659757 | BK8: 2.065335 | BL8: 0.012545136 | BM8: 2.8578541 | BN8: 0.039806992 | BO8: 8.1832371e-05 | BP8: 0.036946664 | BQ8: 0 | BR8: 737.84595 | BS8: 2.8880033e-06 | BT8: 0.003724848 | BU8: 0 | BV8: 141.18163 | BW8: 0.13656216 | BX8: 0 | BY8: 141.32192 | BZ8: 879.16787
A9: 0580 | B9: Extração de carvão mineral e de minerais não metálicos | C9: 6.8313103 | D9: 34.485463 | E9: 0.029799187 | F9: 21.69791 | G9: 76.904063 | H9: 0.02021512 | I9: 1.8004386 | J9: 3.9400901 | K9: 0.091696174 | L9: 11.529101 | M9: 0.6617966 | N9: 0 | O9: 0.0085013816 | P9: 0 | Q9: 0.0065207629 | R9: 0 | S9: 0.3537371 | T9: 0.025303882 | U9: 7.7358312 | V9: 18.08258 | W9: 180.32219 | X9: 6.1817179 | Y9: 0.13264519 | Z9: 0.02356203 | AA9: 0.22193047 | AB9: 872.97601 | AC9: 1127.7802 | AD9: 99.105085 | AE9: 0.35870895 | AF9: 0.017617818 | AG9: 2.1256874 | AH9: 0.26537633 | AI9: 0.52326218 | AJ9: 12.040485 | AK9: 0.099243693 | AL9: 2.3568435 | AM9: 0.14108445 | AN9: 300.84814 | AO9: 73.727142 | AP9: 856.80807 | AQ9: 5.2472785 | AR9: 0 | AS9: 0.0005718553 | AT9: 0 | AU9: 0.00063632568 | AV9: 0.056546983 | AW9: 0.48573332 | AX9: 0 | AY9: 0 | AZ9: 0.0012649316 | BA9: 0 | BB9: 0 | BC9: 30.87306 | BD9: 0.00098407306 | BE9: 1.0283274 | BF9: 0.0004273447 | BG9: 0 | BH9: 0.016273694 | BI9: 0 | BJ9: 10.428383 | BK9: 2.3168999 | BL9: 0.0062815712 | BM9: 0.17489257 | BN9: 0.078576053 | BO9: 0.00020935854 | BP9: 0.049291046 | BQ9: 0 | BR9: 3771.025 | BS9: 0 | BT9: 0 | BU9: 0 | BV9: 0.55813519 | BW9: 0.11341536 | BX9: 0 | BY9: 0.67155055 | BZ9: 3771.6966
A10: 0680 | B10: Extração de petróleo e gás, inclusive as atividades de apoio | C10: 1.7942698 | D10: 1.6380446 | E10: 0 | F10: 0.016626345 | G10: 3.5970489 | H10: 1.1534651 | I10: 0.11043362 | J10: 0.20538177 | K10: 0.0003490028 | L10: 0.69414656 | M10: 0.19356972 | N10: 0 | O10: 0.10867274 | P10: 0.00015941145 | Q10: 0.042492599 | R10: 0.0038532718 | S10: 0.47928646 | T10: 0 | U10: 1278.5219 | V10: 0.010790739 | W10: 1.2931183 | X10: 0.53564878 | Y10: 0.1466793 | Z10: 0.00017292546 | AA10: 0.82981026 | AB10: 2.0458735 | AC10: 1.4795362 | AD10: 0.13162112 | AE10: 0.12957748 | AF10: 0.0030663888 | AG10: 0.41122946 | AH10: 2.1885965 | AI10: 0.19094138 | AJ10: 0.17624497 | AK10: 0.057131982 | AL10: 0.043259429 | AM10: 0.93174852 | AN10: 0.074059782 | AO10: 0.127842 | AP10: 1.4384629 | AQ10: 3.5336011 | AR10: 1.7582502 | AS10: 0.049102582 | AT10: 0 | AU10: 0.065782284 | AV10: 0.0010749544 | AW10: 4.2943831 | AX10: 0 | AY10: 0 | AZ10: 0.0043192068 | BA10: 0 | BB10: 0 | BC10: 0.018987483 | BD10: 0 | BE10: 0.053151642 | BF10: 0.050652418 | BG10: 0.46020539 | BH10: 0.12871091 | BI10: 0.00039232705 | BJ10: 0.38946169 | BK10: 0.13148318 | BL10: 0 | BM10: 0.055582126 | BN10: 0.052800222 | BO10: 0 | BP10: 0.41761431 | BQ10: 0 | BR10: 1312.2707 | BS10: 0 | BT10: 0 | BU10: 0 | BV10: 0.2925917 | BW10: 3.4881745 | BX10: 0 | BY10: 3.7807662 | BZ10: 1316.0515
A11: 0791 | B11: Extração de minério de ferro, inclusive beneficiamentos e a aglomeração | C11: 0 | D11: 0 | E11: 0 | F11: 0.0014292883 | G11: 0.27216864 | H11: 406.75879 | I11: 6.3821469 | J11: 0.014122582 | K11: 0 | L11: 0.024450335 | M11: 0 | N11: 0 | O11: 0 | P11: 0 | Q11: 0 | R11: 0 | S11: 0.014644506 | T11: 0.013656063 | U11: 0 | V11: 0 | W11: 0 | X11: 0.0080323214 | Y11: 0 | Z11: 0 | AA11: 0.0086870108 | AB11: 21.152192 | AC11: 3067.068 | AD11: 9.3596862 | AE11: 0.14541126 | AF11: 0.009508029 | AG11: 0.37526261 | AH11: 0.89854495 | AI11: 0.083389975 | AJ11: 0.13986716 | AK11: 0.047906771 | AL11: 0.14019094 | AM11: 0.34547286 | AN11: 0 | AO11: 0.0051640715 | AP11: 0.20193878 | AQ11: 0.023987741 | AR11: 0 | AS11: 0.0071261968 | AT11: 0 | AU11: 0.0079295969 | AV11: 0 | AW11: 0 | AX11: 0 | AY11: 0 | AZ11: 0.0017580691 | BA11: 0 | BB11: 0 | BC11: 0.0014101766 | BD11: 0 | BE11: 0.31802821 | BF11: 0 | BG11: 0 | BH11: 0.052224601 | BI11: 0 | BJ11: 0.0017399817 | BK11: 0 | BL11: 0 | BM11: 0.0052064621 | BN11: 0 | BO11: 0 | BP11: 0 | BQ11: 0 | BR11: 3513.8901 | BS11: 0 | BT11: 0 | BU11: 0 | BV11: 0.12875529 | BW11: 1.4133299 | BX11: 0 | BY11: 1.5420852 | BZ11: 3515.4322
A12: 0792 | B12: Extração de minerais metálicos não ferrosos, inclusive beneficiamentos | C12: 0.075186838 | D12: 0.030526763 | E12: 0.00061285588 | F12: 0.00081780211 | G12: 6.2908159 | H12: 0.029488574 | I12: 177.27048 | J12: 0.12494332 | K12: 0.0037839434 | L12: 0.23607711 | M12: 0.024880781 | N12: 0 | O12: 0.00077285288 | P12: 0 | Q12: 0.00059279662 | R12: 0 | S12: 0.15295768 | T12: 0.120816 | U12: 0 | V12: 0 | W12: 0.14117743 | X12: 0.088966064 | Y12: 0.0073311234 | Z12: 0.0014901153 | AA12: 0.057250833 | AB12: 3.7684778 | AC12: 65.967765 | AD12: 1107.6997 | AE12: 1.2909891 | AF12: 0.084118092 | AG12: 3.1936218 | AH12: 0.52221544 | AI12: 0.2915416 | AJ12: 1.238018 | AK12: 0.32211454 | AL12: 1.2453307 | AM12: 0.15585724 | AN12: 0.0016636512 | AO12: 0.036532907 | AP12: 0.97733583 | AQ12: 0.020409952 | AR12: 0 | AS12: 4.3988869e-05 | AT12: 0 | AU12: 4.8948129e-05 | AV12: 0.001607213 | AW12: 0.0060020296 | AX12: 0 | AY12: 0 | AZ12: 1.0852278e-05 | BA12: 0 | BB12: 0 | BC12: 0.017964166 | BD12: 0 | BE12: 2.1853657e-05 | BF12: 0 | BG12: 0 | BH12: 0.00078144819 | BI12: 0 | BJ12: 0.0023694856 | BK12: 0.00063866703 | BL12: 0 | BM12: 0.0032310018 | BN12: 0.0034853009 | BO12: 0 | BP12: 0.002163732 | BQ12: 0 | BR12: 1371.513 | BS12: 0 | BT12: 0 | BU12: 0 | BV12: 0.13760191 | BW12: 0.0087242588 | BX12: 0 | BY12: 0.14632616 | BZ12: 1371.6594
A13: 1091 | B13: Abate e produtos de carne, inclusive os produtos do laticínio e da pesca | C13: 2.8658272 | D13: 117.13131 | E13: 1.3779864 | F13: 0.28444173 | G13: 0.19238587 | H13: 0.15218457 | I13: 0.031587152 | J13: 1619.9971 | K13: 0.0027911581 | L13: 202.75119 | M13: 4.3658116 | N13: 0 | O13: 0.090511224 | P13: 0.040051706 | Q13: 76.800993 | R13: 0.122156 | S13: 0.48317492 | T13: 0.023009652 | U13: 0.055374398 | V13: 42.845826 | W13: 1.6760092 | X13: 3.210113 | Y13: 126.15549 | Z13: 0.34915485 | AA13: 0.33810371 | AB13: 0.068518702 | AC13: 0.11523864 | AD13: 0.046117437 | AE13: 3.5910208 | AF13: 0.016366015 | AG13: 0.079257401 | AH13: 0.15391728 | AI13: 0.076664636 | AJ13: 0.037507165 | AK13: 0.01948119 | AL13: 0.11066619 | AM13: 0.093666539 | AN13: 0.036493999 | AO13: 0.047477183 | AP13: 0.36740069 | AQ13: 39.79914 | AR13: 0.022786084 | AS13: 0.0013087543 | AT13: 0.014185215 | AU13: 0.0091797296 | AV13: 33.009378 | AW13: 996.68083 | AX13: 0 | AY13: 0.0021615613 | AZ13: 0.036982574 | BA13: 0.002668563 | BB13: 0.096258261 | BC13: 0.014439347 | BD13: 0.050553773 | BE13: 0.0063910294 | BF13: 0.060927381 | BG13: 0.0087059347 | BH13: 0.033741207 | BI13: 0.0040686161 | BJ13: 169.70825 | BK13: 83.574686 | BL13: 17.183632 | BM13: 113.01524 | BN13: 41.400994 | BO13: 0.026583915 | BP13: 12.538532 | BQ13: 0 | BR13: 3713.504 | BS13: 0.25133342 | BT13: 0.051975437 | BU13: 0 | BV13: 776.69167 | BW13: 0.16452009 | BX13: 0 | BY13: 777.1595 | BZ13: 4490.6635
A14: 1092 | B14: Fabricação e refino de açúcar | C14: 0.89363676 | D14: 12.459994 | E14: 0 | F14: 0.0063591997 | G14: 10.651371 | H14: 0.91815905 | I14: 0.093202777 | J14: 62.800158 | K14: 321.43928 | L14: 778.22591 | M14: 179.00045 | N14: 0 | O14: 0.0043676189 | P14: 0.0033656406 | Q14: 0 | R14: 0.0069212463 | S14: 0.034336377 | T14: 0 | U14: 280.34569 | V14: 243.24867 | W14: 4.8404534 | X14: 83.655787 | Y14: 23.417578 | Z14: 10.747838 | AA14: 0.016082563 | AB14: 0.020503539 | AC14: 0.0056672087 | AD14: 0.0098464377 | AE14: 0.39570008 | AF14: 0.0026644655 | AG14: 0.051484092 | AH14: 2.9365353 | AI14: 0.18327219 | AJ14: 0.0040576894 | AK14: 0.046415175 | AL14: 0 | AM14: 1.1704026 | AN14: 0 | AO14: 0.011027622 | AP14: 6.3838196 | AQ14: 20.374978 | AR14: 11.316698 | AS14: 0.12407385 | AT14: 0.0011286189 | AU14: 1.0163222 | AV14: 0.16606235 | AW14: 144.68673 | AX14: 0.0651729 | AY14: 0.010916796 | AZ14: 0.028939027 | BA14: 0 | BB14: 1.8911935 | BC14: 0.25023632 | BD14: 2.1953858 | BE14: 2.1276933 | BF14: 1.069718 | BG14: 3.1630982 | BH14: 4.6061709 | BI14: 0.86615699 | BJ14: 26.559434 | BK14: 11.596162 | BL14: 0.9499021 | BM14: 14.704892 | BN14: 3.8957237 | BO14: 0.27375893 | BP14: 3.8489949 | BQ14: 0 | BR14: 2279.8205 | BS14: 0 | BT14: 0 | BU14: 0 | BV14: 97.826366 | BW14: 4.9379305 | BX14: 0 | BY14: 102.7643 | BZ14: 2382.5848
A15: 1093 | B15: Outros produtos alimentares | C15: 114.52154 | D15: 992.35552 | E15: 66.574221 | F15: 6.5196112 | G15: 6.372078 | H15: 1.7950647 | I15: 0.42222057 | J15: 1983.2518 | K15: 3.568123 | L15: 1973.7013 | M15: 178.63695 | N15: 0.012707283 | O15: 0.8503087 | P15: 0.50348964 | Q15: 1.0275712 | R15: 1.8443183 | S15: 39.423954 | T15: 0.417006 | U15: 100.41041 | V15: 129.09178 | W15: 19.613201 | X15: 42.595389 | Y15: 24.511543 | Z15: 7.1845959 | AA15: 3.9982595 | AB15: 6.2938476 | AC15: 2.3219836 | AD15: 0.53085475 | AE15: 3.6220196 | AF15: 0.096098637 | AG15: 0.76232623 | AH15: 1.6507507 | AI15: 0.72765338 | AJ15: 0.72865314 | AK15: 0.16107918 | AL15: 1.3121766 | AM15: 0.91304704 | AN15: 0.18422446 | AO15: 1.0179648 | AP15: 10.09432 | AQ15: 163.77877 | AR15: 4.9334854 | AS15: 0.053080009 | AT15: 1.6069348 | AU15: 0.49885516 | AV15: 19.334383 | AW15: 937.71127 | AX15: 0.03411354 | AY15: 0.025225476 | AZ15: 0.87850875 | BA15: 0.029578126 | BB15: 10.460602 | BC15: 1.5450194 | BD15: 3.241592 | BE15: 0.8483967 | BF15: 2.5727112 | BG15: 1.2588998 | BH15: 2.0384912 | BI15: 0.31956313 | BJ15: 181.63265 | BK15: 106.41433 | BL15: 13.156699 | BM15: 182.01238 | BN15: 48.50852 | BO15: 1.1279428 | BP15: 39.102911 | BQ15: 0 | BR15: 7452.7448 | BS15: 7.850796e-05 | BT15: 0.17404619 | BU15: 0 | BV15: 871.32255 | BW15: 1.2530169 | BX15: 0 | BY15: 872.7497 | BZ15: 8325.4945
A16: 1100 | B16: Fabricação de bebidas | C16: 0.034748847 | D16: 0.054659464 | E16: 0.00020761871 | F16: 0.44498383 | G16: 0.29634916 | H16: 0.41283892 | I16: 0.065381387 | J16: 43.822945 | K16: 0.010574497 | L16: 4.0478173 | M16: 743.2417 | N16: 0 | O16: 0.025102593 | P16: 0.002840022 | Q16: 0.017549712 | R16: 0.22688052 | S16: 0.15818002 | T16: 0.038338547 | U16: 0.87723413 | V16: 0.092033046 | W16: 0.26518629 | X16: 0.80278386 | Y16: 0.29050074 | Z16: 0.21201389 | AA16: 0.28274806 | AB16: 0.11768455 | AC16: 0.14445407 | AD16: 0.035081378 | AE16: 0.59137072 | AF16: 0.054743409 | AG16: 0.21006912 | AH16: 1.0154802 | AI16: 0.28466834 | AJ16: 0.11964628 | AK16: 0.066496036 | AL16: 0.1396594 | AM16: 0.47260779 | AN16: 0.10981885 | AO16: 0.071471977 | AP16: 1.3715055 | AQ16: 0.55948249 | AR16: 0.056846714 | AS16: 0.0056859467 | AT16: 0.69982725 | AU16: 0.018175967 | AV16: 28.937872 | AW16: 1071.8959 | AX16: 0.00018092185 | AY16: 0 | AZ16: 0.0018462839 | BA16: 0 | BB16: 6.9081184 | BC16: 0.015328102 | BD16: 0.006939075 | BE16: 0.0058532705 | BF16: 0.0025025987 | BG16: 0.0087209641 | BH16: 0.070872173 | BI16: 0.009181035 | BJ16: 15.931112 | BK16: 8.2667402 | BL16: 1.0921936 | BM16: 11.53718 | BN16: 14.261275 | BO16: 1.2099215 | BP16: 0.79361944 | BQ16: 0 | BR16: 1962.8237 | BS16: 0 | BT16: 0 | BU16: 0 | BV16: 754.96736 | BW16: 1.3480571 | BX16: 0 | BY16: 756.31542 | BZ16: 2719.1392
A17: 1200 | B17: Fabricação de produtos do fumo | C17: 0.11144102 | D17: 0.011599523 | E17: 0.0005754239 | F17: 0.00011469598 | G17: 0.01825887 | H17: 0.022339364 | I17: 0.0017235446 | J17: 0.022087329 | K17: 0.00037800797 | L17: 0.022749417 | M17: 0.0014223017 | N17: 18.842392 | O17: 0.0037222039 | P17: 0.0023730339 | Q17: 0.0029141307 | R17: 0.011815433 | S17: 0.087292047 | T17: 0.0085145527 | U17: 0.0012450377 | V17: 0.00063033681 | W17: 0.0040857265 | X17: 0.0011383977 | Y17: 0.0092438924 | Z17: 0.0055980373 | AA17: 0.01693952 | AB17: 0.013333363 | AC17: 0 | AD17: 0 | AE17: 0.0084312268 | AF17: 0.0046643983 | AG17: 0.0034528422 | AH17: 0.068034572 | AI17: 0.0066211346 | AJ17: 0.0040830657 | AK17: 0.00093590735 | AL17: 0.0058215598 | AM17: 0.026361376 | AN17: 0.00027380215 | AO17: 0.00040458921 | AP17: 0.011324037 | AQ17: 0.051490323 | AR17: 0.00099670438 | AS17: 0.00097417794 | AT17: 0 | AU17: 0.002855091 | AV17: 0.0014625486 | AW17: 0.0073128779 | AX17: 0.0048582561 | AY17: 0.00075059885 | AZ17: 0.0003624845 | BA17: 0.0059004739 | BB17: 0.0086296424 | BC17: 0.0017873965 | BD17: 0.011251354 | BE17: 0.002520119 | BF17: 0.0052593409 | BG17: 0.0033909223 | BH17: 0.022686778 | BI17: 0 | BJ17: 0.0061446114 | BK17: 0.0047652635 | BL17: 0.0036675889 | BM17: 0.0020757046 | BN17: 0.011140522 | BO17: 0 | BP17: 0.0043362371 | BQ17: 0 | BR17: 19.528954 | BS17: 0 | BT17: 0 | BU17: 0 | BV17: 21.42127 | BW17: 0.11341536 | BX17: 0 | BY17: 21.534685 | BZ17: 41.063639
... A72: 9700 | B72: Serviços domésticos | C72: 0 | D72: 0 | E72: 0 | F72: 0 | G72: 0 | H72: 0 | I72: 0 | J72: 0 | K72: 0 | L72: 0 | M72: 0 | N72: 0 | O72: 0 | P72: 0 | Q72: 0 | R72: 0 | S72: 0 | T72: 0 | U72: 0 | V72: 0 | W72: 0 | X72: 0 | Y72: 0 | Z72: 0 | AA72: 0 | AB72: 0 | AC72: 0 | AD72: 0 | AE72: 0 | AF72: 0 | AG72: 0 | AH72: 0 | AI72: 0 | AJ72: 0 | AK72: 0 | AL72: 0 | AM72: 0 | AN72: 0 | AO72: 0 | AP72: 0 | AQ72: 0 | AR72: 0 | AS72: 0 | AT72: 0 | AU72: 0 | AV72: 0 | AW72: 0 | AX72: 0 | AY72: 0 | AZ72: 0 | BA72: 0 | BB72: 0 | BC72: 0 | BD72: 0 | BE72: 0 | BF72: 0 | BG72: 0 | BH72: 0 | BI72: 0 | BJ72: 0 | BK72: 0 | BL72: 0 | BM72: 0 | BN72: 0 | BO72: 0 | BP72: 0 | BQ72: 0 | BR72: 0 | BS72: 0 | BT72: 0 | BU72: 0 | BV72: 0 | BW72: 0 | BX72: 0 | BY72: 0 | BZ72: 0
A74: Total | C74: 3097.4602 | D74: 2835.4786 | E74: 175.46457 | F74: 163.05551 | G74: 1041.036 | H74: 1051.0307 | I74: 280.86622 | J74: 6060.9692 | K74: 2086.236 | L74: 12841.264 | M74: 1666.7598 | N74: 66.669065 | O74: 789.62676 | P74: 929.17349 | Q74: 616.4875 | R74: 532.93003 | S74: 1880.5339 | T74: 121.87049 | U74: 2933.7478 | V74: 2079.4537 | W74: 2699.3492 | X74: 923.36063 | Y74: 780.66296 | Z74: 294.6771 | AA74: 1430.9406 | AB74: 2017.5154 | AC74: 5565.7559 | AD74: 1977.0998 | AE74: 1803.2098 | AF74: 1308.5452 | AG74: 1031.6393 | AH74: 1746.2869 | AI74: 1538.4567 | AJ74: 985.74293 | AK74: 269.57178 | AL74: 740.95774 | AM74: 706.28255 | AN74: 817.26843 | AO74: 307.49848 | AP74: 5027.8755 | AQ74: 3620.0957 | AR74: 2313.5068 | AS74: 107.60527 | AT74: 219.73581 | AU74: 152.29228 | AV74: 263.59872 | AW74: 4358.831 | AX74: 46.0163 | AY74: 74.566764 | AZ74: 74.736721 | BA74: 216.1462 | BB74: 280.77431 | BC74: 180.41915 | BD74: 217.43387 | BE74: 184.96713 | BF74: 256.90317 | BG74: 156.04992 | BH74: 491.0772 | BI74: 80.805393 | BJ74: 1214.5696 | BK74: 591.49611 | BL74: 93.506557 | BM74: 1306.8304 | BN74: 1202.5315 | BO74: 57.362797 | BP74: 842.34528 | BQ74: 0 | BR74: 91827.015 | BS74: 10.789849 | BT74: 56.373802 | BU74: 0 | BV74: 14055.729 | BW74: 6753.0926 | BX74: 0 | BY74: 20875.985 | BZ74: 112703
A76: (1) Exportação de bens e serviços líquida de ajuste CIF/FOB.

Sheet An
A1: Tabela 8 - Matriz dos coeficientes técnicos dos insumos nacionais (An) - 2021 (Preços correntes)
A2: Matriz D.Bn
A3: Código da Atividade Nível 67 | B3: Descrição da Atividade Nível 67 | C3: Atividades | L3: =C3 -> Atividades | U3: =L3 -> Atividades | AD3: =U3 -> Atividades | AM3: =AD3 -> Atividades | AV3: =AM3 -> Atividades | BE3: =AV3 -> Atividades | BQ3: =BE3 -> Atividades
C4: 0191 | D4: 0192 | E4: 0280 | F4: 0580 | G4: 0680 | H4: 0791 | I4: 0792 | J4: 1091 | K4: 1092 | L4: 1093 | M4: 1100 | N4: 1200 | O4: 1300 | P4: 1400 | Q4: 1500 | R4: 1600 | S4: 1700 | T4: 1800 | U4: 1991 | V4: 1992 | W4: 2091 | X4: 2092 | Y4: 2093 | Z4: 2100 | AA4: 2200 | AB4: 2300 | AC4: 2491 | AD4: 2492 | AE4: 2500 | AF4: 2600 | AG4: 2700 | AH4: 2800 | AI4: 2991 | AJ4: 2992 | AK4: 3000 | AL4: 3180 | AM4: 3300 | AN4: 3500 | AO4: 3680 | AP4: 4180 | AQ4: 4580 | AR4: 4900 | AS4: 5000 | AT4: 5100 | AU4: 5280 | AV4: 5500 | AW4: 5600 | AX4: 5800 | AY4: 5980 | AZ4: 6100 | BA4: 6280 | BB4: 6480 | BC4: 6800 | BD4: 6980 | BE4: 7180 | BF4: 7380 | BG4: 7700 | BH4: 7880 | BI4: 8000 | BJ4: 8400 | BK4: 8591 | BL4: 8592 | BM4: 8691 | BN4: 8692 | BO4: 9080 | BP4: 9480 | BQ4: 9700
C5: Agricultura, inclusive o apoio à agricultura e a pós-colheita | D5: Pecuária, inclusive o apoio à pecuária | E5: Produção florestal; pesca e aquicultura | F5: Extração de carvão mineral e de minerais não metálicos | G5: Extração de petróleo e gás, inclusive as atividades de apoio | H5: Extração de minério de ferro, inclusive beneficiamentos e a aglomeração | I5: Extração de minerais metálicos não ferrosos, inclusive beneficiamentos | J5: Abate e produtos de carne, inclusive os produtos do laticínio e da pesca | K5: Fabricação e refino de açúcar | L5: Outros produtos alimentares | M5: Fabricação de bebidas | N5: Fabricação de produtos do fumo | O5: Fabricação de produtos têxteis | P5: Confecção de artefatos do vestuário e acessórios | Q5: Fabricação de calçados e de artefatos de couro | R5: Fabricação de produtos da madeira | S5: Fabricação de celulose, papel e produtos de papel | T5: Impressão e reprodução de gravações | U5: Refino de petróleo e coquerias | V5: Fabricação de biocombustíveis | W5: Fabricação de químicos orgânicos e inorgânicos, resinas e elastômeros | X5: Fabricação de defensivos, desinfestantes, tintas e químicos diversos | Y5: Fabricação de produtos de limpeza, cosméticos/perfumaria e higiene pessoal | Z5: Fabricação de produtos farmoquímicos e farmacêuticos | AA5: Fabricação de produtos de borracha e de material plástico | AB5: Fabricação de produtos de minerais não metálicos | AC5: Produção de ferro gusa/ferroligas, siderurgia e tubos de aço sem costura | AD5: Metalurgia de metais não ferosos e a fundição de metais | AE5: Fabricação de produtos de metal, exceto máquinas e equipamentos | AF5: Fabricação de equipamentos de informática, produtos eletrônicos e ópticos | AG5: Fabricação de máquinas e equipamentos elétricos | AH5: Fabricação de máquinas e equipamentos mecânicos | AI5: Fabricação de automóveis, caminhões e ônibus, exceto peças | AJ5: Fabricação de peças e acessórios para veículos automotores | AK5: Fabricação de outros equipamentos de transporte, exceto veículos automotores | AL5: Fabricação de móveis e de produtos de indústrias diversas | AM5: Manutenção, reparação e instalação de máquinas e equipamentos | AN5: Energia elétrica, gás natural e outras utilidades | AO5: Água, esgoto e gestão de resíduos | AP5: Construção | AQ5: Comércio por atacado e varejo | AR5: Transporte terrestre | AS5: Transporte aquaviário | AT5: Transporte aéreo | AU5: Armazenamento, atividades auxiliares dos transportes e correio | AV5: Alojamento | AW5: Alimentação | AX5: Edição e edição integrada à impressão | AY5: Atividades de televisão, rádio, cinema e gravação/edição de som e imagem | AZ5: Telecomunicações | BA5: Desenvolvimento de sistemas e outros serviços de informação | BB5: Intermediação financeira, seguros e previdência complementar | BC5: Atividades imobiliárias | BD5: Atividades jurídicas, contábeis, consultoria e sedes de empresas | BE5: Serviços de arquitetura, engenharia, testes/análises técnicas e P & D | BF5: Outras atividades profissionais, científicas e técnicas | BG5: Aluguéis não imobiliários e gestão de ativos de propriedade intelectual | BH5: Outras atividades administrativas e serviços complementares | BI5: Atividades de vigilância, segurança e investigação | BJ5: Administração pública, defesa e seguridade social | BK5: Educação pública | BL5: Educação privada | BM5: Saúde pública | BN5: Saúde privada | BO5: Atividades artísticas, criativas e de espetáculos | BP5: Organizações associativas e outros serviços pessoais | BQ5: Serviços domésticos
A6: 0191 | B6: Agricultura, inclusive o apoio à agricultura e a pós-colheita | C6: 0.022080253 | D6: 0.044026109 | E6: 0.0040142243 | F6: 8.1267873e-05 | G6: 2.4762068e-05 | H6: 6.7474062e-05 | I6: 8.4626389e-05 | J6: 0.0278027 | K6: 0.42630859 | L6: 0.28107319 | M6: 0.031577297 | N6: 0.39434711 | O6: 0.14668922 | P6: 0.010247144 | Q6: 0.00016164021 | R6: 0.0022678829 | S6: 0.0016745362 | T6: 1.364974e-05 | U6: 2.5431308e-05 | V6: 0.34914015 | W6: 5.3651916e-05 | X6: 0.00016412256 | Y6: 6.2469969e-05 | Z6: 0.00028216043 | AA6: 0.00019249372 | AB6: 0.00016976784 | AC6: 0.00020031746 | AD6: 0.00032709789 | AE6: 3.294783e-05 | AF6: 2.906259e-06 | AG6: 3.6738452e-06 | AH6: 6.0207243e-06 | AI6: 3.0115978e-06 | AJ6: 4.1729774e-06 | AK6: 1.2365652e-05 | AL6: 0.00015588083 | AM6: 1.1662192e-06 | AN6: 2.1097608e-06 | AO6: 0.00072060921 | AP6: 0.00058943698 | AQ6: 0.011987073 | AR6: 4.1119585e-06 | AS6: 3.2700724e-06 | AT6: 9.7101003e-06 | AU6: 0.0001052993 | AV6: 0.013755438 | AW6: 0.020143199 | AX6: 1.2159624e-05 | AY6: 2.0378029e-05 | AZ6: 0.00025015107 | BA6: 2.0017796e-05 | BB6: 2.2745777e-05 | BC6: 2.5676984e-05 | BD6: 4.7890428e-05 | BE6: 0.00019325807 | BF6: 1.4298188e-05 | BG6: 1.8730182e-05 | BH6: 0.00067559537 | BI6: 1.0301982e-05 | BJ6: 0.0013087089 | BK6: 0.0012792715 | BL6: 0.00061568361 | BM6: 0.0024157324 | BN6: 0.00073054119 | BO6: 0.000131622 | BP6: 0.0022737796 | BQ6: 0
A7: 0192 | B7: Pecuária, inclusive o apoio à pecuária | C7: 0.002437073 | D7: 0.039732298 | E7: 0.0051479699 | F7: 0.00020519791 | G7: 6.1034758e-05 | H7: 0.00012110227 | I7: 0.00015478441 | J7: 0.32423921 | K7: 0.0024024687 | L7: 0.01621153 | M7: 0.00078617482 | N7: 0.018319538 | O7: 0.0058087643 | P7: 0.004781477 | Q7: 0.00017492997 | R7: 0.0045496088 | S7: 0.002972409 | T7: 2.3423424e-05 | U7: 1.9421505e-06 | V7: 0.0040318921 | W7: 0.00014913787 | X7: 7.9727174e-05 | Y7: 0.00015980541 | Z7: 0.00013875166 | AA7: 0.00029114786 | AB7: 0.00077420406 | AC7: 0.00042665196 | AD7: 0.00062939812 | AE7: 2.6460305e-05 | AF7: 5.9023134e-06 | AG7: 1.1033583e-05 | AH7: 1.1732579e-05 | AI7: 5.5164851e-06 | AJ7: 9.1743131e-06 | AK7: 1.8635301e-05 | AL7: 9.282763e-05 | AM7: 2.754806e-06 | AN7: 2.7708377e-06 | AO7: 0.00011249581 | AP7: 0.0011616424 | AQ7: 0.00043035488 | AR7: 4.0877729e-06 | AS7: 2.7165395e-06 | AT7: 9.8556646e-06 | AU7: 0.00017488585 | AV7: 0.016336205 | AW7: 0.0090107508 | AX7: 1.8695948e-05 | AY7: 3.1484563e-05 | AZ7: 0.0004463788 | BA7: 3.2682285e-05 | BB7: 3.520449e-05 | BC7: 4.7273918e-05 | BD7: 3.717018e-05 | BE7: 0.00025049544 | BF7: 6.5537589e-05 | BG7: 2.5521771e-05 | BH7: 0.00012724821 | BI7: 1.2599278e-05 | BJ7: 0.00043146669 | BK7: 0.00037665272 | BL7: 0.00019644106 | BM7: 0.00067228825 | BN7: 0.00034944391 | BO7: 0.00011864407 | BP7: 0.00032182773 | BQ7: 0
A8: 0280 | B8: Produção florestal; pesca e aquicultura | C8: 0.0021952584 | D8: 0.0062447215 | E8: 0.046112668 | F8: 8.0492855e-05 | G8: 4.7800085e-06 | H8: 9.2069286e-06 | I8: 1.1434981e-05 | J8: 0.0058687985 | K8: 1.3663213e-05 | L8: 0.00066145487 | M8: 0.00015759559 | N8: 0.00096207808 | O8: 0.00032212112 | P8: 8.2200259e-05 | Q8: 8.9490919e-05 | R8: 0.053594027 | S8: 0.034170112 | T8: 1.8468161e-06 | U8: 1.6168813e-07 | V8: 0.00012324075 | W8: 0.00094593411 | X8: 2.6048433e-05 | Y8: 2.0697896e-06 | Z8: 2.1105707e-06 | AA8: 0.0030672022 | AB8: 0.00081556474 | AC8: 0.0046757841 | AD8: 4.6414168e-05 | AE8: 3.0214653e-05 | AF8: 6.3203299e-07 | AG8: 1.0505896e-06 | AH8: 1.3106791e-06 | AI8: 5.9069325e-07 | AJ8: 8.8612522e-07 | AK8: 1.6027643e-06 | AL8: 1.8188346e-05 | AM8: 3.2860091e-07 | AN8: 3.7938974e-07 | AO8: 7.7208359e-06 | AP8: 0.0013618128 | AQ8: 0.00010600298 | AR8: 4.4992867e-07 | AS8: 3.1279392e-07 | AT8: 9.0552714e-07 | AU8: 1.3563295e-05 | AV8: 0.0013543363 | AW8: 0.0016466721 | AX8: 2.2201611e-06 | AY8: 3.3135983e-06 | AZ8: 3.2990539e-05 | BA8: 3.1635788e-06 | BB8: 2.9162143e-06 | BC8: 3.5850553e-06 | BD8: 3.3568174e-06 | BE8: 4.6379043e-05 | BF8: 1.6619004e-06 | BG8: 2.5977794e-06 | BH8: 8.8200811e-06 | BI8: 1.2842587e-06 | BJ8: 0.00011554124 | BK8: 0.0001767929 | BL8: 4.6946716e-05 | BM8: 0.00033595145 | BN8: 4.0761666e-05 | BO8: 1.1332777e-05 | BP8: 2.3434108e-05 | BQ8: 0
A9: 0580 | B9: Extração de carvão mineral e de minerais não metálicos | C9: 0.0001941155 | D9: 0.0030103577 | E9: 0.00040346344 | F9: 0.013693411 | G9: 0.0020171098 | H9: 4.8506335e-06 | I9: 0.00018865273 | J9: 0.00021167312 | K9: 0.00021924686 | L9: 0.00063610365 | M9: 0.00024597905 | N9: 1.5220099e-06 | O9: 5.2985493e-06 | P9: 2.5826e-06 | Q9: 6.5001787e-06 | R9: 2.9955402e-06 | S9: 0.0001017973 | T9: 4.9012332e-05 | U9: 1.6759353e-05 | V9: 0.0055435595 | W9: 0.0052822271 | X9: 0.00096802486 | Y9: 8.9803198e-05 | Z9: 1.4008767e-05 | AA9: 3.3497614e-05 | AB9: 0.053607885 | AC9: 0.006427242 | AD9: 0.0051574776 | AE9: 7.5800828e-05 | AF9: 4.9387328e-06 | AG9: 0.00059348431 | AH9: 3.5872202e-05 | AI9: 0.00010212137 | AJ9: 0.00039156801 | AK9: 8.5417594e-05 | AL9: 0.00042163198 | AM9: 4.2609359e-05 | AN9: 0.0007920624 | AO9: 0.0058380746 | AP9: 0.010256116 | AQ9: 8.1412086e-05 | AR9: 1.416909e-06 | AS9: 4.1341999e-06 | AT9: 1.3193403e-06 | AU9: 4.5896521e-05 | AV9: 9.2334602e-05 | AW9: 4.9254787e-05 | AX9: 5.6086579e-06 | AY9: 2.8689079e-06 | AZ9: 3.2222083e-06 | BA9: 3.3863258e-06 | BB9: 1.6971739e-06 | BC9: 0.00034909349 | BD9: 4.8288563e-06 | BE9: 1.6165264e-05 | BF9: 3.4016662e-06 | BG9: 4.9466377e-06 | BH9: 6.169607e-06 | BI9: 2.2612537e-06 | BJ9: 9.7944672e-05 | BK9: 5.3114144e-05 | BL9: 9.6011299e-06 | BM9: 5.1392436e-05 | BN9: 1.1614876e-05 | BO9: 2.3249503e-05 | BP9: 1.5059817e-05 | BQ9: 0
A10: 0680 | B10: Extração de petróleo e gás, inclusive as atividades de apoio | C10: 3.8351942e-05 | D10: 6.734038e-05 | E10: 2.4172687e-05 | F10: 0.00014622201 | G10: 0.023901103 | H10: 0.0046494484 | I10: 0.0021609298 | J10: 7.307333e-05 | K10: 1.3173987e-05 | L10: 0.00061538306 | M10: 0.00059336555 | N10: 1.3296316e-05 | O10: 0.00066117696 | P10: 1.4654171e-05 | Q10: 3.3936199e-05 | R10: 0.00046839457 | S10: 0.0022958821 | T10: 2.7213746e-05 | U10: 0.23983758 | V10: 1.7018667e-05 | W10: 0.002669001 | X10: 0.00036762169 | Y10: 0.00022249307 | Z10: 0.00016968883 | AA10: 0.00032943602 | AB10: 0.0023834905 | AC10: 0.00077742795 | AD10: 0.0012893652 | AE10: 0.0009445186 | AF10: 6.2249802e-06 | AG10: 0.00016386169 | AH10: 0.00024912049 | AI10: 0.00011710242 | AJ10: 0.00045386425 | AK10: 3.0124683e-05 | AL10: 2.3593952e-05 | AM10: 0.00021325605 | AN10: 0.022901479 | AO10: 0.014511301 | AP10: 0.002520689 | AQ10: 0.00012703093 | AR10: 0.00029188679 | AS10: 7.3530628e-05 | AT10: 8.9718053e-06 | AU10: 0.00076751949 | AV10: 0.00010073844 | AW10: 0.00013430562 | AX10: 3.5114868e-05 | AY10: 2.8871927e-05 | AZ10: 0.0010606236 | BA10: 3.0351368e-05 | BB10: 1.8253389e-05 | BC10: 6.3646978e-06 | BD10: 5.0071573e-05 | BE10: 0.00094454075 | BF10: 3.2681033e-05 | BG10: 7.8762299e-05 | BH10: 4.8580163e-05 | BI10: 2.0041932e-05 | BJ10: 0.0032784552 | BK10: 9.4484897e-05 | BL10: 9.515334e-05 | BM10: 1.1851706e-05 | BN10: 2.1258615e-05 | BO10: 0.00024641147 | BP10: 0.00019361722 | BQ10: 0
A11: 0791 | B11: Extração de minério de ferro, inclusive beneficiamentos e a aglomeração | C11: 7.5327491e-07 | D11: 4.1330299e-06 | E11: 1.3183349e-06 | F11: 2.556852e-06 | G11: 3.241624e-05 | H11: 0.025385668 | I11: 0.0031474028 | J11: 2.3353639e-06 | K11: 1.0970767e-06 | L11: 2.5463549e-06 | M11: 3.3129412e-06 | N11: 5.4112406e-06 | O11: 2.5757348e-06 | P11: 1.0689896e-06 | Q11: 1.8805967e-06 | R11: 3.094897e-06 | S11: 5.8041908e-06 | T11: 2.8202998e-05 | U11: 4.3491846e-07 | V11: 1.6611976e-07 | W11: 1.5097073e-06 | X11: 3.8502331e-06 | Y11: 3.8850104e-06 | Z11: 9.9760584e-06 | AA11: 2.3480818e-06 | AB11: 0.0025166854 | AC11: 0.1747721 | AD11: 0.00077260517 | AE11: 2.9213302e-05 | AF11: 3.4539073e-06 | AG11: 9.6563494e-05 | AH11: 8.84032e-05 | AI11: 1.6168905e-05 | AJ11: 4.2912978e-05 | AK11: 3.8140743e-05 | AL11: 4.1293128e-05 | AM11: 7.5791212e-05 | AN11: 6.9116132e-07 | AO11: 0.00019061071 | AP11: 0.00025261682 | AQ11: 2.6252934e-06 | AR11: 2.7409773e-06 | AS11: 5.8440733e-06 | AT11: 1.2008923e-07 | AU11: 5.2458411e-05 | AV11: 1.0738673e-05 | AW11: 1.146284e-05 | AX11: 9.0464672e-07 | AY11: 4.6247366e-07 | AZ11: 0.00013447758 | BA11: 2.9026188e-06 | BB11: 7.1106018e-06 | BC11: 1.085177e-05 | BD11: 6.8314484e-06 | BE11: 0.00015976725 | BF11: 8.256837e-07 | BG11: 2.6814036e-06 | BH11: 2.8300705e-05 | BI11: 1.7127223e-06 | BJ11: 5.7890132e-05 | BK11: 6.7714598e-06 | BL11: 1.707494e-06 | BM11: 6.5089798e-05 | BN11: 4.2800285e-07 | BO11: 2.1005622e-05 | BP11: 3.0131767e-06 | BQ11: 0
A12: 0792 | B12: Extração de minerais metálicos não ferrosos, inclusive beneficiamentos | C12: 2.8154639e-06 | D12: 3.3061899e-06 | E12: 5.8580758e-07 | F12: 1.3650173e-06 | G12: 0.00020744391 | H12: 0.00016438643 | I12: 0.036423778 | J12: 1.2123324e-05 | K12: 1.1362087e-06 | L12: 2.0900392e-05 | M12: 9.6413936e-06 | N12: 5.5271164e-07 | O12: 6.1776086e-07 | P12: 4.1736738e-07 | Q12: 8.7665238e-07 | R12: 3.6970599e-07 | S12: 3.8803147e-05 | T12: 0.00019771254 | U12: 2.8076765e-08 | V12: 1.428637e-07 | W12: 1.6700028e-05 | X12: 3.0350026e-05 | Y12: 5.1302789e-06 | Z12: 3.4499891e-06 | AA12: 1.1243387e-05 | AB12: 0.00053643921 | AC12: 0.010600731 | AD12: 0.050981762 | AE12: 0.00024412778 | AF12: 1.7740954e-05 | AG12: 0.00077859926 | AH12: 7.7305099e-05 | AI12: 5.2129904e-05 | AJ12: 0.00043351418 | AK12: 0.00026344969 | AL12: 0.00035775759 | AM12: 5.5185889e-05 | AN12: 6.8860001e-07 | AO12: 1.614341e-05 | AP12: 4.9833628e-05 | AQ12: 4.3400136e-07 | AR12: 7.6955002e-07 | AS12: 9.1976112e-08 | AT12: 4.6278552e-08 | AU12: 4.1814457e-08 | AV12: 2.9670227e-06 | AW12: 1.3116577e-06 | AX12: 3.0271673e-07 | AY12: 8.3974465e-08 | AZ12: 1.4198294e-07 | BA12: 1.7621826e-07 | BB12: 1.5996427e-08 | BC12: 8.8459272e-07 | BD12: 3.2029004e-08 | BE12: 1.3954906e-05 | BF12: 1.5047394e-07 | BG12: 2.2255965e-07 | BH12: 2.1057822e-07 | BI12: 4.246137e-08 | BJ12: 2.8163952e-07 | BK12: 2.5449646e-07 | BL12: 4.2019814e-08 | BM12: 7.2814146e-07 | BN12: 5.4587254e-07 | BO12: 5.738151e-08 | BP12: 4.5579749e-07 | BQ12: 0
